Workbook

Sheet NDDP NDVA
A1: revenue and expenditure | B1: Sr. No. | C1: District | D1: Crops | E1: Livestock | F1: Forestry and Logging | G1: Fishing and aquaculture | H1: Agriculture & Allied Activities | I1: Minign & Quarrying | J1: Primary Sector | K1: Manufacturing | L1: Electricity, Gas, Water Supply & Other Utility Services | M1: Construction | N1: Secondary Sector | O1: Industry | P1: Trade, Repair, Hotels & Restaurants | Q1: Railways | R1: Transport by means other than Railways | S1: Storage | T1: Comm. and services related to Broad. | U1: Financial Services | V1: R. Estate, O. Dwellings & Professional Services | W1: Public Admini- stration & Defence | X1: Other Services | Y1: Services/ Tertiary Sector | Z1: NDVA | AA1: Taxes on products | AB1: Less subsidies on products | AC1: NDDP | AD1: Popula- tion ('000) | AE1: Per capita District Domestic Product ( )
A2: 2011 | B2: 10 | C2: Ahmednagar | D2: 6042 | E2: 3513 | F2: 578 | G2: 14 | H2: 10147 | I2: 179 | J2: 10326 | K2: 5841 | L2: 509 | M2: 2170 | N2: 8521 | O2: 8700 | P2: 2770 | Q2: 145 | R2: 1011 | S2: 22 | T2: 364 | U2: 3276 | V2: 3985 | W2: 786 | X2: 1650 | Y2: 14009 | Z2: 32856 | AA2: 5376 | AB2: 867 | AC2: 37365 | AD2: 4565 | AE2: 81842
A3: 2012 | B3: 10 | C3: Ahmednagar | D3: 5023 | E3: 3632 | F3: 578 | G3: 8 | H3: 9242 | I3: 418 | J3: 9661 | K3: 6163 | L3: 518 | M3: 2037 | N3: 8718 | O3: 9136 | P3: 3002 | Q3: 148 | R3: 1094 | S3: 23 | T3: 374 | U3: 3475 | V3: 4219 | W3: 783 | X3: 1780 | Y3: 14897 | Z3: 33276 | AA3: 5668 | AB3: 1043 | AC3: 37901 | AD3: 4604 | AE3: 82327
A4: 2013 | B4: 10 | C4: Ahmednagar | D4: 6486 | E4: 4278 | F4: 555 | G4: 15 | H4: 11334 | I4: 93 | J4: 11427 | K4: 6955 | L4: 398 | M4: 2081 | N4: 9433 | O4: 9527 | P4: 2930 | Q4: 150 | R4: 1115 | S4: 23 | T4: 377 | U4: 3943 | V4: 4656 | W4: 797 | X4: 1963 | Y4: 15954 | Z4: 36815 | AA4: 6225 | AB4: 1083 | AC4: 41956 | AD4: 4642 | AE4: 90392
A5: 2014 | B5: 10 | C5: Ahmednagar | D5: 6130 | E5: 4675 | F5: 559 | G5: 15 | H5: 11380 | I5: 170 | J5: 11550 | K5: 7295 | L5: 527 | M5: 2249 | N5: 10072 | O5: 10242 | P5: 2997 | Q5: 168 | R5: 1241 | S5: 24 | T5: 432 | U5: 4231 | V5: 5201 | W5: 818 | X5: 2205 | Y5: 17317 | Z5: 38938 | AA5: 6598 | AB5: 1055 | AC5: 44481 | AD5: 4679 | AE5: 95060
A6: 2015 | B6: 10 | C6: Ahmednagar | D6: 4736 | E6: 4855 | F6: 562 | G6: 9 | H6: 10161 | I6: 241 | J6: 10402 | K6: 8223 | L6: 562 | M6: 2301 | N6: 11086 | O6: 11326 | P6: 2998 | Q6: 179 | R6: 1416 | S6: 24 | T6: 528 | U6: 4494 | V6: 5747 | W6: 871 | X6: 2441 | Y6: 18699 | Z6: 40186 | AA6: 6778 | AB6: 844 | AC6: 46121 | AD6: 4717 | AE6: 97782
A7: 2016 | B7: 10 | C7: Ahmednagar | D7: 5453 | E7: 5173 | F7: 596 | G7: 9 | H7: 11232 | I7: 91 | J7: 11324 | K7: 8960 | L7: 599 | M7: 2419 | N7: 11977 | O7: 12069 | P7: 3377 | Q7: 205 | R7: 1548 | S7: 24 | T7: 491 | U7: 4750 | V7: 6325 | W7: 944 | X7: 2723 | Y7: 20387 | Z7: 43688 | AA7: 7309 | AB7: 743 | AC7: 50254 | AD7: 4751 | AE7: 105777
A8: 2017 | B8: 10 | C8: Ahmednagar | D8: 7080 | E8: 5468 | F8: 593 | G8: 12 | H8: 13153 | I8: 23 | J8: 13176 | K8: 9722 | L8: 632 | M8: 2450 | N8: 12804 | O8: 12827 | P8: 3612 | Q8: 236 | R8: 1657 | S8: 26 | T8: 421 | U8: 4880 | V8: 6703 | W8: 1028 | X8: 2925 | Y8: 21487 | Z8: 47467 | AA8: 8127 | AB8: 720 | AC8: 54874 | AD8: 4783 | AE8: 114733
A9: 2018 | B9: 10 | C9: Ahmednagar | D9: 6264 | E9: 6033 | F9: 619 | G9: 13 | H9: 12929 | I9: 25 | J9: 12954 | K9: 10255 | L9: 697 | M9: 2466 | N9: 13418 | O9: 13443 | P9: 3903 | Q9: 227 | R9: 1769 | S9: 26 | T9: 413 | U9: 5096 | V9: 7344 | W9: 1059 | X9: 3163 | Y9: 22999 | Z9: 49372 | AA9: 8795 | AB9: 754 | AC9: 57413 | AD9: 4814 | AE9: 119254
A10: 2019 | B10: 10 | C10: Ahmednagar | D10: 5671 | E10: 6303 | F10: 615 | G10: 19 | H10: 12609 | I10: 301 | J10: 12910 | K10: 9982 | L10: 725 | M10: 2466 | N10: 13173 | O10: 13474 | P10: 4078 | Q10: 233 | R10: 1871 | S10: 27 | T10: 459 | U10: 5221 | V10: 7868 | W10: 1233 | X10: 3452 | Y10: 24442 | Z10: 50525 | AA10: 8936 | AB10: 816 | AC10: 58645 | AD10: 4846 | AE10: 121024
A11: 2011 | B11: 25 | C11: Akola | D11: 1734 | E11: 234 | F11: 144 | G11: 13 | H11: 2125 | I11: 75 | J11: 2200 | K11: 2365 | L11: 206 | M11: 879 | N11: 3450 | O11: 3525 | P11: 1122 | Q11: 59 | R11: 409 | S11: 9 | T11: 147 | U11: 1326 | V11: 1614 | W11: 318 | X11: 668 | Y11: 5673 | Z11: 11323 | AA11: 1853 | AB11: 299 | AC11: 12877 | AD11: 1825 | AE11: 70551
A12: 2012 | B12: 25 | C12: Akola | D12: 2131 | E12: 245 | F12: 140 | G12: 13 | H12: 2530 | I12: 86 | J12: 2616 | K12: 2521 | L12: 212 | M12: 833 | N12: 3566 | O12: 3652 | P12: 1228 | Q12: 61 | R12: 447 | S12: 9 | T12: 153 | U12: 1422 | V12: 1726 | W12: 320 | X12: 728 | Y12: 6094 | Z12: 12276 | AA12: 2090 | AB12: 385 | AC12: 13982 | AD12: 1845 | AE12: 75801
A13: 2013 | B13: 25 | C13: Akola | D13: 2179 | E13: 281 | F13: 132 | G13: 21 | H13: 2613 | I13: 145 | J13: 2758 | K13: 2788 | L13: 159 | M13: 834 | N13: 3781 | O13: 3926 | P13: 1174 | Q13: 60 | R13: 447 | S13: 9 | T13: 151 | U13: 1580 | V13: 1866 | W13: 319 | X13: 787 | Y13: 6394 | Z13: 12933 | AA13: 2187 | AB13: 381 | AC13: 14740 | AD13: 1864 | AE13: 79081
... A307: 2019 | B307: 28 | C307: Yavatmal | D307: 2704 | E307: 502 | F307: 920 | G307: 44 | H307: 4169 | I307: 818 | J307: 4987 | K307: 4238 | L307: 308 | M307: 1047 | N307: 5592 | O307: 6411 | P307: 1731 | Q307: 99 | R307: 794 | S307: 12 | T307: 195 | U307: 2217 | V307: 3340 | W307: 524 | X307: 1466 | Y307: 10377 | Z307: 20957 | AA307: 3703 | AB307: 338 | AC307: 24322 | AD307: 2961 | AE307: 82132

Sheet GDDP GDVA
A1: Financial Year | B1: Sr. No. | C1: District | D1: Crops | E1: Livestock | F1: Forestry and Logging | G1: Fishing and aquaculture | H1: Agriculture & Allied Activities | I1: Minign & Quarrying | J1: Primary Sector | K1: Manufacturing | L1: Electricity, Gas, Water Supply & Other Utility Services | M1: Construction | N1: Secondary Sector | O1: Industry | P1: Trade, Repair, Hotels & Restaurants | Q1: Railways | R1: Transport by means other than Railways | S1: Storage | T1: Comm. and services related to Broad. | U1: Financial Services | V1: R. Estate, O. Dwellings & Professional Services | W1: Public Admini- stration & Defence | X1: Other Services | Y1: Services/ Tertiary Sector | Z1: GDVA | AA1: Taxes on products | AB1: Less subsidies on products | AC1: GDDP | AD1: Popula- tion ('000) | AE1: Per capita District Domestic Product ( )
A2: 2011 | B2: 10 | C2: Ahmednagar | D2: 6405 | E2: 3563 | F2: 584 | G2: 16 | H2: 10568 | I2: 204 | J2: 10772 | K2: 6938 | L2: 756 | M2: 2271 | N2: 9965 | O2: 10169 | P2: 2978 | Q2: 169 | R2: 1176 | S2: 26 | T2: 448 | U2: 3323 | V2: 5382 | W2: 1102 | X2: 1879 | Y2: 16482 | Z2: 37219 | AA2: 5271 | AB2: 850 | AC2: 41640 | AD2: 4565 | AE2: 91207
A3: 2012 | B3: 10 | C3: Ahmednagar | D3: 5349 | E3: 3686 | F3: 584 | G3: 9 | H3: 9629 | I3: 473 | J3: 10102 | K3: 7380 | L3: 781 | M3: 2149 | N3: 10310 | O3: 10783 | P3: 3239 | Q3: 172 | R3: 1272 | S3: 26 | T3: 462 | U3: 3532 | V3: 5738 | W3: 1104 | X3: 2013 | Y3: 17557 | Z3: 37969 | AA3: 5569 | AB3: 1025 | AC3: 42513 | AD3: 4604 | AE3: 92346
A4: 2013 | B4: 10 | C4: Ahmednagar | D4: 6868 | E4: 4343 | F4: 561 | G4: 17 | H4: 11788 | I4: 109 | J4: 11897 | K4: 8125 | L4: 748 | M4: 2233 | N4: 11106 | O4: 11214 | P4: 3195 | Q4: 178 | R4: 1320 | S4: 28 | T4: 522 | U4: 4007 | V4: 6400 | W4: 1132 | X4: 2215 | Y4: 18997 | Z4: 42000 | AA4: 6092 | AB4: 1060 | AC4: 47032 | AD4: 4642 | AE4: 101328
A5: 2014 | B5: 10 | C5: Ahmednagar | D5: 6593 | E5: 4746 | F5: 564 | G5: 18 | H5: 11921 | I5: 198 | J5: 12120 | K5: 8515 | L5: 855 | M5: 2403 | N5: 11773 | O5: 11972 | P5: 3290 | Q5: 201 | R5: 1453 | S5: 29 | T5: 574 | U5: 4307 | V5: 7193 | W5: 1157 | X5: 2469 | Y5: 20672 | Z5: 44565 | AA5: 6461 | AB5: 1033 | AC5: 49993 | AD5: 4679 | AE5: 106840
A6: 2015 | B6: 10 | C6: Ahmednagar | D6: 5139 | E6: 4927 | F6: 566 | G6: 10 | H6: 10641 | I6: 253 | J6: 10894 | K6: 9430 | L6: 895 | M6: 2447 | N6: 12773 | O6: 13025 | P6: 3303 | Q6: 215 | R6: 1621 | S6: 29 | T6: 680 | U6: 4567 | V6: 7856 | W6: 1215 | X6: 2704 | Y6: 22192 | Z6: 45858 | AA6: 6666 | AB6: 830 | AC6: 51695 | AD6: 4717 | AE6: 109599
A7: 2016 | B7: 10 | C7: Ahmednagar | D7: 5834 | E7: 5245 | F7: 602 | G7: 11 | H7: 11693 | I7: 95 | J7: 11787 | K7: 10096 | L7: 925 | M7: 2586 | N7: 13607 | O7: 13702 | P7: 3718 | Q7: 246 | R7: 1765 | S7: 29 | T7: 660 | U7: 4830 | V7: 8612 | W7: 1308 | X7: 3014 | Y7: 24182 | Z7: 49577 | AA7: 7193 | AB7: 731 | AC7: 56039 | AD7: 4751 | AE7: 117954
A8: 2017 | B8: 10 | C8: Ahmednagar | D8: 7629 | E8: 5540 | F8: 599 | G8: 14 | H8: 13781 | I8: 24 | J8: 13805 | K8: 10924 | L8: 1024 | M8: 2637 | N8: 14585 | O8: 14608 | P8: 4021 | Q8: 281 | R8: 1917 | S8: 31 | T8: 623 | U8: 4961 | V8: 9083 | W8: 1393 | X8: 3264 | Y8: 25574 | Z8: 53964 | AA8: 7984 | AB8: 707 | AC8: 61240 | AD8: 4783 | AE8: 128044
A9: 2018 | B9: 10 | C9: Ahmednagar | D9: 6799 | E9: 6105 | F9: 625 | G9: 15 | H9: 13545 | I9: 26 | J9: 13571 | K9: 11520 | L9: 1103 | M9: 2677 | N9: 15300 | O9: 15326 | P9: 4352 | Q9: 277 | R9: 2066 | S9: 32 | T9: 646 | U9: 5192 | V9: 9869 | W9: 1440 | X9: 3530 | Y9: 27404 | Z9: 56275 | AA9: 8645 | AB9: 741 | AC9: 64179 | AD9: 4814 | AE9: 133307
A10: 2019 | B10: 10 | C10: Ahmednagar | D10: 6156 | E10: 6379 | F10: 621 | G10: 22 | H10: 13178 | I10: 309 | J10: 13487 | K10: 11234 | L10: 1149 | M10: 2681 | N10: 15064 | O10: 15373 | P10: 4556 | Q10: 285 | R10: 2188 | S10: 33 | T10: 720 | U10: 5328 | V10: 10593 | W10: 1680 | X10: 3859 | Y10: 29243 | Z10: 57794 | AA10: 8789 | AB10: 802 | AC10: 65780 | AD10: 4846 | AE10: 135749
A11: 2011 | B11: 25 | C11: Akola | D11: 1838 | E11: 238 | F11: 145 | G11: 15 | H11: 2236 | I11: 85 | J11: 2321 | K11: 2809 | L11: 306 | M11: 920 | N11: 4035 | O11: 4120 | P11: 1206 | Q11: 68 | R11: 476 | S11: 11 | T11: 181 | U11: 1345 | V11: 2179 | W11: 446 | X11: 761 | Y11: 6674 | Z11: 13030 | AA11: 1846 | AB11: 298 | AC11: 14578 | AD11: 1825 | AE11: 79873
A12: 2012 | B12: 25 | C12: Akola | D12: 2269 | E12: 249 | F12: 142 | G12: 15 | H12: 2675 | I12: 97 | J12: 2772 | K12: 3018 | L12: 319 | M12: 879 | N12: 4216 | O12: 4313 | P12: 1324 | Q12: 70 | R12: 520 | S12: 11 | T12: 189 | U12: 1445 | V12: 2346 | W12: 451 | X12: 823 | Y12: 7180 | Z12: 14168 | AA12: 2077 | AB12: 382 | AC12: 15863 | AD12: 1845 | AE12: 86000
A13: 2013 | B13: 25 | C13: Akola | D13: 2307 | E13: 285 | F13: 134 | G13: 24 | H13: 2750 | I13: 168 | J13: 2918 | K13: 3257 | L13: 300 | M13: 895 | N13: 4452 | O13: 4620 | P13: 1281 | Q13: 71 | R13: 529 | S13: 11 | T13: 209 | U13: 1606 | V13: 2566 | W13: 454 | X13: 888 | Y13: 7615 | Z13: 14985 | AA13: 2174 | AB13: 378 | AC13: 16781 | AD13: 1864 | AE13: 90033
... A307: 2019 | B307: 28 | C307: Yavatmal | D307: 2935 | E307: 508 | F307: 929 | G307: 50 | H307: 4421 | I307: 841 | J307: 5262 | K307: 4791 | L307: 490 | M307: 1144 | N307: 6424 | O307: 7265 | P307: 1943 | Q307: 122 | R307: 933 | S307: 14 | T307: 307 | U307: 2272 | V307: 4518 | W307: 716 | X307: 1646 | Y307: 12471 | Z307: 24158 | AA307: 3672 | AB307: 335 | AC307: 27494 | AD307: 2961 | AE307: 92846

Sheet Gram Panchayat Income & Expendi
A1: Year | B1: District | C1: Land and other property taxes | D1: Other taxes and charges | E1: Total Tax | F1: Government Grants | G1: Contribution, donations and other grants | H1: Total grants and contributions | I1: Other deposits | J1: Total Income | K1: Administration | L1: Health and Hygiene | M1: Public Works | N1: Public Lighting | O1: Education | P1: Public Welfare | Q1: Other Expenses | R1: Total Expenditure
A2: 2009 | B2: Ahmadnagar | C2: 868 | D2: 1287 | E2: 2155 | F2: 2505 | G2: 1867 | H2: 4372 | I2: 1090 | J2: 7617 | K2: 2687 | L2: 1612 | M2: 1792 | N2: 203 | O2: 38 | P2: 19 | Q2: 15 | R2: 6366
A3: 2010 | B3: Ahmadnagar | C3: 1738 | D3: 837 | E3: 2575 | F3: 2302 | G3: 2172 | H3: 4474 | I3: 68 | J3: 7117 | K3: 2212 | L3: 1820 | M3: 1960 | N3: 296 | O3: 235 | P3: 66 | Q3: 16 | R3: 6605
A4: 2011 | B4: Ahmadnagar | C4: 1125 | D4: 1576 | E4: 2701 | F4: 4561 | G4: 2759 | H4: 7320 | I4: 61 | J4: 10082 | K4: 2767 | L4: 2111 | M4: 2996 | N4: 336 | O4: 246 | P4: 28 | Q4: 58 | R4: 8543
A5: 2012 | B5: Ahmadnagar | C5: 2005 | D5: 1970 | E5: 3975 | F5: 5437 | G5: 3141 | H5: 8578 | I5: 945 | J5: 13498 | K5: 4198 | L5: 3646 | M5: 2738 | N5: 484 | O5: 679 | P5: 443 | Q5: 583 | R5: 12770
A6: 2013 | B6: Ahmadnagar | C6: 2315 | D6: 2537 | E6: 4852 | F6: 4494 | G6: 3031 | H6: 7525 | I6: 1 | J6: 12378 | K6: 3864 | L6: 2911 | M6: 4006 | N6: 451 | O6: 390 | P6: 40 | Q6: 96 | R6: 11758
A7: 2014 | B7: Ahmadnagar | C7: 2680 | D7: 2526 | E7: 5206 | F7: 4911 | G7: 4141 | H7: 9052 | I7: 2 | J7: 14260 | K7: 4577 | L7: 3225 | M7: 3766 | N7: 455 | O7: 564 | P7: 149 | Q7: 428 | R7: 13164
A8: 2015 | B8: Ahmadnagar | C8: 1801 | D8: 2382 | E8: 4183 | F8: 3340 | G8: 3460 | H8: 6800 | I8: 2 | J8: 10985 | K8: 4759 | L8: 3038 | M8: 3475 | N8: 500 | O8: 492 | P8: 181 | Q8: 20 | R8: 12465
A9: 2016 | B9: Ahmadnagar | C9: 2857 | D9: 2676 | E9: 5533 | F9: 2867 | G9: 3685 | H9: 6552 | I9: 85 | J9: 12170 | K9: 4177 | L9: 3169 | M9: 3169 | N9: 458 | O9: 422 | P9: 200 | Q9: 16 | R9: 11612
A10: 2017 | B10: Ahmadnagar | C10: 3206 | D10: 2730 | E10: 5936 | F10: 2921 | G10: 3218 | H10: 6139 | I10: 102 | J10: 12176 | K10: 4548 | L10: 3187 | M10: 3142 | N10: 477 | O10: 463 | P10: 208 | Q10: 23 | R10: 12047
A11: 2018 | B11: Ahmadnagar | C11: 3178 | D11: 1041 | E11: 4219 | F11: 4227 | G11: 3286 | H11: 7513 | I11: 112 | J11: 11844 | K11: 3575 | L11: 1977 | M11: 3307 | N11: 544 | O11: 475 | P11: 357 | Q11: 264 | R11: 10498
A12: 2019 | B12: Ahmadnagar | C12: 2777 | D12: 2489 | E12: 5267 | F12: 5256 | G12: 2425 | H12: 7681 | I12: 96 | J12: 13044 | K12: 3704 | L12: 3792 | M12: 5158 | N12: 524 | O12: 442 | P12: 348 | Q12: 65 | R12: 14032
A13: 2020 | B13: Ahmadnagar | C13: 2921 | D13: 2614 | E13: 5535 | F13: 5522 | G13: 2552 | H13: 8074 | I13: 102 | J13: 13711 | K13: 3891 | L13: 3985 | M13: 5418 | N13: 555 | O13: 466 | P13: 368 | Q13: 71 | R13: 14754
... A259: 2017 | B259: Washim | C259: 1245 | D259: 186 | E259: 1431 | F259: 10113 | G259: 196 | H259: 10309 | I259: 516 | J259: 12256 | K259: 601 | L259: 290 | M259: 8711 | N259: 146 | O259: 6 | P259: 114 | Q259: 1425 | R259: 11292
A260: 2018 | B260: Washim
A261: 2019 | B261: Washim | C261: 1157 | D261: 249 | E261: 1406 | F261: 10403 | G261: 60 | H261: 10463 | I261: 839 | J261: 12708 | K261: 507 | L261: 354 | M261: 4657 | N261: 1044 | O261: 12 | P261: 141 | Q261: 2496 | R261: 9212
A262: 2020 | B262: Washim | C262: 798 | D262: 437 | E262: 1235 | F262: 6132 | G262: 1285 | H262: 7418 | I262: 1603 | J262: 10255 | K262: 728 | L262: 331 | M262: 4155 | N262: 87 | O262: 17 | P262: 77 | Q262: 752 | R262: 6148
A263: 2021 | B263: Washim | C263: 1360 | D263: 524 | E263: 1883 | F263: 7119 | G263: 72 | H263: 7191 | I263: 659 | J263: 9733 | K263: 291 | L263: 443 | M263: 3573 | N263: 1803 | O263: 25 | P263: 123 | Q263: 3210 | R263: 9469
A264: 2012 | B264: Yavatmal | C264: 1055 | D264: 112 | E264: 1167 | F264: 2086 | G264: 497 | H264: 2583 | I264: 930 | J264: 4680 | K264: 475 | L264: 495 | M264: 340 | N264: 456 | O264: 521 | P264: 282 | Q264: 707 | R264: 3276
A265: 2013 | B265: Yavatmal | C265: 2921 | D265: 415 | E265: 3336 | F265: 4694 | G265: 1299 | H265: 5993 | I265: 1921 | J265: 11250 | K265: 1166 | L265: 1717 | M265: 4171 | N265: 842 | O265: 357 | P265: 277 | Q265: 2993 | R265: 11522
A266: 2014 | B266: Yavatmal | C266: 2191 | D266: 515 | E266: 2706 | F266: 2426 | G266: 1378 | H266: 3804 | I266: 276 | J266: 6786 | K266: 669 | L266: 1142 | M266: 2250 | N266: 944 | O266: 150 | P266: 389 | Q266: 940 | R266: 6483
A267: 2015 | B267: Yavatmal | C267: 1247 | D267: 641 | E267: 1887 | F267: 4793 | G267: 1235 | H267: 6028 | I267: 1779 | J267: 9694 | K267: 1306 | L267: 1633 | M267: 3241 | N267: 399 | O267: 344 | P267: 240 | Q267: 924 | R267: 8087
A268: 2016 | B268: Yavatmal | C268: 4587 | D268: 325 | E268: 4911 | F268: 8179 | G268: 2330 | H268: 10510 | I268: 376 | J268: 15797 | K268: 1913 | L268: 1986 | M268: 5592 | N268: 736 | O268: 316 | P268: 564 | Q268: 2516 | R268: 13622
A269: 2017 | B269: Yavatmal | C269: 1092 | D269: 1898 | E269: 2990 | F269: 11001 | G269: 2543 | H269: 13543 | I269: 2064 | J269: 18598 | K269: 1576 | L269: 3094 | M269: 2250 | N269: 522 | O269: 857 | P269: 182 | Q269: 8654 | R269: 17135
A270: 2018 | B270: Yavatmal | C270: 1873 | D270: 1129 | E270: 3002 | F270: 13353 | G270: 1221 | H270: 14574 | I270: 508 | J270: 18085 | K270: 1209 | L270: 2545 | M270: 4855 | N270: 1069 | O270: 1735 | P270: 2252 | Q270: 2884 | R270: 16549
A271: 2019 | B271: Yavatmal | C271: 2000 | D271: 1148 | E271: 3148 | F271: 18465 | G271: 506 | H271: 18971 | I271: 1442 | J271: 23562 | K271: 1094 | L271: 2655 | M271: 8239 | N271: 372 | O271: 2409 | P271: 277 | Q271: 14501 | R271: 29546
A272: 2020 | B272: Yavatmal | C272: 2333 | D272: 1488 | E272: 3821 | F272: 12563 | G272: 764 | H272: 13327 | I272: 915 | J272: 18063 | K272: 1321 | L272: 2550 | M272: 5104 | N272: 740 | O272: 1142 | P272: 526 | Q272: 5198 | R272: 16580
... A349: 2021 | B349: Kolhapur | C349: 7345 | D349: 3540 | E349: 10885 | F349: 4040 | G349: 2458 | H349: 6498 | I349: 3825 | J349: 21208 | K349: 6475 | L349: 3455 | M349: 3335 | N349: 646 | O349: 64 | P349: 991 | Q349: 4433 | R349: 19398

Sheet Clean Jilla Parishad Income and
A1: District | B1: Year | C1: Opening Balance | D1: Revenue from self-made tools | E1: Government subsidies | F1: Purposive grants | G1: Establishment grants | H1: Grants for Plan Scheme | I1: Other Statutory grants | J1: For Agency Schemes | K1: Total Grants | L1: Other sources of income | M1: Capital receipts | N1: Total receipts | O1: Total Income (C+M) | P1: General Administration | Q1: Education | R1: Public Works | S1: Irrigation | T1: Agriculture | U1: Animal Husbandary | V1: Forests | W1: Public Health | X1: Social Welfare | Y1: Other Expenses | Z1: Total Revenue Expenditure | AA1: Capital Expenditure | AB1: Total Expenses
A2: Ahmadnagar | B2: =IF('Jilla Parishad Income & Expendi'!B2="", "", VALUE(SUBSTITUTE('Jilla Parishad Income & Expendi'!B2, ",", ""))) -> 2012 | C2: =IF('Jilla Parishad Income & Expendi'!C2="", "", VALUE(SUBSTITUTE('Jilla Parishad Income & Expendi'!C2, ",", ""))) -> 22558 | D2: =IF('Jilla Parishad Income & Expendi'!D2="", "", VALUE(SUBSTITUTE('Jilla Parishad Income & Expendi'!D2, ",", ""))) -> 215 | E2: =IF('Jilla Parishad Income & Expendi'!E2="", "", VALUE(SUBSTITUTE('Jilla Parishad Income & Expendi'!E2, ",", ""))) | F2: =IF('Jilla Parishad Income & Expendi'!F2="", "", VALUE(SUBSTITUTE('Jilla Parishad Income & Expendi'!F2, ",", ""))) -> 79949 | G2: =IF('Jilla Parishad Income & Expendi'!G2="", "", VALUE(SUBSTITUTE('Jilla Parishad Income & Expendi'!G2, ",", ""))) -> 11644 | H2: =IF('Jilla Parishad Income & Expendi'!H2="", "", VALUE(SUBSTITUTE('Jilla Parishad Income & Expendi'!H2, ",", ""))) -> 25133 | I2: =IF('Jilla Parishad Income & Expendi'!I2="", "", VALUE(SUBSTITUTE('Jilla Parishad Income & Expendi'!I2, ",", ""))) -> 0 | J2: =IF('Jilla Parishad Income & Expendi'!J2="", "", VALUE(SUBSTITUTE('Jilla Parishad Income & Expendi'!J2, ",", ""))) -> 82 | K2: =SUM(F2:J2) -> 116808 | L2: =IF('Jilla Parishad Income & Expendi'!K2="", "", VALUE(SUBSTITUTE('Jilla Parishad Income & Expendi'!K2, ",", ""))) -> 1045 | M2: =IF('Jilla Parishad Income & Expendi'!L2="", "", VALUE(SUBSTITUTE('Jilla Parishad Income & Expendi'!L2, ",", ""))) -> 3221 | N2: =IF('Jilla Parishad Income & Expendi'!M2="", "", VALUE(SUBSTITUTE('Jilla Parishad Income & Expendi'!M2, ",", ""))) -> 121289 | O2: =IF('Jilla Parishad Income & Expendi'!N2="", "", VALUE(SUBSTITUTE('Jilla Parishad Income & Expendi'!N2, ",", ""))) -> 143847 | P2: =IF('Jilla Parishad Income & Expendi'!O2="", "", VALUE(SUBSTITUTE('Jilla Parishad Income & Expendi'!O2, ",", ""))) -> 6686 | Q2: =IF('Jilla Parishad Income & Expendi'!P2="", "", VALUE(SUBSTITUTE('Jilla Parishad Income & Expendi'!P2, ",", ""))) -> 49386 | R2: =IF('Jilla Parishad Income & Expendi'!Q2="", "", VALUE(SUBSTITUTE('Jilla Parishad Income & Expendi'!Q2, ",", ""))) -> 6692 | S2: =IF('Jilla Parishad Income & Expendi'!R2="", "", VALUE(SUBSTITUTE('Jilla Parishad Income & Expendi'!R2, ",", ""))) -> 1945 | ... AD2: =IF('Jilla Parishad Income & Expendi'!AC2="", "", VALUE(SUBSTITUTE('Jilla Parishad Income & Expendi'!AC2, ",", "")))
A3: Ahmadnagar | B3: =IF('Jilla Parishad Income & Expendi'!B3="", "", VALUE(SUBSTITUTE('Jilla Parishad Income & Expendi'!B3, ",", ""))) -> 2013 | C3: =IF('Jilla Parishad Income & Expendi'!C3="", "", VALUE(SUBSTITUTE('Jilla Parishad Income & Expendi'!C3, ",", ""))) -> 27560 | D3: =IF('Jilla Parishad Income & Expendi'!D3="", "", VALUE(SUBSTITUTE('Jilla Parishad Income & Expendi'!D3, ",", ""))) -> 5069 | E3: =IF('Jilla Parishad Income & Expendi'!E3="", "", VALUE(SUBSTITUTE('Jilla Parishad Income & Expendi'!E3, ",", ""))) | F3: =IF('Jilla Parishad Income & Expendi'!F3="", "", VALUE(SUBSTITUTE('Jilla Parishad Income & Expendi'!F3, ",", ""))) -> 75857 | G3: =IF('Jilla Parishad Income & Expendi'!G3="", "", VALUE(SUBSTITUTE('Jilla Parishad Income & Expendi'!G3, ",", ""))) -> 13757 | H3: =IF('Jilla Parishad Income & Expendi'!H3="", "", VALUE(SUBSTITUTE('Jilla Parishad Income & Expendi'!H3, ",", ""))) -> 22792 | I3: =IF('Jilla Parishad Income & Expendi'!I3="", "", VALUE(SUBSTITUTE('Jilla Parishad Income & Expendi'!I3, ",", ""))) -> 104672 | J3: =IF('Jilla Parishad Income & Expendi'!J3="", "", VALUE(SUBSTITUTE('Jilla Parishad Income & Expendi'!J3, ",", ""))) -> 8225 | K3: =SUM(F3:J3) -> 225303 | L3: =IF('Jilla Parishad Income & Expendi'!K3="", "", VALUE(SUBSTITUTE('Jilla Parishad Income & Expendi'!K3, ",", ""))) -> 0 | M3: =IF('Jilla Parishad Income & Expendi'!L3="", "", VALUE(SUBSTITUTE('Jilla Parishad Income & Expendi'!L3, ",", ""))) -> 12217 | N3: =IF('Jilla Parishad Income & Expendi'!M3="", "", VALUE(SUBSTITUTE('Jilla Parishad Income & Expendi'!M3, ",", ""))) -> 242589 | O3: =IF('Jilla Parishad Income & Expendi'!N3="", "", VALUE(SUBSTITUTE('Jilla Parishad Income & Expendi'!N3, ",", ""))) -> 270149 | P3: =IF('Jilla Parishad Income & Expendi'!O3="", "", VALUE(SUBSTITUTE('Jilla Parishad Income & Expendi'!O3, ",", ""))) -> 755.02 | Q3: =IF('Jilla Parishad Income & Expendi'!P3="", "", VALUE(SUBSTITUTE('Jilla Parishad Income & Expendi'!P3, ",", ""))) -> 54878.85 | R3: =IF('Jilla Parishad Income & Expendi'!Q3="", "", VALUE(SUBSTITUTE('Jilla Parishad Income & Expendi'!Q3, ",", ""))) -> 6710.03 | S3: =IF('Jilla Parishad Income & Expendi'!R3="", "", VALUE(SUBSTITUTE('Jilla Parishad Income & Expendi'!R3, ",", ""))) -> 2131.6 | ... AD3: =IF('Jilla Parishad Income & Expendi'!AC3="", "", VALUE(SUBSTITUTE('Jilla Parishad Income & Expendi'!AC3, ",", "")))
A4: Ahmadnagar | B4: =IF('Jilla Parishad Income & Expendi'!B4="", "", VALUE(SUBSTITUTE('Jilla Parishad Income & Expendi'!B4, ",", ""))) -> 2014 | C4: =IF('Jilla Parishad Income & Expendi'!C4="", "", VALUE(SUBSTITUTE('Jilla Parishad Income & Expendi'!C4, ",", ""))) -> 30282 | D4: =IF('Jilla Parishad Income & Expendi'!D4="", "", VALUE(SUBSTITUTE('Jilla Parishad Income & Expendi'!D4, ",", ""))) -> 12775 | E4: =IF('Jilla Parishad Income & Expendi'!E4="", "", VALUE(SUBSTITUTE('Jilla Parishad Income & Expendi'!E4, ",", ""))) | F4: =IF('Jilla Parishad Income & Expendi'!F4="", "", VALUE(SUBSTITUTE('Jilla Parishad Income & Expendi'!F4, ",", ""))) -> 88311 | G4: =IF('Jilla Parishad Income & Expendi'!G4="", "", VALUE(SUBSTITUTE('Jilla Parishad Income & Expendi'!G4, ",", ""))) -> 13970 | H4: =IF('Jilla Parishad Income & Expendi'!H4="", "", VALUE(SUBSTITUTE('Jilla Parishad Income & Expendi'!H4, ",", ""))) -> 27567 | I4: =IF('Jilla Parishad Income & Expendi'!I4="", "", VALUE(SUBSTITUTE('Jilla Parishad Income & Expendi'!I4, ",", ""))) -> 98665 | J4: =IF('Jilla Parishad Income & Expendi'!J4="", "", VALUE(SUBSTITUTE('Jilla Parishad Income & Expendi'!J4, ",", ""))) -> 8806 | K4: =SUM(F4:J4) -> 237319 | L4: =IF('Jilla Parishad Income & Expendi'!K4="", "", VALUE(SUBSTITUTE('Jilla Parishad Income & Expendi'!K4, ",", ""))) -> 0 | M4: =IF('Jilla Parishad Income & Expendi'!L4="", "", VALUE(SUBSTITUTE('Jilla Parishad Income & Expendi'!L4, ",", ""))) -> 59226 | N4: =IF('Jilla Parishad Income & Expendi'!M4="", "", VALUE(SUBSTITUTE('Jilla Parishad Income & Expendi'!M4, ",", ""))) -> 309320 | O4: =IF('Jilla Parishad Income & Expendi'!N4="", "", VALUE(SUBSTITUTE('Jilla Parishad Income & Expendi'!N4, ",", ""))) -> 339602 | P4: =IF('Jilla Parishad Income & Expendi'!O4="", "", VALUE(SUBSTITUTE('Jilla Parishad Income & Expendi'!O4, ",", ""))) -> 7915.09 | Q4: =IF('Jilla Parishad Income & Expendi'!P4="", "", VALUE(SUBSTITUTE('Jilla Parishad Income & Expendi'!P4, ",", ""))) -> 60334.78 | R4: =IF('Jilla Parishad Income & Expendi'!Q4="", "", VALUE(SUBSTITUTE('Jilla Parishad Income & Expendi'!Q4, ",", ""))) -> 6860.52 | S4: =IF('Jilla Parishad Income & Expendi'!R4="", "", VALUE(SUBSTITUTE('Jilla Parishad Income & Expendi'!R4, ",", ""))) -> 1798.22 | ... AD4: =IF('Jilla Parishad Income & Expendi'!AC4="", "", VALUE(SUBSTITUTE('Jilla Parishad Income & Expendi'!AC4, ",", "")))
A5: Ahmadnagar | B5: =IF('Jilla Parishad Income & Expendi'!B5="", "", VALUE(SUBSTITUTE('Jilla Parishad Income & Expendi'!B5, ",", ""))) -> 2015 | C5: =IF('Jilla Parishad Income & Expendi'!C5="", "", VALUE(SUBSTITUTE('Jilla Parishad Income & Expendi'!C5, ",", ""))) -> 32661 | D5: =IF('Jilla Parishad Income & Expendi'!D5="", "", VALUE(SUBSTITUTE('Jilla Parishad Income & Expendi'!D5, ",", ""))) -> 6378 | E5: =IF('Jilla Parishad Income & Expendi'!E5="", "", VALUE(SUBSTITUTE('Jilla Parishad Income & Expendi'!E5, ",", ""))) | F5: =IF('Jilla Parishad Income & Expendi'!F5="", "", VALUE(SUBSTITUTE('Jilla Parishad Income & Expendi'!F5, ",", ""))) -> 97717 | G5: =IF('Jilla Parishad Income & Expendi'!G5="", "", VALUE(SUBSTITUTE('Jilla Parishad Income & Expendi'!G5, ",", ""))) -> 21646 | H5: =IF('Jilla Parishad Income & Expendi'!H5="", "", VALUE(SUBSTITUTE('Jilla Parishad Income & Expendi'!H5, ",", ""))) -> 30176 | I5: =IF('Jilla Parishad Income & Expendi'!I5="", "", VALUE(SUBSTITUTE('Jilla Parishad Income & Expendi'!I5, ",", ""))) -> 30625 | J5: =IF('Jilla Parishad Income & Expendi'!J5="", "", VALUE(SUBSTITUTE('Jilla Parishad Income & Expendi'!J5, ",", ""))) -> 13357 | K5: =SUM(F5:J5) -> 193521 | L5: =IF('Jilla Parishad Income & Expendi'!K5="", "", VALUE(SUBSTITUTE('Jilla Parishad Income & Expendi'!K5, ",", ""))) -> 0 | M5: =IF('Jilla Parishad Income & Expendi'!L5="", "", VALUE(SUBSTITUTE('Jilla Parishad Income & Expendi'!L5, ",", ""))) -> 52095 | N5: =IF('Jilla Parishad Income & Expendi'!M5="", "", VALUE(SUBSTITUTE('Jilla Parishad Income & Expendi'!M5, ",", ""))) -> 251995 | O5: =IF('Jilla Parishad Income & Expendi'!N5="", "", VALUE(SUBSTITUTE('Jilla Parishad Income & Expendi'!N5, ",", ""))) -> 284655 | P5: =IF('Jilla Parishad Income & Expendi'!O5="", "", VALUE(SUBSTITUTE('Jilla Parishad Income & Expendi'!O5, ",", ""))) -> 13803.81 | Q5: =IF('Jilla Parishad Income & Expendi'!P5="", "", VALUE(SUBSTITUTE('Jilla Parishad Income & Expendi'!P5, ",", ""))) -> 81040.09 | R5: =IF('Jilla Parishad Income & Expendi'!Q5="", "", VALUE(SUBSTITUTE('Jilla Parishad Income & Expendi'!Q5, ",", ""))) -> 6213.06 | S5: =IF('Jilla Parishad Income & Expendi'!R5="", "", VALUE(SUBSTITUTE('Jilla Parishad Income & Expendi'!R5, ",", ""))) -> 602.65 | ... AD5: =IF('Jilla Parishad Income & Expendi'!AC5="", "", VALUE(SUBSTITUTE('Jilla Parishad Income & Expendi'!AC5, ",", "")))
A6: Ahmadnagar | B6: =IF('Jilla Parishad Income & Expendi'!B6="", "", VALUE(SUBSTITUTE('Jilla Parishad Income & Expendi'!B6, ",", ""))) -> 2016 | C6: =IF('Jilla Parishad Income & Expendi'!C6="", "", VALUE(SUBSTITUTE('Jilla Parishad Income & Expendi'!C6, ",", ""))) -> 38745 | D6: =IF('Jilla Parishad Income & Expendi'!D6="", "", VALUE(SUBSTITUTE('Jilla Parishad Income & Expendi'!D6, ",", ""))) -> 5419 | E6: =IF('Jilla Parishad Income & Expendi'!E6="", "", VALUE(SUBSTITUTE('Jilla Parishad Income & Expendi'!E6, ",", ""))) | F6: =IF('Jilla Parishad Income & Expendi'!F6="", "", VALUE(SUBSTITUTE('Jilla Parishad Income & Expendi'!F6, ",", ""))) -> 107363 | G6: =IF('Jilla Parishad Income & Expendi'!G6="", "", VALUE(SUBSTITUTE('Jilla Parishad Income & Expendi'!G6, ",", ""))) -> 17545 | H6: =IF('Jilla Parishad Income & Expendi'!H6="", "", VALUE(SUBSTITUTE('Jilla Parishad Income & Expendi'!H6, ",", ""))) -> 29623 | I6: =IF('Jilla Parishad Income & Expendi'!I6="", "", VALUE(SUBSTITUTE('Jilla Parishad Income & Expendi'!I6, ",", ""))) -> 0 | J6: =IF('Jilla Parishad Income & Expendi'!J6="", "", VALUE(SUBSTITUTE('Jilla Parishad Income & Expendi'!J6, ",", ""))) -> 10069 | K6: =SUM(F6:J6) -> 164600 | L6: =IF('Jilla Parishad Income & Expendi'!K6="", "", VALUE(SUBSTITUTE('Jilla Parishad Income & Expendi'!K6, ",", ""))) -> 92201 | M6: =IF('Jilla Parishad Income & Expendi'!L6="", "", VALUE(SUBSTITUTE('Jilla Parishad Income & Expendi'!L6, ",", ""))) -> 11512 | N6: =IF('Jilla Parishad Income & Expendi'!M6="", "", VALUE(SUBSTITUTE('Jilla Parishad Income & Expendi'!M6, ",", ""))) -> 273730 | O6: =IF('Jilla Parishad Income & Expendi'!N6="", "", VALUE(SUBSTITUTE('Jilla Parishad Income & Expendi'!N6, ",", ""))) -> 312474 | P6: =IF('Jilla Parishad Income & Expendi'!O6="", "", VALUE(SUBSTITUTE('Jilla Parishad Income & Expendi'!O6, ",", ""))) -> 15516.1 | Q6: =IF('Jilla Parishad Income & Expendi'!P6="", "", VALUE(SUBSTITUTE('Jilla Parishad Income & Expendi'!P6, ",", ""))) -> 85281.57 | R6: =IF('Jilla Parishad Income & Expendi'!Q6="", "", VALUE(SUBSTITUTE('Jilla Parishad Income & Expendi'!Q6, ",", ""))) -> 5531.07 | S6: =IF('Jilla Parishad Income & Expendi'!R6="", "", VALUE(SUBSTITUTE('Jilla Parishad Income & Expendi'!R6, ",", ""))) -> 812.41 | ... AD6: =IF('Jilla Parishad Income & Expendi'!AC6="", "", VALUE(SUBSTITUTE('Jilla Parishad Income & Expendi'!AC6, ",", "")))
A7: Ahmadnagar | B7: =IF('Jilla Parishad Income & Expendi'!B7="", "", VALUE(SUBSTITUTE('Jilla Parishad Income & Expendi'!B7, ",", ""))) -> 2017 | C7: =IF('Jilla Parishad Income & Expendi'!C7="", "", VALUE(SUBSTITUTE('Jilla Parishad Income & Expendi'!C7, ",", ""))) -> 40707 | D7: =IF('Jilla Parishad Income & Expendi'!D7="", "", VALUE(SUBSTITUTE('Jilla Parishad Income & Expendi'!D7, ",", ""))) -> 2767 | E7: =IF('Jilla Parishad Income & Expendi'!E7="", "", VALUE(SUBSTITUTE('Jilla Parishad Income & Expendi'!E7, ",", ""))) | F7: =IF('Jilla Parishad Income & Expendi'!F7="", "", VALUE(SUBSTITUTE('Jilla Parishad Income & Expendi'!F7, ",", ""))) -> 39733 | G7: =IF('Jilla Parishad Income & Expendi'!G7="", "", VALUE(SUBSTITUTE('Jilla Parishad Income & Expendi'!G7, ",", ""))) -> 17347 | H7: =IF('Jilla Parishad Income & Expendi'!H7="", "", VALUE(SUBSTITUTE('Jilla Parishad Income & Expendi'!H7, ",", ""))) -> 110296 | I7: =IF('Jilla Parishad Income & Expendi'!I7="", "", VALUE(SUBSTITUTE('Jilla Parishad Income & Expendi'!I7, ",", ""))) -> 0 | J7: =IF('Jilla Parishad Income & Expendi'!J7="", "", VALUE(SUBSTITUTE('Jilla Parishad Income & Expendi'!J7, ",", ""))) -> 5567 | K7: =SUM(F7:J7) -> 172943 | L7: =IF('Jilla Parishad Income & Expendi'!K7="", "", VALUE(SUBSTITUTE('Jilla Parishad Income & Expendi'!K7, ",", ""))) -> 70330 | M7: =IF('Jilla Parishad Income & Expendi'!L7="", "", VALUE(SUBSTITUTE('Jilla Parishad Income & Expendi'!L7, ",", ""))) -> 16051 | N7: =IF('Jilla Parishad Income & Expendi'!M7="", "", VALUE(SUBSTITUTE('Jilla Parishad Income & Expendi'!M7, ",", ""))) -> 262090 | O7: =IF('Jilla Parishad Income & Expendi'!N7="", "", VALUE(SUBSTITUTE('Jilla Parishad Income & Expendi'!N7, ",", ""))) -> 302797 | P7: =IF('Jilla Parishad Income & Expendi'!O7="", "", VALUE(SUBSTITUTE('Jilla Parishad Income & Expendi'!O7, ",", ""))) -> 15278.95 | Q7: =IF('Jilla Parishad Income & Expendi'!P7="", "", VALUE(SUBSTITUTE('Jilla Parishad Income & Expendi'!P7, ",", ""))) -> 89993.68 | R7: =IF('Jilla Parishad Income & Expendi'!Q7="", "", VALUE(SUBSTITUTE('Jilla Parishad Income & Expendi'!Q7, ",", ""))) -> 1908.22 | S7: =IF('Jilla Parishad Income & Expendi'!R7="", "", VALUE(SUBSTITUTE('Jilla Parishad Income & Expendi'!R7, ",", ""))) -> 911.33 | ... AD7: =IF('Jilla Parishad Income & Expendi'!AC7="", "", VALUE(SUBSTITUTE('Jilla Parishad Income & Expendi'!AC7, ",", "")))
A8: Ahmadnagar | B8: =IF('Jilla Parishad Income & Expendi'!B8="", "", VALUE(SUBSTITUTE('Jilla Parishad Income & Expendi'!B8, ",", ""))) -> 2018 | C8: =IF('Jilla Parishad Income & Expendi'!C8="", "", VALUE(SUBSTITUTE('Jilla Parishad Income & Expendi'!C8, ",", ""))) -> 46861 | D8: =IF('Jilla Parishad Income & Expendi'!D8="", "", VALUE(SUBSTITUTE('Jilla Parishad Income & Expendi'!D8, ",", ""))) -> 2994 | E8: =IF('Jilla Parishad Income & Expendi'!E8="", "", VALUE(SUBSTITUTE('Jilla Parishad Income & Expendi'!E8, ",", ""))) | F8: =IF('Jilla Parishad Income & Expendi'!F8="", "", VALUE(SUBSTITUTE('Jilla Parishad Income & Expendi'!F8, ",", ""))) -> 30528 | G8: =IF('Jilla Parishad Income & Expendi'!G8="", "", VALUE(SUBSTITUTE('Jilla Parishad Income & Expendi'!G8, ",", ""))) -> 18328 | H8: =IF('Jilla Parishad Income & Expendi'!H8="", "", VALUE(SUBSTITUTE('Jilla Parishad Income & Expendi'!H8, ",", ""))) -> 120617 | I8: =IF('Jilla Parishad Income & Expendi'!I8="", "", VALUE(SUBSTITUTE('Jilla Parishad Income & Expendi'!I8, ",", ""))) -> 0 | J8: =IF('Jilla Parishad Income & Expendi'!J8="", "", VALUE(SUBSTITUTE('Jilla Parishad Income & Expendi'!J8, ",", ""))) -> 7570 | K8: =SUM(F8:J8) -> 177043 | L8: =IF('Jilla Parishad Income & Expendi'!K8="", "", VALUE(SUBSTITUTE('Jilla Parishad Income & Expendi'!K8, ",", ""))) -> 53018 | M8: =IF('Jilla Parishad Income & Expendi'!L8="", "", VALUE(SUBSTITUTE('Jilla Parishad Income & Expendi'!L8, ",", ""))) -> 71772 | N8: =IF('Jilla Parishad Income & Expendi'!M8="", "", VALUE(SUBSTITUTE('Jilla Parishad Income & Expendi'!M8, ",", ""))) -> 304826 | O8: =IF('Jilla Parishad Income & Expendi'!N8="", "", VALUE(SUBSTITUTE('Jilla Parishad Income & Expendi'!N8, ",", ""))) -> 351687 | P8: =IF('Jilla Parishad Income & Expendi'!O8="", "", VALUE(SUBSTITUTE('Jilla Parishad Income & Expendi'!O8, ",", ""))) -> 18498.86 | Q8: =IF('Jilla Parishad Income & Expendi'!P8="", "", VALUE(SUBSTITUTE('Jilla Parishad Income & Expendi'!P8, ",", ""))) -> 95606.74 | R8: =IF('Jilla Parishad Income & Expendi'!Q8="", "", VALUE(SUBSTITUTE('Jilla Parishad Income & Expendi'!Q8, ",", ""))) -> 6472.43 | S8: =IF('Jilla Parishad Income & Expendi'!R8="", "", VALUE(SUBSTITUTE('Jilla Parishad Income & Expendi'!R8, ",", ""))) -> 3670.21 | ... AD8: =IF('Jilla Parishad Income & Expendi'!AC8="", "", VALUE(SUBSTITUTE('Jilla Parishad Income & Expendi'!AC8, ",", "")))
A9: Ahmadnagar | B9: =IF('Jilla Parishad Income & Expendi'!B9="", "", VALUE(SUBSTITUTE('Jilla Parishad Income & Expendi'!B9, ",", ""))) -> 2019 | C9: =IF('Jilla Parishad Income & Expendi'!C9="", "", VALUE(SUBSTITUTE('Jilla Parishad Income & Expendi'!C9, ",", ""))) -> 46861 | D9: =IF('Jilla Parishad Income & Expendi'!D9="", "", VALUE(SUBSTITUTE('Jilla Parishad Income & Expendi'!D9, ",", ""))) -> 2165 | E9: =IF('Jilla Parishad Income & Expendi'!E9="", "", VALUE(SUBSTITUTE('Jilla Parishad Income & Expendi'!E9, ",", ""))) | F9: =IF('Jilla Parishad Income & Expendi'!F9="", "", VALUE(SUBSTITUTE('Jilla Parishad Income & Expendi'!F9, ",", ""))) -> 28757 | G9: =IF('Jilla Parishad Income & Expendi'!G9="", "", VALUE(SUBSTITUTE('Jilla Parishad Income & Expendi'!G9, ",", ""))) -> 24892 | H9: =IF('Jilla Parishad Income & Expendi'!H9="", "", VALUE(SUBSTITUTE('Jilla Parishad Income & Expendi'!H9, ",", ""))) -> 166370 | I9: =IF('Jilla Parishad Income & Expendi'!I9="", "", VALUE(SUBSTITUTE('Jilla Parishad Income & Expendi'!I9, ",", ""))) -> 0 | J9: =IF('Jilla Parishad Income & Expendi'!J9="", "", VALUE(SUBSTITUTE('Jilla Parishad Income & Expendi'!J9, ",", ""))) -> 8956 | K9: =SUM(F9:J9) -> 228975 | L9: =IF('Jilla Parishad Income & Expendi'!K9="", "", VALUE(SUBSTITUTE('Jilla Parishad Income & Expendi'!K9, ",", ""))) -> 58248 | M9: =IF('Jilla Parishad Income & Expendi'!L9="", "", VALUE(SUBSTITUTE('Jilla Parishad Income & Expendi'!L9, ",", ""))) -> 50566 | N9: =IF('Jilla Parishad Income & Expendi'!M9="", "", VALUE(SUBSTITUTE('Jilla Parishad Income & Expendi'!M9, ",", ""))) -> 339954 | O9: =IF('Jilla Parishad Income & Expendi'!N9="", "", VALUE(SUBSTITUTE('Jilla Parishad Income & Expendi'!N9, ",", ""))) -> 386815 | P9: =IF('Jilla Parishad Income & Expendi'!O9="", "", VALUE(SUBSTITUTE('Jilla Parishad Income & Expendi'!O9, ",", ""))) -> 24180.49 | Q9: =IF('Jilla Parishad Income & Expendi'!P9="", "", VALUE(SUBSTITUTE('Jilla Parishad Income & Expendi'!P9, ",", ""))) -> 122784.95 | R9: =IF('Jilla Parishad Income & Expendi'!Q9="", "", VALUE(SUBSTITUTE('Jilla Parishad Income & Expendi'!Q9, ",", ""))) -> 9489.65 | S9: =IF('Jilla Parishad Income & Expendi'!R9="", "", VALUE(SUBSTITUTE('Jilla Parishad Income & Expendi'!R9, ",", ""))) -> 4062.07 | ... AD9: =IF('Jilla Parishad Income & Expendi'!AC9="", "", VALUE(SUBSTITUTE('Jilla Parishad Income & Expendi'!AC9, ",", "")))
A10: Ahmadnagar | B10: =IF('Jilla Parishad Income & Expendi'!B10="", "", VALUE(SUBSTITUTE('Jilla Parishad Income & Expendi'!B10, ",", ""))) -> 2020 | C10: =IF('Jilla Parishad Income & Expendi'!C10="", "", VALUE(SUBSTITUTE('Jilla Parishad Income & Expendi'!C10, ",", ""))) -> 45711 | D10: =IF('Jilla Parishad Income & Expendi'!D10="", "", VALUE(SUBSTITUTE('Jilla Parishad Income & Expendi'!D10, ",", ""))) -> 3247 | E10: =IF('Jilla Parishad Income & Expendi'!E10="", "", VALUE(SUBSTITUTE('Jilla Parishad Income & Expendi'!E10, ",", ""))) | F10: =IF('Jilla Parishad Income & Expendi'!F10="", "", VALUE(SUBSTITUTE('Jilla Parishad Income & Expendi'!F10, ",", ""))) -> 34450 | G10: =IF('Jilla Parishad Income & Expendi'!G10="", "", VALUE(SUBSTITUTE('Jilla Parishad Income & Expendi'!G10, ",", ""))) -> 122385 | H10: =IF('Jilla Parishad Income & Expendi'!H10="", "", VALUE(SUBSTITUTE('Jilla Parishad Income & Expendi'!H10, ",", ""))) -> 57698 | I10: =IF('Jilla Parishad Income & Expendi'!I10="", "", VALUE(SUBSTITUTE('Jilla Parishad Income & Expendi'!I10, ",", ""))) -> 0 | J10: =IF('Jilla Parishad Income & Expendi'!J10="", "", VALUE(SUBSTITUTE('Jilla Parishad Income & Expendi'!J10, ",", ""))) -> 9071 | K10: =SUM(F10:J10) -> 223604 | L10: =IF('Jilla Parishad Income & Expendi'!K10="", "", VALUE(SUBSTITUTE('Jilla Parishad Income & Expendi'!K10, ",", ""))) -> 49700 | M10: =IF('Jilla Parishad Income & Expendi'!L10="", "", VALUE(SUBSTITUTE('Jilla Parishad Income & Expendi'!L10, ",", ""))) -> 49881 | N10: =IF('Jilla Parishad Income & Expendi'!M10="", "", VALUE(SUBSTITUTE('Jilla Parishad Income & Expendi'!M10, ",", ""))) -> 326433 | O10: =IF('Jilla Parishad Income & Expendi'!N10="", "", VALUE(SUBSTITUTE('Jilla Parishad Income & Expendi'!N10, ",", ""))) -> 372144 | P10: =IF('Jilla Parishad Income & Expendi'!O10="", "", VALUE(SUBSTITUTE('Jilla Parishad Income & Expendi'!O10, ",", ""))) -> 20813.44 | Q10: =IF('Jilla Parishad Income & Expendi'!P10="", "", VALUE(SUBSTITUTE('Jilla Parishad Income & Expendi'!P10, ",", ""))) -> 117956.45 | R10: =IF('Jilla Parishad Income & Expendi'!Q10="", "", VALUE(SUBSTITUTE('Jilla Parishad Income & Expendi'!Q10, ",", ""))) -> 5810.9 | S10: =IF('Jilla Parishad Income & Expendi'!R10="", "", VALUE(SUBSTITUTE('Jilla Parishad Income & Expendi'!R10, ",", ""))) -> 1908.84 | ... AD10: =IF('Jilla Parishad Income & Expendi'!AC10="", "", VALUE(SUBSTITUTE('Jilla Parishad Income & Expendi'!AC10, ",", "")))
A11: Akola | B11: =IF('Jilla Parishad Income & Expendi'!B11="", "", VALUE(SUBSTITUTE('Jilla Parishad Income & Expendi'!B11, ",", ""))) -> 2012 | C11: =IF('Jilla Parishad Income & Expendi'!C11="", "", VALUE(SUBSTITUTE('Jilla Parishad Income & Expendi'!C11, ",", ""))) -> 10988.41 | D11: =IF('Jilla Parishad Income & Expendi'!D11="", "", VALUE(SUBSTITUTE('Jilla Parishad Income & Expendi'!D11, ",", ""))) -> 0 | E11: =IF('Jilla Parishad Income & Expendi'!E11="", "", VALUE(SUBSTITUTE('Jilla Parishad Income & Expendi'!E11, ",", ""))) | F11: =IF('Jilla Parishad Income & Expendi'!F11="", "", VALUE(SUBSTITUTE('Jilla Parishad Income & Expendi'!F11, ",", ""))) -> 27017.6 | G11: =IF('Jilla Parishad Income & Expendi'!G11="", "", VALUE(SUBSTITUTE('Jilla Parishad Income & Expendi'!G11, ",", ""))) -> 4726.93 | H11: =IF('Jilla Parishad Income & Expendi'!H11="", "", VALUE(SUBSTITUTE('Jilla Parishad Income & Expendi'!H11, ",", ""))) -> 12999.99 | I11: =IF('Jilla Parishad Income & Expendi'!I11="", "", VALUE(SUBSTITUTE('Jilla Parishad Income & Expendi'!I11, ",", ""))) -> 179.36 | J11: =IF('Jilla Parishad Income & Expendi'!J11="", "", VALUE(SUBSTITUTE('Jilla Parishad Income & Expendi'!J11, ",", ""))) -> 2613.12 | K11: =SUM(F11:J11) -> 47537 | L11: =IF('Jilla Parishad Income & Expendi'!K11="", "", VALUE(SUBSTITUTE('Jilla Parishad Income & Expendi'!K11, ",", ""))) -> 0 | M11: =IF('Jilla Parishad Income & Expendi'!L11="", "", VALUE(SUBSTITUTE('Jilla Parishad Income & Expendi'!L11, ",", ""))) -> 50063.4 | N11: =IF('Jilla Parishad Income & Expendi'!M11="", "", VALUE(SUBSTITUTE('Jilla Parishad Income & Expendi'!M11, ",", ""))) -> 97600 | O11: =IF('Jilla Parishad Income & Expendi'!N11="", "", VALUE(SUBSTITUTE('Jilla Parishad Income & Expendi'!N11, ",", ""))) -> 108589 | P11: =IF('Jilla Parishad Income & Expendi'!O11="", "", VALUE(SUBSTITUTE('Jilla Parishad Income & Expendi'!O11, ",", ""))) -> 1976.1 | Q11: =IF('Jilla Parishad Income & Expendi'!P11="", "", VALUE(SUBSTITUTE('Jilla Parishad Income & Expendi'!P11, ",", ""))) -> 24250.41 | R11: =IF('Jilla Parishad Income & Expendi'!Q11="", "", VALUE(SUBSTITUTE('Jilla Parishad Income & Expendi'!Q11, ",", ""))) -> 2540.9 | S11: =IF('Jilla Parishad Income & Expendi'!R11="", "", VALUE(SUBSTITUTE('Jilla Parishad Income & Expendi'!R11, ",", ""))) -> 601.23 | ... AD11: =IF('Jilla Parishad Income & Expendi'!AC11="", "", VALUE(SUBSTITUTE('Jilla Parishad Income & Expendi'!AC11, ",", "")))
A12: Akola | B12: =IF('Jilla Parishad Income & Expendi'!B12="", "", VALUE(SUBSTITUTE('Jilla Parishad Income & Expendi'!B12, ",", ""))) -> 2013 | C12: =IF('Jilla Parishad Income & Expendi'!C12="", "", VALUE(SUBSTITUTE('Jilla Parishad Income & Expendi'!C12, ",", ""))) -> 13073.92 | D12: =IF('Jilla Parishad Income & Expendi'!D12="", "", VALUE(SUBSTITUTE('Jilla Parishad Income & Expendi'!D12, ",", ""))) -> 3920.53 | E12: =IF('Jilla Parishad Income & Expendi'!E12="", "", VALUE(SUBSTITUTE('Jilla Parishad Income & Expendi'!E12, ",", ""))) | F12: =IF('Jilla Parishad Income & Expendi'!F12="", "", VALUE(SUBSTITUTE('Jilla Parishad Income & Expendi'!F12, ",", ""))) -> 28212.05 | G12: =IF('Jilla Parishad Income & Expendi'!G12="", "", VALUE(SUBSTITUTE('Jilla Parishad Income & Expendi'!G12, ",", ""))) -> 5062.06 | H12: =IF('Jilla Parishad Income & Expendi'!H12="", "", VALUE(SUBSTITUTE('Jilla Parishad Income & Expendi'!H12, ",", ""))) -> 11451.46 | I12: =IF('Jilla Parishad Income & Expendi'!I12="", "", VALUE(SUBSTITUTE('Jilla Parishad Income & Expendi'!I12, ",", ""))) -> 11.36 | J12: =IF('Jilla Parishad Income & Expendi'!J12="", "", VALUE(SUBSTITUTE('Jilla Parishad Income & Expendi'!J12, ",", ""))) -> 2680.86 | K12: =SUM(F12:J12) -> 47417.79 | L12: =IF('Jilla Parishad Income & Expendi'!K12="", "", VALUE(SUBSTITUTE('Jilla Parishad Income & Expendi'!K12, ",", ""))) -> 131.13 | M12: =IF('Jilla Parishad Income & Expendi'!L12="", "", VALUE(SUBSTITUTE('Jilla Parishad Income & Expendi'!L12, ",", ""))) -> 49579.17 | N12: =IF('Jilla Parishad Income & Expendi'!M12="", "", VALUE(SUBSTITUTE('Jilla Parishad Income & Expendi'!M12, ",", ""))) -> 101049 | O12: =IF('Jilla Parishad Income & Expendi'!N12="", "", VALUE(SUBSTITUTE('Jilla Parishad Income & Expendi'!N12, ",", ""))) -> 114123 | P12: =IF('Jilla Parishad Income & Expendi'!O12="", "", VALUE(SUBSTITUTE('Jilla Parishad Income & Expendi'!O12, ",", ""))) -> 2230.21 | Q12: =IF('Jilla Parishad Income & Expendi'!P12="", "", VALUE(SUBSTITUTE('Jilla Parishad Income & Expendi'!P12, ",", ""))) -> 25881.29 | R12: =IF('Jilla Parishad Income & Expendi'!Q12="", "", VALUE(SUBSTITUTE('Jilla Parishad Income & Expendi'!Q12, ",", ""))) -> 2155.08 | S12: =IF('Jilla Parishad Income & Expendi'!R12="", "", VALUE(SUBSTITUTE('Jilla Parishad Income & Expendi'!R12, ",", ""))) -> 416 | ... AD12: =IF('Jilla Parishad Income & Expendi'!AC12="", "", VALUE(SUBSTITUTE('Jilla Parishad Income & Expendi'!AC12, ",", "")))
A13: Akola | B13: =IF('Jilla Parishad Income & Expendi'!B13="", "", VALUE(SUBSTITUTE('Jilla Parishad Income & Expendi'!B13, ",", ""))) -> 2014 | C13: =IF('Jilla Parishad Income & Expendi'!C13="", "", VALUE(SUBSTITUTE('Jilla Parishad Income & Expendi'!C13, ",", ""))) -> 19039.92 | D13: =IF('Jilla Parishad Income & Expendi'!D13="", "", VALUE(SUBSTITUTE('Jilla Parishad Income & Expendi'!D13, ",", ""))) -> 3948.69 | E13: =IF('Jilla Parishad Income & Expendi'!E13="", "", VALUE(SUBSTITUTE('Jilla Parishad Income & Expendi'!E13, ",", ""))) | F13: =IF('Jilla Parishad Income & Expendi'!F13="", "", VALUE(SUBSTITUTE('Jilla Parishad Income & Expendi'!F13, ",", ""))) -> 27867.28 | G13: =IF('Jilla Parishad Income & Expendi'!G13="", "", VALUE(SUBSTITUTE('Jilla Parishad Income & Expendi'!G13, ",", ""))) -> 9175.73 | H13: =IF('Jilla Parishad Income & Expendi'!H13="", "", VALUE(SUBSTITUTE('Jilla Parishad Income & Expendi'!H13, ",", ""))) -> 13058.25 | I13: =IF('Jilla Parishad Income & Expendi'!I13="", "", VALUE(SUBSTITUTE('Jilla Parishad Income & Expendi'!I13, ",", ""))) -> 45.5 | J13: =IF('Jilla Parishad Income & Expendi'!J13="", "", VALUE(SUBSTITUTE('Jilla Parishad Income & Expendi'!J13, ",", ""))) -> 3738.17 | K13: =SUM(F13:J13) -> 53884.93 | L13: =IF('Jilla Parishad Income & Expendi'!K13="", "", VALUE(SUBSTITUTE('Jilla Parishad Income & Expendi'!K13, ",", ""))) -> 0 | M13: =IF('Jilla Parishad Income & Expendi'!L13="", "", VALUE(SUBSTITUTE('Jilla Parishad Income & Expendi'!L13, ",", ""))) -> 51549.49 | N13: =IF('Jilla Parishad Income & Expendi'!M13="", "", VALUE(SUBSTITUTE('Jilla Parishad Income & Expendi'!M13, ",", ""))) -> 109383 | O13: =IF('Jilla Parishad Income & Expendi'!N13="", "", VALUE(SUBSTITUTE('Jilla Parishad Income & Expendi'!N13, ",", ""))) -> 128423 | P13: =IF('Jilla Parishad Income & Expendi'!O13="", "", VALUE(SUBSTITUTE('Jilla Parishad Income & Expendi'!O13, ",", ""))) -> 5564.49 | Q13: =IF('Jilla Parishad Income & Expendi'!P13="", "", VALUE(SUBSTITUTE('Jilla Parishad Income & Expendi'!P13, ",", ""))) -> 26948.05 | R13: =IF('Jilla Parishad Income & Expendi'!Q13="", "", VALUE(SUBSTITUTE('Jilla Parishad Income & Expendi'!Q13, ",", ""))) -> 3428.23 | S13: =IF('Jilla Parishad Income & Expendi'!R13="", "", VALUE(SUBSTITUTE('Jilla Parishad Income & Expendi'!R13, ",", ""))) -> 935.49 | ... AD13: =IF('Jilla Parishad Income & Expendi'!AC13="", "", VALUE(SUBSTITUTE('Jilla Parishad Income & Expendi'!AC13, ",", "")))
... A30: Amravati | B30: =IF('Jilla Parishad Income & Expendi'!B30="", "", VALUE(SUBSTITUTE('Jilla Parishad Income & Expendi'!B30, ",", ""))) -> 2021 | C30: =IF('Jilla Parishad Income & Expendi'!C30="", "", VALUE(SUBSTITUTE('Jilla Parishad Income & Expendi'!C30, ",", ""))) -> 48658.07 | D30: =IF('Jilla Parishad Income & Expendi'!D30="", "", VALUE(SUBSTITUTE('Jilla Parishad Income & Expendi'!D30, ",", ""))) -> 1843.65 | E30: =IF('Jilla Parishad Income & Expendi'!E30="", "", VALUE(SUBSTITUTE('Jilla Parishad Income & Expendi'!E30, ",", ""))) | F30: =IF('Jilla Parishad Income & Expendi'!F30="", "", VALUE(SUBSTITUTE('Jilla Parishad Income & Expendi'!F30, ",", ""))) -> 0 | G30: =IF('Jilla Parishad Income & Expendi'!G30="", "", VALUE(SUBSTITUTE('Jilla Parishad Income & Expendi'!G30, ",", ""))) -> 111488.48 | H30: =IF('Jilla Parishad Income & Expendi'!H30="", "", VALUE(SUBSTITUTE('Jilla Parishad Income & Expendi'!H30, ",", ""))) -> 29389.98 | I30: =IF('Jilla Parishad Income & Expendi'!I30="", "", VALUE(SUBSTITUTE('Jilla Parishad Income & Expendi'!I30, ",", ""))) -> 0 | J30: =IF('Jilla Parishad Income & Expendi'!J30="", "", VALUE(SUBSTITUTE('Jilla Parishad Income & Expendi'!J30, ",", ""))) -> 7981.36 | K30: =SUM(F30:J30) -> 148859.82 | L30: =IF('Jilla Parishad Income & Expendi'!K30="", "", VALUE(SUBSTITUTE('Jilla Parishad Income & Expendi'!K30, ",", ""))) -> 0 | M30: =IF('Jilla Parishad Income & Expendi'!L30="", "", VALUE(SUBSTITUTE('Jilla Parishad Income & Expendi'!L30, ",", ""))) -> 1862.14 | N30: =IF('Jilla Parishad Income & Expendi'!M30="", "", VALUE(SUBSTITUTE('Jilla Parishad Income & Expendi'!M30, ",", ""))) -> 152566 | O30: =IF('Jilla Parishad Income & Expendi'!N30="", "", VALUE(SUBSTITUTE('Jilla Parishad Income & Expendi'!N30, ",", ""))) -> 201224 | P30: =IF('Jilla Parishad Income & Expendi'!O30="", "", VALUE(SUBSTITUTE('Jilla Parishad Income & Expendi'!O30, ",", ""))) -> 309.1 | Q30: =IF('Jilla Parishad Income & Expendi'!P30="", "", VALUE(SUBSTITUTE('Jilla Parishad Income & Expendi'!P30, ",", ""))) -> 75026.73 | R30: =IF('Jilla Parishad Income & Expendi'!Q30="", "", VALUE(SUBSTITUTE('Jilla Parishad Income & Expendi'!Q30, ",", ""))) -> 13355.06 | S30: =IF('Jilla Parishad Income & Expendi'!R30="", "", VALUE(SUBSTITUTE('Jilla Parishad Income & Expendi'!R30, ",", ""))) -> 1250.16 | ... AD30: =IF('Jilla Parishad Income & Expendi'!AC30="", "", VALUE(SUBSTITUTE('Jilla Parishad Income & Expendi'!AC30, ",", "")))
A31: Bhandara | B31: =IF('Jilla Parishad Income & Expendi'!B31="", "", VALUE(SUBSTITUTE('Jilla Parishad Income & Expendi'!B31, ",", ""))) -> 2012 | C31: =IF('Jilla Parishad Income & Expendi'!C31="", "", VALUE(SUBSTITUTE('Jilla Parishad Income & Expendi'!C31, ",", ""))) -> 13642 | D31: =IF('Jilla Parishad Income & Expendi'!D31="", "", VALUE(SUBSTITUTE('Jilla Parishad Income & Expendi'!D31, ",", ""))) -> 0 | E31: =IF('Jilla Parishad Income & Expendi'!E31="", "", VALUE(SUBSTITUTE('Jilla Parishad Income & Expendi'!E31, ",", ""))) | F31: =IF('Jilla Parishad Income & Expendi'!F31="", "", VALUE(SUBSTITUTE('Jilla Parishad Income & Expendi'!F31, ",", ""))) -> 41775 | G31: =IF('Jilla Parishad Income & Expendi'!G31="", "", VALUE(SUBSTITUTE('Jilla Parishad Income & Expendi'!G31, ",", ""))) | H31: =IF('Jilla Parishad Income & Expendi'!H31="", "", VALUE(SUBSTITUTE('Jilla Parishad Income & Expendi'!H31, ",", ""))) | I31: =IF('Jilla Parishad Income & Expendi'!I31="", "", VALUE(SUBSTITUTE('Jilla Parishad Income & Expendi'!I31, ",", ""))) | J31: =IF('Jilla Parishad Income & Expendi'!J31="", "", VALUE(SUBSTITUTE('Jilla Parishad Income & Expendi'!J31, ",", ""))) | K31: =SUM(F31:J31) -> 41775 | L31: =IF('Jilla Parishad Income & Expendi'!K31="", "", VALUE(SUBSTITUTE('Jilla Parishad Income & Expendi'!K31, ",", ""))) -> 587 | M31: =IF('Jilla Parishad Income & Expendi'!L31="", "", VALUE(SUBSTITUTE('Jilla Parishad Income & Expendi'!L31, ",", ""))) -> 2620 | P31: =IF('Jilla Parishad Income & Expendi'!O31="", "", VALUE(SUBSTITUTE('Jilla Parishad Income & Expendi'!O31, ",", ""))) -> 1805 | Q31: =IF('Jilla Parishad Income & Expendi'!P31="", "", VALUE(SUBSTITUTE('Jilla Parishad Income & Expendi'!P31, ",", ""))) -> 19482 | R31: =IF('Jilla Parishad Income & Expendi'!Q31="", "", VALUE(SUBSTITUTE('Jilla Parishad Income & Expendi'!Q31, ",", ""))) -> 1954 | S31: =IF('Jilla Parishad Income & Expendi'!R31="", "", VALUE(SUBSTITUTE('Jilla Parishad Income & Expendi'!R31, ",", ""))) -> 1377 | T31: =IF('Jilla Parishad Income & Expendi'!S31="", "", VALUE(SUBSTITUTE('Jilla Parishad Income & Expendi'!S31, ",", ""))) -> 431 | U31: =IF('Jilla Parishad Income & Expendi'!T31="", "", VALUE(SUBSTITUTE('Jilla Parishad Income & Expendi'!T31, ",", ""))) -> 343 | V31: =IF('Jilla Parishad Income & Expendi'!U31="", "", VALUE(SUBSTITUTE('Jilla Parishad Income & Expendi'!U31, ",", ""))) -> 22 | W31: =IF('Jilla Parishad Income & Expendi'!V31="", "", VALUE(SUBSTITUTE('Jilla Parishad Income & Expendi'!V31, ",", ""))) -> 2437 | ... AD31: =IF('Jilla Parishad Income & Expendi'!AC31="", "", VALUE(SUBSTITUTE('Jilla Parishad Income & Expendi'!AC31, ",", "")))
A32: Bhandara | B32: =IF('Jilla Parishad Income & Expendi'!B32="", "", VALUE(SUBSTITUTE('Jilla Parishad Income & Expendi'!B32, ",", ""))) -> 2013 | C32: =IF('Jilla Parishad Income & Expendi'!C32="", "", VALUE(SUBSTITUTE('Jilla Parishad Income & Expendi'!C32, ",", ""))) -> 17434 | D32: =IF('Jilla Parishad Income & Expendi'!D32="", "", VALUE(SUBSTITUTE('Jilla Parishad Income & Expendi'!D32, ",", ""))) -> 0 | E32: =IF('Jilla Parishad Income & Expendi'!E32="", "", VALUE(SUBSTITUTE('Jilla Parishad Income & Expendi'!E32, ",", ""))) | F32: =IF('Jilla Parishad Income & Expendi'!F32="", "", VALUE(SUBSTITUTE('Jilla Parishad Income & Expendi'!F32, ",", ""))) -> 44957 | G32: =IF('Jilla Parishad Income & Expendi'!G32="", "", VALUE(SUBSTITUTE('Jilla Parishad Income & Expendi'!G32, ",", ""))) | H32: =IF('Jilla Parishad Income & Expendi'!H32="", "", VALUE(SUBSTITUTE('Jilla Parishad Income & Expendi'!H32, ",", ""))) | I32: =IF('Jilla Parishad Income & Expendi'!I32="", "", VALUE(SUBSTITUTE('Jilla Parishad Income & Expendi'!I32, ",", ""))) | J32: =IF('Jilla Parishad Income & Expendi'!J32="", "", VALUE(SUBSTITUTE('Jilla Parishad Income & Expendi'!J32, ",", ""))) | K32: =SUM(F32:J32) -> 44957 | L32: =IF('Jilla Parishad Income & Expendi'!K32="", "", VALUE(SUBSTITUTE('Jilla Parishad Income & Expendi'!K32, ",", ""))) -> 495 | M32: =IF('Jilla Parishad Income & Expendi'!L32="", "", VALUE(SUBSTITUTE('Jilla Parishad Income & Expendi'!L32, ",", ""))) -> 1908 | P32: =IF('Jilla Parishad Income & Expendi'!O32="", "", VALUE(SUBSTITUTE('Jilla Parishad Income & Expendi'!O32, ",", ""))) -> 4873 | Q32: =IF('Jilla Parishad Income & Expendi'!P32="", "", VALUE(SUBSTITUTE('Jilla Parishad Income & Expendi'!P32, ",", ""))) -> 23505 | R32: =IF('Jilla Parishad Income & Expendi'!Q32="", "", VALUE(SUBSTITUTE('Jilla Parishad Income & Expendi'!Q32, ",", ""))) -> 3023 | S32: =IF('Jilla Parishad Income & Expendi'!R32="", "", VALUE(SUBSTITUTE('Jilla Parishad Income & Expendi'!R32, ",", ""))) -> 1140 | T32: =IF('Jilla Parishad Income & Expendi'!S32="", "", VALUE(SUBSTITUTE('Jilla Parishad Income & Expendi'!S32, ",", ""))) -> 554 | U32: =IF('Jilla Parishad Income & Expendi'!T32="", "", VALUE(SUBSTITUTE('Jilla Parishad Income & Expendi'!T32, ",", ""))) -> 583 | V32: =IF('Jilla Parishad Income & Expendi'!U32="", "", VALUE(SUBSTITUTE('Jilla Parishad Income & Expendi'!U32, ",", ""))) -> 13 | W32: =IF('Jilla Parishad Income & Expendi'!V32="", "", VALUE(SUBSTITUTE('Jilla Parishad Income & Expendi'!V32, ",", ""))) -> 3373 | ... AD32: =IF('Jilla Parishad Income & Expendi'!AC32="", "", VALUE(SUBSTITUTE('Jilla Parishad Income & Expendi'!AC32, ",", "")))
A33: Bhandara | B33: =IF('Jilla Parishad Income & Expendi'!B33="", "", VALUE(SUBSTITUTE('Jilla Parishad Income & Expendi'!B33, ",", ""))) -> 2014 | C33: =IF('Jilla Parishad Income & Expendi'!C33="", "", VALUE(SUBSTITUTE('Jilla Parishad Income & Expendi'!C33, ",", ""))) -> 14812 | D33: =IF('Jilla Parishad Income & Expendi'!D33="", "", VALUE(SUBSTITUTE('Jilla Parishad Income & Expendi'!D33, ",", ""))) -> 0 | E33: =IF('Jilla Parishad Income & Expendi'!E33="", "", VALUE(SUBSTITUTE('Jilla Parishad Income & Expendi'!E33, ",", ""))) | F33: =IF('Jilla Parishad Income & Expendi'!F33="", "", VALUE(SUBSTITUTE('Jilla Parishad Income & Expendi'!F33, ",", ""))) -> 49800 | G33: =IF('Jilla Parishad Income & Expendi'!G33="", "", VALUE(SUBSTITUTE('Jilla Parishad Income & Expendi'!G33, ",", ""))) | H33: =IF('Jilla Parishad Income & Expendi'!H33="", "", VALUE(SUBSTITUTE('Jilla Parishad Income & Expendi'!H33, ",", ""))) | I33: =IF('Jilla Parishad Income & Expendi'!I33="", "", VALUE(SUBSTITUTE('Jilla Parishad Income & Expendi'!I33, ",", ""))) | J33: =IF('Jilla Parishad Income & Expendi'!J33="", "", VALUE(SUBSTITUTE('Jilla Parishad Income & Expendi'!J33, ",", ""))) | K33: =SUM(F33:J33) -> 49800 | L33: =IF('Jilla Parishad Income & Expendi'!K33="", "", VALUE(SUBSTITUTE('Jilla Parishad Income & Expendi'!K33, ",", ""))) -> 799 | M33: =IF('Jilla Parishad Income & Expendi'!L33="", "", VALUE(SUBSTITUTE('Jilla Parishad Income & Expendi'!L33, ",", ""))) -> 2420 | P33: =IF('Jilla Parishad Income & Expendi'!O33="", "", VALUE(SUBSTITUTE('Jilla Parishad Income & Expendi'!O33, ",", ""))) -> 5467 | Q33: =IF('Jilla Parishad Income & Expendi'!P33="", "", VALUE(SUBSTITUTE('Jilla Parishad Income & Expendi'!P33, ",", ""))) -> 24748 | R33: =IF('Jilla Parishad Income & Expendi'!Q33="", "", VALUE(SUBSTITUTE('Jilla Parishad Income & Expendi'!Q33, ",", ""))) -> 5038 | S33: =IF('Jilla Parishad Income & Expendi'!R33="", "", VALUE(SUBSTITUTE('Jilla Parishad Income & Expendi'!R33, ",", ""))) -> 814 | T33: =IF('Jilla Parishad Income & Expendi'!S33="", "", VALUE(SUBSTITUTE('Jilla Parishad Income & Expendi'!S33, ",", ""))) -> 612 | U33: =IF('Jilla Parishad Income & Expendi'!T33="", "", VALUE(SUBSTITUTE('Jilla Parishad Income & Expendi'!T33, ",", ""))) -> 579 | V33: =IF('Jilla Parishad Income & Expendi'!U33="", "", VALUE(SUBSTITUTE('Jilla Parishad Income & Expendi'!U33, ",", ""))) -> 5 | W33: =IF('Jilla Parishad Income & Expendi'!V33="", "", VALUE(SUBSTITUTE('Jilla Parishad Income & Expendi'!V33, ",", ""))) -> 4499 | ... AD33: =IF('Jilla Parishad Income & Expendi'!AC33="", "", VALUE(SUBSTITUTE('Jilla Parishad Income & Expendi'!AC33, ",", "")))
A34: Bhandara | B34: =IF('Jilla Parishad Income & Expendi'!B34="", "", VALUE(SUBSTITUTE('Jilla Parishad Income & Expendi'!B34, ",", ""))) -> 2015 | C34: =IF('Jilla Parishad Income & Expendi'!C34="", "", VALUE(SUBSTITUTE('Jilla Parishad Income & Expendi'!C34, ",", ""))) -> 13177 | D34: =IF('Jilla Parishad Income & Expendi'!D34="", "", VALUE(SUBSTITUTE('Jilla Parishad Income & Expendi'!D34, ",", ""))) -> 599 | E34: =IF('Jilla Parishad Income & Expendi'!E34="", "", VALUE(SUBSTITUTE('Jilla Parishad Income & Expendi'!E34, ",", ""))) | F34: =IF('Jilla Parishad Income & Expendi'!F34="", "", VALUE(SUBSTITUTE('Jilla Parishad Income & Expendi'!F34, ",", ""))) -> 51509 | G34: =IF('Jilla Parishad Income & Expendi'!G34="", "", VALUE(SUBSTITUTE('Jilla Parishad Income & Expendi'!G34, ",", ""))) | H34: =IF('Jilla Parishad Income & Expendi'!H34="", "", VALUE(SUBSTITUTE('Jilla Parishad Income & Expendi'!H34, ",", ""))) | I34: =IF('Jilla Parishad Income & Expendi'!I34="", "", VALUE(SUBSTITUTE('Jilla Parishad Income & Expendi'!I34, ",", ""))) | J34: =IF('Jilla Parishad Income & Expendi'!J34="", "", VALUE(SUBSTITUTE('Jilla Parishad Income & Expendi'!J34, ",", ""))) -> 2326 | K34: =SUM(F34:J34) -> 53835 | L34: =IF('Jilla Parishad Income & Expendi'!K34="", "", VALUE(SUBSTITUTE('Jilla Parishad Income & Expendi'!K34, ",", ""))) -> 374 | M34: =IF('Jilla Parishad Income & Expendi'!L34="", "", VALUE(SUBSTITUTE('Jilla Parishad Income & Expendi'!L34, ",", ""))) -> 3750 | P34: =IF('Jilla Parishad Income & Expendi'!O34="", "", VALUE(SUBSTITUTE('Jilla Parishad Income & Expendi'!O34, ",", ""))) -> 6264 | Q34: =IF('Jilla Parishad Income & Expendi'!P34="", "", VALUE(SUBSTITUTE('Jilla Parishad Income & Expendi'!P34, ",", ""))) -> 24995 | R34: =IF('Jilla Parishad Income & Expendi'!Q34="", "", VALUE(SUBSTITUTE('Jilla Parishad Income & Expendi'!Q34, ",", ""))) -> 3659 | S34: =IF('Jilla Parishad Income & Expendi'!R34="", "", VALUE(SUBSTITUTE('Jilla Parishad Income & Expendi'!R34, ",", ""))) -> 1805 | T34: =IF('Jilla Parishad Income & Expendi'!S34="", "", VALUE(SUBSTITUTE('Jilla Parishad Income & Expendi'!S34, ",", ""))) -> 601 | U34: =IF('Jilla Parishad Income & Expendi'!T34="", "", VALUE(SUBSTITUTE('Jilla Parishad Income & Expendi'!T34, ",", ""))) -> 647 | V34: =IF('Jilla Parishad Income & Expendi'!U34="", "", VALUE(SUBSTITUTE('Jilla Parishad Income & Expendi'!U34, ",", ""))) -> 8 | W34: =IF('Jilla Parishad Income & Expendi'!V34="", "", VALUE(SUBSTITUTE('Jilla Parishad Income & Expendi'!V34, ",", ""))) -> 3339 | ... AD34: =IF('Jilla Parishad Income & Expendi'!AC34="", "", VALUE(SUBSTITUTE('Jilla Parishad Income & Expendi'!AC34, ",", "")))
A35: Bhandara | B35: =IF('Jilla Parishad Income & Expendi'!B35="", "", VALUE(SUBSTITUTE('Jilla Parishad Income & Expendi'!B35, ",", ""))) -> 2016 | C35: =IF('Jilla Parishad Income & Expendi'!C35="", "", VALUE(SUBSTITUTE('Jilla Parishad Income & Expendi'!C35, ",", ""))) -> 13599 | D35: =IF('Jilla Parishad Income & Expendi'!D35="", "", VALUE(SUBSTITUTE('Jilla Parishad Income & Expendi'!D35, ",", ""))) -> 697 | E35: =IF('Jilla Parishad Income & Expendi'!E35="", "", VALUE(SUBSTITUTE('Jilla Parishad Income & Expendi'!E35, ",", ""))) | F35: =IF('Jilla Parishad Income & Expendi'!F35="", "", VALUE(SUBSTITUTE('Jilla Parishad Income & Expendi'!F35, ",", ""))) -> 54333 | G35: =IF('Jilla Parishad Income & Expendi'!G35="", "", VALUE(SUBSTITUTE('Jilla Parishad Income & Expendi'!G35, ",", ""))) | H35: =IF('Jilla Parishad Income & Expendi'!H35="", "", VALUE(SUBSTITUTE('Jilla Parishad Income & Expendi'!H35, ",", ""))) | I35: =IF('Jilla Parishad Income & Expendi'!I35="", "", VALUE(SUBSTITUTE('Jilla Parishad Income & Expendi'!I35, ",", ""))) | J35: =IF('Jilla Parishad Income & Expendi'!J35="", "", VALUE(SUBSTITUTE('Jilla Parishad Income & Expendi'!J35, ",", ""))) -> 1642 | K35: =SUM(F35:J35) -> 55975 | L35: =IF('Jilla Parishad Income & Expendi'!K35="", "", VALUE(SUBSTITUTE('Jilla Parishad Income & Expendi'!K35, ",", ""))) -> 295 | M35: =IF('Jilla Parishad Income & Expendi'!L35="", "", VALUE(SUBSTITUTE('Jilla Parishad Income & Expendi'!L35, ",", ""))) -> 3975 | P35: =IF('Jilla Parishad Income & Expendi'!O35="", "", VALUE(SUBSTITUTE('Jilla Parishad Income & Expendi'!O35, ",", ""))) -> 6938 | Q35: =IF('Jilla Parishad Income & Expendi'!P35="", "", VALUE(SUBSTITUTE('Jilla Parishad Income & Expendi'!P35, ",", ""))) -> 27887 | R35: =IF('Jilla Parishad Income & Expendi'!Q35="", "", VALUE(SUBSTITUTE('Jilla Parishad Income & Expendi'!Q35, ",", ""))) -> 3192 | S35: =IF('Jilla Parishad Income & Expendi'!R35="", "", VALUE(SUBSTITUTE('Jilla Parishad Income & Expendi'!R35, ",", ""))) -> 1249 | T35: =IF('Jilla Parishad Income & Expendi'!S35="", "", VALUE(SUBSTITUTE('Jilla Parishad Income & Expendi'!S35, ",", ""))) -> 781 | U35: =IF('Jilla Parishad Income & Expendi'!T35="", "", VALUE(SUBSTITUTE('Jilla Parishad Income & Expendi'!T35, ",", ""))) -> 647 | V35: =IF('Jilla Parishad Income & Expendi'!U35="", "", VALUE(SUBSTITUTE('Jilla Parishad Income & Expendi'!U35, ",", ""))) -> 6 | W35: =IF('Jilla Parishad Income & Expendi'!V35="", "", VALUE(SUBSTITUTE('Jilla Parishad Income & Expendi'!V35, ",", ""))) -> 3693 | ... AD35: =IF('Jilla Parishad Income & Expendi'!AC35="", "", VALUE(SUBSTITUTE('Jilla Parishad Income & Expendi'!AC35, ",", "")))
A36: Bhandara | B36: =IF('Jilla Parishad Income & Expendi'!B36="", "", VALUE(SUBSTITUTE('Jilla Parishad Income & Expendi'!B36, ",", ""))) -> 2017 | C36: =IF('Jilla Parishad Income & Expendi'!C36="", "", VALUE(SUBSTITUTE('Jilla Parishad Income & Expendi'!C36, ",", ""))) -> 17513 | D36: =IF('Jilla Parishad Income & Expendi'!D36="", "", VALUE(SUBSTITUTE('Jilla Parishad Income & Expendi'!D36, ",", ""))) -> 1061 | E36: =IF('Jilla Parishad Income & Expendi'!E36="", "", VALUE(SUBSTITUTE('Jilla Parishad Income & Expendi'!E36, ",", ""))) | F36: =IF('Jilla Parishad Income & Expendi'!F36="", "", VALUE(SUBSTITUTE('Jilla Parishad Income & Expendi'!F36, ",", ""))) -> 0 | G36: =IF('Jilla Parishad Income & Expendi'!G36="", "", VALUE(SUBSTITUTE('Jilla Parishad Income & Expendi'!G36, ",", ""))) -> 37225 | H36: =IF('Jilla Parishad Income & Expendi'!H36="", "", VALUE(SUBSTITUTE('Jilla Parishad Income & Expendi'!H36, ",", ""))) -> 17626 | I36: =IF('Jilla Parishad Income & Expendi'!I36="", "", VALUE(SUBSTITUTE('Jilla Parishad Income & Expendi'!I36, ",", ""))) -> 53 | J36: =IF('Jilla Parishad Income & Expendi'!J36="", "", VALUE(SUBSTITUTE('Jilla Parishad Income & Expendi'!J36, ",", ""))) -> 2434 | K36: =SUM(F36:J36) -> 57338 | L36: =IF('Jilla Parishad Income & Expendi'!K36="", "", VALUE(SUBSTITUTE('Jilla Parishad Income & Expendi'!K36, ",", ""))) -> 70 | M36: =IF('Jilla Parishad Income & Expendi'!L36="", "", VALUE(SUBSTITUTE('Jilla Parishad Income & Expendi'!L36, ",", ""))) -> 2751 | N36: =IF('Jilla Parishad Income & Expendi'!M36="", "", VALUE(SUBSTITUTE('Jilla Parishad Income & Expendi'!M36, ",", ""))) -> 61220 | O36: =IF('Jilla Parishad Income & Expendi'!N36="", "", VALUE(SUBSTITUTE('Jilla Parishad Income & Expendi'!N36, ",", ""))) -> 78733 | P36: =IF('Jilla Parishad Income & Expendi'!O36="", "", VALUE(SUBSTITUTE('Jilla Parishad Income & Expendi'!O36, ",", ""))) -> 6607 | Q36: =IF('Jilla Parishad Income & Expendi'!P36="", "", VALUE(SUBSTITUTE('Jilla Parishad Income & Expendi'!P36, ",", ""))) -> 29249 | R36: =IF('Jilla Parishad Income & Expendi'!Q36="", "", VALUE(SUBSTITUTE('Jilla Parishad Income & Expendi'!Q36, ",", ""))) -> 601 | S36: =IF('Jilla Parishad Income & Expendi'!R36="", "", VALUE(SUBSTITUTE('Jilla Parishad Income & Expendi'!R36, ",", ""))) -> 725 | ... AD36: =IF('Jilla Parishad Income & Expendi'!AC36="", "", VALUE(SUBSTITUTE('Jilla Parishad Income & Expendi'!AC36, ",", "")))
A37: Bhandara | B37: =IF('Jilla Parishad Income & Expendi'!B37="", "", VALUE(SUBSTITUTE('Jilla Parishad Income & Expendi'!B37, ",", ""))) -> 2018 | C37: =IF('Jilla Parishad Income & Expendi'!C37="", "", VALUE(SUBSTITUTE('Jilla Parishad Income & Expendi'!C37, ",", ""))) -> 12641 | D37: =IF('Jilla Parishad Income & Expendi'!D37="", "", VALUE(SUBSTITUTE('Jilla Parishad Income & Expendi'!D37, ",", ""))) -> 931 | E37: =IF('Jilla Parishad Income & Expendi'!E37="", "", VALUE(SUBSTITUTE('Jilla Parishad Income & Expendi'!E37, ",", ""))) | F37: =IF('Jilla Parishad Income & Expendi'!F37="", "", VALUE(SUBSTITUTE('Jilla Parishad Income & Expendi'!F37, ",", ""))) -> 0 | G37: =IF('Jilla Parishad Income & Expendi'!G37="", "", VALUE(SUBSTITUTE('Jilla Parishad Income & Expendi'!G37, ",", ""))) -> 39239 | H37: =IF('Jilla Parishad Income & Expendi'!H37="", "", VALUE(SUBSTITUTE('Jilla Parishad Income & Expendi'!H37, ",", ""))) -> 18507 | I37: =IF('Jilla Parishad Income & Expendi'!I37="", "", VALUE(SUBSTITUTE('Jilla Parishad Income & Expendi'!I37, ",", ""))) -> 56 | J37: =IF('Jilla Parishad Income & Expendi'!J37="", "", VALUE(SUBSTITUTE('Jilla Parishad Income & Expendi'!J37, ",", ""))) -> 3270 | K37: =SUM(F37:J37) -> 61072 | L37: =IF('Jilla Parishad Income & Expendi'!K37="", "", VALUE(SUBSTITUTE('Jilla Parishad Income & Expendi'!K37, ",", ""))) -> 73 | M37: =IF('Jilla Parishad Income & Expendi'!L37="", "", VALUE(SUBSTITUTE('Jilla Parishad Income & Expendi'!L37, ",", ""))) -> 3984 | N37: =IF('Jilla Parishad Income & Expendi'!M37="", "", VALUE(SUBSTITUTE('Jilla Parishad Income & Expendi'!M37, ",", ""))) -> 66060 | O37: =IF('Jilla Parishad Income & Expendi'!N37="", "", VALUE(SUBSTITUTE('Jilla Parishad Income & Expendi'!N37, ",", ""))) -> 78701 | P37: =IF('Jilla Parishad Income & Expendi'!O37="", "", VALUE(SUBSTITUTE('Jilla Parishad Income & Expendi'!O37, ",", ""))) -> 6911 | Q37: =IF('Jilla Parishad Income & Expendi'!P37="", "", VALUE(SUBSTITUTE('Jilla Parishad Income & Expendi'!P37, ",", ""))) -> 31283 | R37: =IF('Jilla Parishad Income & Expendi'!Q37="", "", VALUE(SUBSTITUTE('Jilla Parishad Income & Expendi'!Q37, ",", ""))) -> 662 | S37: =IF('Jilla Parishad Income & Expendi'!R37="", "", VALUE(SUBSTITUTE('Jilla Parishad Income & Expendi'!R37, ",", ""))) -> 785 | ... AD37: =IF('Jilla Parishad Income & Expendi'!AC37="", "", VALUE(SUBSTITUTE('Jilla Parishad Income & Expendi'!AC37, ",", "")))
A38: Bhandara | B38: =IF('Jilla Parishad Income & Expendi'!B38="", "", VALUE(SUBSTITUTE('Jilla Parishad Income & Expendi'!B38, ",", ""))) -> 2019 | C38: =IF('Jilla Parishad Income & Expendi'!C38="", "", VALUE(SUBSTITUTE('Jilla Parishad Income & Expendi'!C38, ",", ""))) -> 12947 | D38: =IF('Jilla Parishad Income & Expendi'!D38="", "", VALUE(SUBSTITUTE('Jilla Parishad Income & Expendi'!D38, ",", ""))) -> 1127 | E38: =IF('Jilla Parishad Income & Expendi'!E38="", "", VALUE(SUBSTITUTE('Jilla Parishad Income & Expendi'!E38, ",", ""))) | F38: =IF('Jilla Parishad Income & Expendi'!F38="", "", VALUE(SUBSTITUTE('Jilla Parishad Income & Expendi'!F38, ",", ""))) -> 0 | G38: =IF('Jilla Parishad Income & Expendi'!G38="", "", VALUE(SUBSTITUTE('Jilla Parishad Income & Expendi'!G38, ",", ""))) -> 46637 | H38: =IF('Jilla Parishad Income & Expendi'!H38="", "", VALUE(SUBSTITUTE('Jilla Parishad Income & Expendi'!H38, ",", ""))) -> 17983 | I38: =IF('Jilla Parishad Income & Expendi'!I38="", "", VALUE(SUBSTITUTE('Jilla Parishad Income & Expendi'!I38, ",", ""))) -> 17 | J38: =IF('Jilla Parishad Income & Expendi'!J38="", "", VALUE(SUBSTITUTE('Jilla Parishad Income & Expendi'!J38, ",", ""))) -> 3270 | K38: =SUM(F38:J38) -> 67907 | L38: =IF('Jilla Parishad Income & Expendi'!K38="", "", VALUE(SUBSTITUTE('Jilla Parishad Income & Expendi'!K38, ",", ""))) -> 0 | M38: =IF('Jilla Parishad Income & Expendi'!L38="", "", VALUE(SUBSTITUTE('Jilla Parishad Income & Expendi'!L38, ",", ""))) -> 2733 | N38: =IF('Jilla Parishad Income & Expendi'!M38="", "", VALUE(SUBSTITUTE('Jilla Parishad Income & Expendi'!M38, ",", ""))) -> 71767 | O38: =IF('Jilla Parishad Income & Expendi'!N38="", "", VALUE(SUBSTITUTE('Jilla Parishad Income & Expendi'!N38, ",", ""))) -> 84714 | P38: =IF('Jilla Parishad Income & Expendi'!O38="", "", VALUE(SUBSTITUTE('Jilla Parishad Income & Expendi'!O38, ",", ""))) -> 7322 | Q38: =IF('Jilla Parishad Income & Expendi'!P38="", "", VALUE(SUBSTITUTE('Jilla Parishad Income & Expendi'!P38, ",", ""))) -> 33061 | R38: =IF('Jilla Parishad Income & Expendi'!Q38="", "", VALUE(SUBSTITUTE('Jilla Parishad Income & Expendi'!Q38, ",", ""))) -> 785 | S38: =IF('Jilla Parishad Income & Expendi'!R38="", "", VALUE(SUBSTITUTE('Jilla Parishad Income & Expendi'!R38, ",", ""))) -> 848 | ... AD38: =IF('Jilla Parishad Income & Expendi'!AC38="", "", VALUE(SUBSTITUTE('Jilla Parishad Income & Expendi'!AC38, ",", "")))
A39: Bhandara | B39: =IF('Jilla Parishad Income & Expendi'!B39="", "", VALUE(SUBSTITUTE('Jilla Parishad Income & Expendi'!B39, ",", ""))) -> 2020 | C39: =IF('Jilla Parishad Income & Expendi'!C39="", "", VALUE(SUBSTITUTE('Jilla Parishad Income & Expendi'!C39, ",", ""))) -> 13180 | D39: =IF('Jilla Parishad Income & Expendi'!D39="", "", VALUE(SUBSTITUTE('Jilla Parishad Income & Expendi'!D39, ",", ""))) -> 878 | E39: =IF('Jilla Parishad Income & Expendi'!E39="", "", VALUE(SUBSTITUTE('Jilla Parishad Income & Expendi'!E39, ",", ""))) | F39: =IF('Jilla Parishad Income & Expendi'!F39="", "", VALUE(SUBSTITUTE('Jilla Parishad Income & Expendi'!F39, ",", ""))) -> 0 | G39: =IF('Jilla Parishad Income & Expendi'!G39="", "", VALUE(SUBSTITUTE('Jilla Parishad Income & Expendi'!G39, ",", ""))) -> 56941 | H39: =IF('Jilla Parishad Income & Expendi'!H39="", "", VALUE(SUBSTITUTE('Jilla Parishad Income & Expendi'!H39, ",", ""))) -> 17014 | I39: =IF('Jilla Parishad Income & Expendi'!I39="", "", VALUE(SUBSTITUTE('Jilla Parishad Income & Expendi'!I39, ",", ""))) -> 122 | J39: =IF('Jilla Parishad Income & Expendi'!J39="", "", VALUE(SUBSTITUTE('Jilla Parishad Income & Expendi'!J39, ",", ""))) -> 3714 | K39: =SUM(F39:J39) -> 77791 | L39: =IF('Jilla Parishad Income & Expendi'!K39="", "", VALUE(SUBSTITUTE('Jilla Parishad Income & Expendi'!K39, ",", ""))) -> 0 | M39: =IF('Jilla Parishad Income & Expendi'!L39="", "", VALUE(SUBSTITUTE('Jilla Parishad Income & Expendi'!L39, ",", ""))) -> 2190 | N39: =IF('Jilla Parishad Income & Expendi'!M39="", "", VALUE(SUBSTITUTE('Jilla Parishad Income & Expendi'!M39, ",", ""))) -> 80859 | O39: =IF('Jilla Parishad Income & Expendi'!N39="", "", VALUE(SUBSTITUTE('Jilla Parishad Income & Expendi'!N39, ",", ""))) -> 94039 | P39: =IF('Jilla Parishad Income & Expendi'!O39="", "", VALUE(SUBSTITUTE('Jilla Parishad Income & Expendi'!O39, ",", ""))) -> 11363 | Q39: =IF('Jilla Parishad Income & Expendi'!P39="", "", VALUE(SUBSTITUTE('Jilla Parishad Income & Expendi'!P39, ",", ""))) -> 41805 | R39: =IF('Jilla Parishad Income & Expendi'!Q39="", "", VALUE(SUBSTITUTE('Jilla Parishad Income & Expendi'!Q39, ",", ""))) -> 3384 | S39: =IF('Jilla Parishad Income & Expendi'!R39="", "", VALUE(SUBSTITUTE('Jilla Parishad Income & Expendi'!R39, ",", ""))) -> 509 | ... AD39: =IF('Jilla Parishad Income & Expendi'!AC39="", "", VALUE(SUBSTITUTE('Jilla Parishad Income & Expendi'!AC39, ",", "")))
A40: Bhandara | B40: =IF('Jilla Parishad Income & Expendi'!B40="", "", VALUE(SUBSTITUTE('Jilla Parishad Income & Expendi'!B40, ",", ""))) -> 2021 | C40: =IF('Jilla Parishad Income & Expendi'!C40="", "", VALUE(SUBSTITUTE('Jilla Parishad Income & Expendi'!C40, ",", ""))) -> 13415 | D40: =IF('Jilla Parishad Income & Expendi'!D40="", "", VALUE(SUBSTITUTE('Jilla Parishad Income & Expendi'!D40, ",", ""))) -> 1015 | E40: =IF('Jilla Parishad Income & Expendi'!E40="", "", VALUE(SUBSTITUTE('Jilla Parishad Income & Expendi'!E40, ",", ""))) | F40: =IF('Jilla Parishad Income & Expendi'!F40="", "", VALUE(SUBSTITUTE('Jilla Parishad Income & Expendi'!F40, ",", ""))) -> 0 | G40: =IF('Jilla Parishad Income & Expendi'!G40="", "", VALUE(SUBSTITUTE('Jilla Parishad Income & Expendi'!G40, ",", ""))) -> 48969 | H40: =IF('Jilla Parishad Income & Expendi'!H40="", "", VALUE(SUBSTITUTE('Jilla Parishad Income & Expendi'!H40, ",", ""))) -> 18702 | I40: =IF('Jilla Parishad Income & Expendi'!I40="", "", VALUE(SUBSTITUTE('Jilla Parishad Income & Expendi'!I40, ",", ""))) -> 18 | J40: =IF('Jilla Parishad Income & Expendi'!J40="", "", VALUE(SUBSTITUTE('Jilla Parishad Income & Expendi'!J40, ",", ""))) -> 3434 | K40: =SUM(F40:J40) -> 71123 | L40: =IF('Jilla Parishad Income & Expendi'!K40="", "", VALUE(SUBSTITUTE('Jilla Parishad Income & Expendi'!K40, ",", ""))) -> 0 | M40: =IF('Jilla Parishad Income & Expendi'!L40="", "", VALUE(SUBSTITUTE('Jilla Parishad Income & Expendi'!L40, ",", ""))) -> 2815 | N40: =IF('Jilla Parishad Income & Expendi'!M40="", "", VALUE(SUBSTITUTE('Jilla Parishad Income & Expendi'!M40, ",", ""))) -> 74953 | O40: =IF('Jilla Parishad Income & Expendi'!N40="", "", VALUE(SUBSTITUTE('Jilla Parishad Income & Expendi'!N40, ",", ""))) -> 88368 | P40: =IF('Jilla Parishad Income & Expendi'!O40="", "", VALUE(SUBSTITUTE('Jilla Parishad Income & Expendi'!O40, ",", ""))) -> 7688 | Q40: =IF('Jilla Parishad Income & Expendi'!P40="", "", VALUE(SUBSTITUTE('Jilla Parishad Income & Expendi'!P40, ",", ""))) -> 39439 | R40: =IF('Jilla Parishad Income & Expendi'!Q40="", "", VALUE(SUBSTITUTE('Jilla Parishad Income & Expendi'!Q40, ",", ""))) -> 1034 | S40: =IF('Jilla Parishad Income & Expendi'!R40="", "", VALUE(SUBSTITUTE('Jilla Parishad Income & Expendi'!R40, ",", ""))) -> 890 | ... AD40: =IF('Jilla Parishad Income & Expendi'!AC40="", "", VALUE(SUBSTITUTE('Jilla Parishad Income & Expendi'!AC40, ",", "")))
A41: Buldhana | B41: =IF('Jilla Parishad Income & Expendi'!B41="", "", VALUE(SUBSTITUTE('Jilla Parishad Income & Expendi'!B41, ",", ""))) -> 2013 | C41: =IF('Jilla Parishad Income & Expendi'!C41="", "", VALUE(SUBSTITUTE('Jilla Parishad Income & Expendi'!C41, ",", ""))) -> 24456 | D41: =IF('Jilla Parishad Income & Expendi'!D41="", "", VALUE(SUBSTITUTE('Jilla Parishad Income & Expendi'!D41, ",", ""))) -> 3497 | E41: =IF('Jilla Parishad Income & Expendi'!E41="", "", VALUE(SUBSTITUTE('Jilla Parishad Income & Expendi'!E41, ",", ""))) | F41: =IF('Jilla Parishad Income & Expendi'!F41="", "", VALUE(SUBSTITUTE('Jilla Parishad Income & Expendi'!F41, ",", ""))) -> 47467 | G41: =IF('Jilla Parishad Income & Expendi'!G41="", "", VALUE(SUBSTITUTE('Jilla Parishad Income & Expendi'!G41, ",", ""))) -> 8670 | H41: =IF('Jilla Parishad Income & Expendi'!H41="", "", VALUE(SUBSTITUTE('Jilla Parishad Income & Expendi'!H41, ",", ""))) -> 9248 | I41: =IF('Jilla Parishad Income & Expendi'!I41="", "", VALUE(SUBSTITUTE('Jilla Parishad Income & Expendi'!I41, ",", ""))) -> 5771 | J41: =IF('Jilla Parishad Income & Expendi'!J41="", "", VALUE(SUBSTITUTE('Jilla Parishad Income & Expendi'!J41, ",", ""))) -> 4298 | K41: =SUM(F41:J41) -> 75454 | L41: =IF('Jilla Parishad Income & Expendi'!K41="", "", VALUE(SUBSTITUTE('Jilla Parishad Income & Expendi'!K41, ",", ""))) -> 0 | M41: =IF('Jilla Parishad Income & Expendi'!L41="", "", VALUE(SUBSTITUTE('Jilla Parishad Income & Expendi'!L41, ",", ""))) -> 2132 | N41: =IF('Jilla Parishad Income & Expendi'!M41="", "", VALUE(SUBSTITUTE('Jilla Parishad Income & Expendi'!M41, ",", ""))) -> 81083 | O41: =IF('Jilla Parishad Income & Expendi'!N41="", "", VALUE(SUBSTITUTE('Jilla Parishad Income & Expendi'!N41, ",", ""))) -> 105539 | P41: =IF('Jilla Parishad Income & Expendi'!O41="", "", VALUE(SUBSTITUTE('Jilla Parishad Income & Expendi'!O41, ",", ""))) -> 7125 | Q41: =IF('Jilla Parishad Income & Expendi'!P41="", "", VALUE(SUBSTITUTE('Jilla Parishad Income & Expendi'!P41, ",", ""))) -> 44722 | R41: =IF('Jilla Parishad Income & Expendi'!Q41="", "", VALUE(SUBSTITUTE('Jilla Parishad Income & Expendi'!Q41, ",", ""))) -> 3174 | S41: =IF('Jilla Parishad Income & Expendi'!R41="", "", VALUE(SUBSTITUTE('Jilla Parishad Income & Expendi'!R41, ",", ""))) -> 999 | ... AD41: =IF('Jilla Parishad Income & Expendi'!AC41="", "", VALUE(SUBSTITUTE('Jilla Parishad Income & Expendi'!AC41, ",", "")))
A42: Buldhana | B42: =IF('Jilla Parishad Income & Expendi'!B42="", "", VALUE(SUBSTITUTE('Jilla Parishad Income & Expendi'!B42, ",", ""))) -> 2014 | C42: =IF('Jilla Parishad Income & Expendi'!C42="", "", VALUE(SUBSTITUTE('Jilla Parishad Income & Expendi'!C42, ",", ""))) -> 25586 | D42: =IF('Jilla Parishad Income & Expendi'!D42="", "", VALUE(SUBSTITUTE('Jilla Parishad Income & Expendi'!D42, ",", ""))) -> 2033 | E42: =IF('Jilla Parishad Income & Expendi'!E42="", "", VALUE(SUBSTITUTE('Jilla Parishad Income & Expendi'!E42, ",", ""))) | F42: =IF('Jilla Parishad Income & Expendi'!F42="", "", VALUE(SUBSTITUTE('Jilla Parishad Income & Expendi'!F42, ",", ""))) -> 49584 | G42: =IF('Jilla Parishad Income & Expendi'!G42="", "", VALUE(SUBSTITUTE('Jilla Parishad Income & Expendi'!G42, ",", ""))) -> 13048 | H42: =IF('Jilla Parishad Income & Expendi'!H42="", "", VALUE(SUBSTITUTE('Jilla Parishad Income & Expendi'!H42, ",", ""))) -> 12192 | I42: =IF('Jilla Parishad Income & Expendi'!I42="", "", VALUE(SUBSTITUTE('Jilla Parishad Income & Expendi'!I42, ",", ""))) -> 4697 | J42: =IF('Jilla Parishad Income & Expendi'!J42="", "", VALUE(SUBSTITUTE('Jilla Parishad Income & Expendi'!J42, ",", ""))) -> 5743 | K42: =SUM(F42:J42) -> 85264 | L42: =IF('Jilla Parishad Income & Expendi'!K42="", "", VALUE(SUBSTITUTE('Jilla Parishad Income & Expendi'!K42, ",", ""))) -> 0 | M42: =IF('Jilla Parishad Income & Expendi'!L42="", "", VALUE(SUBSTITUTE('Jilla Parishad Income & Expendi'!L42, ",", ""))) -> 3233 | N42: =IF('Jilla Parishad Income & Expendi'!M42="", "", VALUE(SUBSTITUTE('Jilla Parishad Income & Expendi'!M42, ",", ""))) -> 90530 | O42: =IF('Jilla Parishad Income & Expendi'!N42="", "", VALUE(SUBSTITUTE('Jilla Parishad Income & Expendi'!N42, ",", ""))) -> 116116 | P42: =IF('Jilla Parishad Income & Expendi'!O42="", "", VALUE(SUBSTITUTE('Jilla Parishad Income & Expendi'!O42, ",", ""))) -> 8629 | Q42: =IF('Jilla Parishad Income & Expendi'!P42="", "", VALUE(SUBSTITUTE('Jilla Parishad Income & Expendi'!P42, ",", ""))) -> 46053 | R42: =IF('Jilla Parishad Income & Expendi'!Q42="", "", VALUE(SUBSTITUTE('Jilla Parishad Income & Expendi'!Q42, ",", ""))) -> 4191 | S42: =IF('Jilla Parishad Income & Expendi'!R42="", "", VALUE(SUBSTITUTE('Jilla Parishad Income & Expendi'!R42, ",", ""))) -> 1762 | ... AD42: =IF('Jilla Parishad Income & Expendi'!AC42="", "", VALUE(SUBSTITUTE('Jilla Parishad Income & Expendi'!AC42, ",", "")))
A43: Buldhana | B43: =IF('Jilla Parishad Income & Expendi'!B43="", "", VALUE(SUBSTITUTE('Jilla Parishad Income & Expendi'!B43, ",", ""))) -> 2015 | C43: =IF('Jilla Parishad Income & Expendi'!C43="", "", VALUE(SUBSTITUTE('Jilla Parishad Income & Expendi'!C43, ",", ""))) -> 29083 | D43: =IF('Jilla Parishad Income & Expendi'!D43="", "", VALUE(SUBSTITUTE('Jilla Parishad Income & Expendi'!D43, ",", ""))) -> 1172 | E43: =IF('Jilla Parishad Income & Expendi'!E43="", "", VALUE(SUBSTITUTE('Jilla Parishad Income & Expendi'!E43, ",", ""))) | F43: =IF('Jilla Parishad Income & Expendi'!F43="", "", VALUE(SUBSTITUTE('Jilla Parishad Income & Expendi'!F43, ",", ""))) | G43: =IF('Jilla Parishad Income & Expendi'!G43="", "", VALUE(SUBSTITUTE('Jilla Parishad Income & Expendi'!G43, ",", ""))) -> 60231 | H43: =IF('Jilla Parishad Income & Expendi'!H43="", "", VALUE(SUBSTITUTE('Jilla Parishad Income & Expendi'!H43, ",", ""))) -> 30890 | I43: =IF('Jilla Parishad Income & Expendi'!I43="", "", VALUE(SUBSTITUTE('Jilla Parishad Income & Expendi'!I43, ",", ""))) | J43: =IF('Jilla Parishad Income & Expendi'!J43="", "", VALUE(SUBSTITUTE('Jilla Parishad Income & Expendi'!J43, ",", ""))) -> 3679 | K43: =SUM(F43:J43) -> 94800 | L43: =IF('Jilla Parishad Income & Expendi'!K43="", "", VALUE(SUBSTITUTE('Jilla Parishad Income & Expendi'!K43, ",", ""))) -> 0 | M43: =IF('Jilla Parishad Income & Expendi'!L43="", "", VALUE(SUBSTITUTE('Jilla Parishad Income & Expendi'!L43, ",", ""))) -> 4618 | N43: =IF('Jilla Parishad Income & Expendi'!M43="", "", VALUE(SUBSTITUTE('Jilla Parishad Income & Expendi'!M43, ",", ""))) -> 100590 | O43: =IF('Jilla Parishad Income & Expendi'!N43="", "", VALUE(SUBSTITUTE('Jilla Parishad Income & Expendi'!N43, ",", ""))) -> 129673 | P43: =IF('Jilla Parishad Income & Expendi'!O43="", "", VALUE(SUBSTITUTE('Jilla Parishad Income & Expendi'!O43, ",", ""))) -> 10395 | Q43: =IF('Jilla Parishad Income & Expendi'!P43="", "", VALUE(SUBSTITUTE('Jilla Parishad Income & Expendi'!P43, ",", ""))) -> 48082 | R43: =IF('Jilla Parishad Income & Expendi'!Q43="", "", VALUE(SUBSTITUTE('Jilla Parishad Income & Expendi'!Q43, ",", ""))) -> 2778 | S43: =IF('Jilla Parishad Income & Expendi'!R43="", "", VALUE(SUBSTITUTE('Jilla Parishad Income & Expendi'!R43, ",", ""))) -> 1195 | ... AD43: =IF('Jilla Parishad Income & Expendi'!AC43="", "", VALUE(SUBSTITUTE('Jilla Parishad Income & Expendi'!AC43, ",", "")))
A44: Buldhana | B44: =IF('Jilla Parishad Income & Expendi'!B44="", "", VALUE(SUBSTITUTE('Jilla Parishad Income & Expendi'!B44, ",", ""))) -> 2016 | C44: =IF('Jilla Parishad Income & Expendi'!C44="", "", VALUE(SUBSTITUTE('Jilla Parishad Income & Expendi'!C44, ",", ""))) -> 36121 | D44: =IF('Jilla Parishad Income & Expendi'!D44="", "", VALUE(SUBSTITUTE('Jilla Parishad Income & Expendi'!D44, ",", ""))) -> 2494 | E44: =IF('Jilla Parishad Income & Expendi'!E44="", "", VALUE(SUBSTITUTE('Jilla Parishad Income & Expendi'!E44, ",", ""))) | F44: =IF('Jilla Parishad Income & Expendi'!F44="", "", VALUE(SUBSTITUTE('Jilla Parishad Income & Expendi'!F44, ",", ""))) -> 16145 | G44: =IF('Jilla Parishad Income & Expendi'!G44="", "", VALUE(SUBSTITUTE('Jilla Parishad Income & Expendi'!G44, ",", ""))) -> 62062 | H44: =IF('Jilla Parishad Income & Expendi'!H44="", "", VALUE(SUBSTITUTE('Jilla Parishad Income & Expendi'!H44, ",", ""))) -> 1614 | I44: =IF('Jilla Parishad Income & Expendi'!I44="", "", VALUE(SUBSTITUTE('Jilla Parishad Income & Expendi'!I44, ",", ""))) -> 11172 | J44: =IF('Jilla Parishad Income & Expendi'!J44="", "", VALUE(SUBSTITUTE('Jilla Parishad Income & Expendi'!J44, ",", ""))) -> 6054 | K44: =SUM(F44:J44) -> 97047 | L44: =IF('Jilla Parishad Income & Expendi'!K44="", "", VALUE(SUBSTITUTE('Jilla Parishad Income & Expendi'!K44, ",", ""))) -> 0 | M44: =IF('Jilla Parishad Income & Expendi'!L44="", "", VALUE(SUBSTITUTE('Jilla Parishad Income & Expendi'!L44, ",", ""))) -> 6039 | N44: =IF('Jilla Parishad Income & Expendi'!M44="", "", VALUE(SUBSTITUTE('Jilla Parishad Income & Expendi'!M44, ",", ""))) -> 105580 | O44: =IF('Jilla Parishad Income & Expendi'!N44="", "", VALUE(SUBSTITUTE('Jilla Parishad Income & Expendi'!N44, ",", ""))) -> 141701 | P44: =IF('Jilla Parishad Income & Expendi'!O44="", "", VALUE(SUBSTITUTE('Jilla Parishad Income & Expendi'!O44, ",", ""))) -> 10290 | Q44: =IF('Jilla Parishad Income & Expendi'!P44="", "", VALUE(SUBSTITUTE('Jilla Parishad Income & Expendi'!P44, ",", ""))) -> 53305 | R44: =IF('Jilla Parishad Income & Expendi'!Q44="", "", VALUE(SUBSTITUTE('Jilla Parishad Income & Expendi'!Q44, ",", ""))) -> 4292 | S44: =IF('Jilla Parishad Income & Expendi'!R44="", "", VALUE(SUBSTITUTE('Jilla Parishad Income & Expendi'!R44, ",", ""))) -> 1662 | ... AD44: =IF('Jilla Parishad Income & Expendi'!AC44="", "", VALUE(SUBSTITUTE('Jilla Parishad Income & Expendi'!AC44, ",", "")))
A45: Buldhana | B45: =IF('Jilla Parishad Income & Expendi'!B45="", "", VALUE(SUBSTITUTE('Jilla Parishad Income & Expendi'!B45, ",", ""))) -> 2017 | C45: =IF('Jilla Parishad Income & Expendi'!C45="", "", VALUE(SUBSTITUTE('Jilla Parishad Income & Expendi'!C45, ",", ""))) -> 40129 | D45: =IF('Jilla Parishad Income & Expendi'!D45="", "", VALUE(SUBSTITUTE('Jilla Parishad Income & Expendi'!D45, ",", ""))) -> 3640 | E45: =IF('Jilla Parishad Income & Expendi'!E45="", "", VALUE(SUBSTITUTE('Jilla Parishad Income & Expendi'!E45, ",", ""))) | F45: =IF('Jilla Parishad Income & Expendi'!F45="", "", VALUE(SUBSTITUTE('Jilla Parishad Income & Expendi'!F45, ",", ""))) -> 8181 | G45: =IF('Jilla Parishad Income & Expendi'!G45="", "", VALUE(SUBSTITUTE('Jilla Parishad Income & Expendi'!G45, ",", ""))) -> 65553 | H45: =IF('Jilla Parishad Income & Expendi'!H45="", "", VALUE(SUBSTITUTE('Jilla Parishad Income & Expendi'!H45, ",", ""))) -> 18609 | I45: =IF('Jilla Parishad Income & Expendi'!I45="", "", VALUE(SUBSTITUTE('Jilla Parishad Income & Expendi'!I45, ",", ""))) -> 11332 | J45: =IF('Jilla Parishad Income & Expendi'!J45="", "", VALUE(SUBSTITUTE('Jilla Parishad Income & Expendi'!J45, ",", ""))) -> 3452 | K45: =SUM(F45:J45) -> 107127 | L45: =IF('Jilla Parishad Income & Expendi'!K45="", "", VALUE(SUBSTITUTE('Jilla Parishad Income & Expendi'!K45, ",", ""))) -> 0 | M45: =IF('Jilla Parishad Income & Expendi'!L45="", "", VALUE(SUBSTITUTE('Jilla Parishad Income & Expendi'!L45, ",", ""))) -> 2002 | N45: =IF('Jilla Parishad Income & Expendi'!M45="", "", VALUE(SUBSTITUTE('Jilla Parishad Income & Expendi'!M45, ",", ""))) -> 112769 | O45: =IF('Jilla Parishad Income & Expendi'!N45="", "", VALUE(SUBSTITUTE('Jilla Parishad Income & Expendi'!N45, ",", ""))) -> 152898 | P45: =IF('Jilla Parishad Income & Expendi'!O45="", "", VALUE(SUBSTITUTE('Jilla Parishad Income & Expendi'!O45, ",", ""))) -> 20375 | Q45: =IF('Jilla Parishad Income & Expendi'!P45="", "", VALUE(SUBSTITUTE('Jilla Parishad Income & Expendi'!P45, ",", ""))) -> 55412 | R45: =IF('Jilla Parishad Income & Expendi'!Q45="", "", VALUE(SUBSTITUTE('Jilla Parishad Income & Expendi'!Q45, ",", ""))) -> 5035 | S45: =IF('Jilla Parishad Income & Expendi'!R45="", "", VALUE(SUBSTITUTE('Jilla Parishad Income & Expendi'!R45, ",", ""))) -> 9979 | ... AD45: =IF('Jilla Parishad Income & Expendi'!AC45="", "", VALUE(SUBSTITUTE('Jilla Parishad Income & Expendi'!AC45, ",", "")))
A46: Buldhana | B46: =IF('Jilla Parishad Income & Expendi'!B46="", "", VALUE(SUBSTITUTE('Jilla Parishad Income & Expendi'!B46, ",", ""))) -> 2018 | C46: =IF('Jilla Parishad Income & Expendi'!C46="", "", VALUE(SUBSTITUTE('Jilla Parishad Income & Expendi'!C46, ",", ""))) -> 47711 | D46: =IF('Jilla Parishad Income & Expendi'!D46="", "", VALUE(SUBSTITUTE('Jilla Parishad Income & Expendi'!D46, ",", ""))) -> 3074 | E46: =IF('Jilla Parishad Income & Expendi'!E46="", "", VALUE(SUBSTITUTE('Jilla Parishad Income & Expendi'!E46, ",", ""))) | F46: =IF('Jilla Parishad Income & Expendi'!F46="", "", VALUE(SUBSTITUTE('Jilla Parishad Income & Expendi'!F46, ",", ""))) -> 8478 | G46: =IF('Jilla Parishad Income & Expendi'!G46="", "", VALUE(SUBSTITUTE('Jilla Parishad Income & Expendi'!G46, ",", ""))) -> 74015 | H46: =IF('Jilla Parishad Income & Expendi'!H46="", "", VALUE(SUBSTITUTE('Jilla Parishad Income & Expendi'!H46, ",", ""))) -> 19505 | I46: =IF('Jilla Parishad Income & Expendi'!I46="", "", VALUE(SUBSTITUTE('Jilla Parishad Income & Expendi'!I46, ",", ""))) -> 11596 | J46: =IF('Jilla Parishad Income & Expendi'!J46="", "", VALUE(SUBSTITUTE('Jilla Parishad Income & Expendi'!J46, ",", ""))) -> 3225 | K46: =SUM(F46:J46) -> 116819 | L46: =IF('Jilla Parishad Income & Expendi'!K46="", "", VALUE(SUBSTITUTE('Jilla Parishad Income & Expendi'!K46, ",", ""))) -> 0 | M46: =IF('Jilla Parishad Income & Expendi'!L46="", "", VALUE(SUBSTITUTE('Jilla Parishad Income & Expendi'!L46, ",", ""))) -> 2595 | N46: =IF('Jilla Parishad Income & Expendi'!M46="", "", VALUE(SUBSTITUTE('Jilla Parishad Income & Expendi'!M46, ",", ""))) -> 122488 | O46: =IF('Jilla Parishad Income & Expendi'!N46="", "", VALUE(SUBSTITUTE('Jilla Parishad Income & Expendi'!N46, ",", ""))) -> 170199 | P46: =IF('Jilla Parishad Income & Expendi'!O46="", "", VALUE(SUBSTITUTE('Jilla Parishad Income & Expendi'!O46, ",", ""))) -> 16648 | Q46: =IF('Jilla Parishad Income & Expendi'!P46="", "", VALUE(SUBSTITUTE('Jilla Parishad Income & Expendi'!P46, ",", ""))) -> 57512 | R46: =IF('Jilla Parishad Income & Expendi'!Q46="", "", VALUE(SUBSTITUTE('Jilla Parishad Income & Expendi'!Q46, ",", ""))) -> 2130 | S46: =IF('Jilla Parishad Income & Expendi'!R46="", "", VALUE(SUBSTITUTE('Jilla Parishad Income & Expendi'!R46, ",", ""))) -> 5960 | ... AD46: =IF('Jilla Parishad Income & Expendi'!AC46="", "", VALUE(SUBSTITUTE('Jilla Parishad Income & Expendi'!AC46, ",", "")))
A47: Buldhana | B47: =IF('Jilla Parishad Income & Expendi'!B47="", "", VALUE(SUBSTITUTE('Jilla Parishad Income & Expendi'!B47, ",", ""))) -> 2019 | C47: =IF('Jilla Parishad Income & Expendi'!C47="", "", VALUE(SUBSTITUTE('Jilla Parishad Income & Expendi'!C47, ",", ""))) -> 68643 | D47: =IF('Jilla Parishad Income & Expendi'!D47="", "", VALUE(SUBSTITUTE('Jilla Parishad Income & Expendi'!D47, ",", ""))) -> 1223 | E47: =IF('Jilla Parishad Income & Expendi'!E47="", "", VALUE(SUBSTITUTE('Jilla Parishad Income & Expendi'!E47, ",", ""))) | F47: =IF('Jilla Parishad Income & Expendi'!F47="", "", VALUE(SUBSTITUTE('Jilla Parishad Income & Expendi'!F47, ",", ""))) -> 6638 | G47: =IF('Jilla Parishad Income & Expendi'!G47="", "", VALUE(SUBSTITUTE('Jilla Parishad Income & Expendi'!G47, ",", ""))) -> 97093 | H47: =IF('Jilla Parishad Income & Expendi'!H47="", "", VALUE(SUBSTITUTE('Jilla Parishad Income & Expendi'!H47, ",", ""))) -> 16643 | I47: =IF('Jilla Parishad Income & Expendi'!I47="", "", VALUE(SUBSTITUTE('Jilla Parishad Income & Expendi'!I47, ",", ""))) -> 11875 | J47: =IF('Jilla Parishad Income & Expendi'!J47="", "", VALUE(SUBSTITUTE('Jilla Parishad Income & Expendi'!J47, ",", ""))) -> 7179 | K47: =SUM(F47:J47) -> 139428 | L47: =IF('Jilla Parishad Income & Expendi'!K47="", "", VALUE(SUBSTITUTE('Jilla Parishad Income & Expendi'!K47, ",", ""))) -> 0 | M47: =IF('Jilla Parishad Income & Expendi'!L47="", "", VALUE(SUBSTITUTE('Jilla Parishad Income & Expendi'!L47, ",", ""))) -> 2267 | N47: =IF('Jilla Parishad Income & Expendi'!M47="", "", VALUE(SUBSTITUTE('Jilla Parishad Income & Expendi'!M47, ",", ""))) -> 142918 | O47: =IF('Jilla Parishad Income & Expendi'!N47="", "", VALUE(SUBSTITUTE('Jilla Parishad Income & Expendi'!N47, ",", ""))) -> 211561 | P47: =IF('Jilla Parishad Income & Expendi'!O47="", "", VALUE(SUBSTITUTE('Jilla Parishad Income & Expendi'!O47, ",", ""))) -> 12044 | Q47: =IF('Jilla Parishad Income & Expendi'!P47="", "", VALUE(SUBSTITUTE('Jilla Parishad Income & Expendi'!P47, ",", ""))) -> 66151 | R47: =IF('Jilla Parishad Income & Expendi'!Q47="", "", VALUE(SUBSTITUTE('Jilla Parishad Income & Expendi'!Q47, ",", ""))) -> 10035 | S47: =IF('Jilla Parishad Income & Expendi'!R47="", "", VALUE(SUBSTITUTE('Jilla Parishad Income & Expendi'!R47, ",", ""))) -> 1576 | ... AD47: =IF('Jilla Parishad Income & Expendi'!AC47="", "", VALUE(SUBSTITUTE('Jilla Parishad Income & Expendi'!AC47, ",", "")))
... A297: Solapur | B297: =IF('Jilla Parishad Income & Expendi'!B297="", "", VALUE(SUBSTITUTE('Jilla Parishad Income & Expendi'!B297, ",", ""))) -> 2021 | C297: =IF('Jilla Parishad Income & Expendi'!C297="", "", VALUE(SUBSTITUTE('Jilla Parishad Income & Expendi'!C297, ",", ""))) -> 32854.34 | D297: =IF('Jilla Parishad Income & Expendi'!D297="", "", VALUE(SUBSTITUTE('Jilla Parishad Income & Expendi'!D297, ",", ""))) -> 0 | E297: =IF('Jilla Parishad Income & Expendi'!E297="", "", VALUE(SUBSTITUTE('Jilla Parishad Income & Expendi'!E297, ",", ""))) -> 0 | F297: =IF('Jilla Parishad Income & Expendi'!F297="", "", VALUE(SUBSTITUTE('Jilla Parishad Income & Expendi'!F297, ",", ""))) -> 0 | G297: =IF('Jilla Parishad Income & Expendi'!G297="", "", VALUE(SUBSTITUTE('Jilla Parishad Income & Expendi'!G297, ",", ""))) -> 148057.87 | H297: =IF('Jilla Parishad Income & Expendi'!H297="", "", VALUE(SUBSTITUTE('Jilla Parishad Income & Expendi'!H297, ",", ""))) -> 39545.06 | I297: =IF('Jilla Parishad Income & Expendi'!I297="", "", VALUE(SUBSTITUTE('Jilla Parishad Income & Expendi'!I297, ",", ""))) -> 0 | J297: =IF('Jilla Parishad Income & Expendi'!J297="", "", VALUE(SUBSTITUTE('Jilla Parishad Income & Expendi'!J297, ",", ""))) -> 3885.99 | K297: =SUM(F297:J297) -> 191488.92 | L297: =IF('Jilla Parishad Income & Expendi'!K297="", "", VALUE(SUBSTITUTE('Jilla Parishad Income & Expendi'!K297, ",", ""))) -> 0 | M297: =IF('Jilla Parishad Income & Expendi'!L297="", "", VALUE(SUBSTITUTE('Jilla Parishad Income & Expendi'!L297, ",", ""))) -> 10062.9 | N297: =IF('Jilla Parishad Income & Expendi'!M297="", "", VALUE(SUBSTITUTE('Jilla Parishad Income & Expendi'!M297, ",", ""))) -> 201552 | O297: =IF('Jilla Parishad Income & Expendi'!N297="", "", VALUE(SUBSTITUTE('Jilla Parishad Income & Expendi'!N297, ",", ""))) -> 234406 | P297: =IF('Jilla Parishad Income & Expendi'!O297="", "", VALUE(SUBSTITUTE('Jilla Parishad Income & Expendi'!O297, ",", ""))) -> 20108.31 | Q297: =IF('Jilla Parishad Income & Expendi'!P297="", "", VALUE(SUBSTITUTE('Jilla Parishad Income & Expendi'!P297, ",", ""))) -> 101392.43 | R297: =IF('Jilla Parishad Income & Expendi'!Q297="", "", VALUE(SUBSTITUTE('Jilla Parishad Income & Expendi'!Q297, ",", ""))) -> 15859.11 | S297: =IF('Jilla Parishad Income & Expendi'!R297="", "", VALUE(SUBSTITUTE('Jilla Parishad Income & Expendi'!R297, ",", ""))) -> 3047.73 | ... AD297: =IF('Jilla Parishad Income & Expendi'!AC297="", "", VALUE(SUBSTITUTE('Jilla Parishad Income & Expendi'!AC297, ",", "")))
A298: Aurangabad | B298: =IF('Jilla Parishad Income & Expendi'!B298="", "", VALUE(SUBSTITUTE('Jilla Parishad Income & Expendi'!B298, ",", ""))) -> 2012 | C298: =IF('Jilla Parishad Income & Expendi'!C298="", "", VALUE(SUBSTITUTE('Jilla Parishad Income & Expendi'!C298, ",", ""))) -> 25053.26 | D298: =IF('Jilla Parishad Income & Expendi'!D298="", "", VALUE(SUBSTITUTE('Jilla Parishad Income & Expendi'!D298, ",", ""))) -> 2102.05 | E298: =IF('Jilla Parishad Income & Expendi'!E298="", "", VALUE(SUBSTITUTE('Jilla Parishad Income & Expendi'!E298, ",", ""))) | F298: =IF('Jilla Parishad Income & Expendi'!F298="", "", VALUE(SUBSTITUTE('Jilla Parishad Income & Expendi'!F298, ",", ""))) -> 51071.55 | G298: =IF('Jilla Parishad Income & Expendi'!G298="", "", VALUE(SUBSTITUTE('Jilla Parishad Income & Expendi'!G298, ",", ""))) -> 8046.86 | H298: =IF('Jilla Parishad Income & Expendi'!H298="", "", VALUE(SUBSTITUTE('Jilla Parishad Income & Expendi'!H298, ",", ""))) -> 11822.35 | I298: =IF('Jilla Parishad Income & Expendi'!I298="", "", VALUE(SUBSTITUTE('Jilla Parishad Income & Expendi'!I298, ",", ""))) -> 0 | J298: -2222.86 | K298: =SUM(F298:J298) -> 68717.9 | L298: =IF('Jilla Parishad Income & Expendi'!K298="", "", VALUE(SUBSTITUTE('Jilla Parishad Income & Expendi'!K298, ",", ""))) -> 8554.93 | M298: =IF('Jilla Parishad Income & Expendi'!L298="", "", VALUE(SUBSTITUTE('Jilla Parishad Income & Expendi'!L298, ",", ""))) -> 100 | N298: =IF('Jilla Parishad Income & Expendi'!M298="", "", VALUE(SUBSTITUTE('Jilla Parishad Income & Expendi'!M298, ",", ""))) -> 90426 | O298: =IF('Jilla Parishad Income & Expendi'!N298="", "", VALUE(SUBSTITUTE('Jilla Parishad Income & Expendi'!N298, ",", ""))) -> 115480 | P298: =IF('Jilla Parishad Income & Expendi'!O298="", "", VALUE(SUBSTITUTE('Jilla Parishad Income & Expendi'!O298, ",", ""))) -> 3365.26 | Q298: =IF('Jilla Parishad Income & Expendi'!P298="", "", VALUE(SUBSTITUTE('Jilla Parishad Income & Expendi'!P298, ",", ""))) -> 43302.89 | R298: =IF('Jilla Parishad Income & Expendi'!Q298="", "", VALUE(SUBSTITUTE('Jilla Parishad Income & Expendi'!Q298, ",", ""))) -> 3536.09 | S298: =IF('Jilla Parishad Income & Expendi'!R298="", "", VALUE(SUBSTITUTE('Jilla Parishad Income & Expendi'!R298, ",", ""))) -> 2272.01 | ... AD298: =IF('Jilla Parishad Income & Expendi'!AC298="", "", VALUE(SUBSTITUTE('Jilla Parishad Income & Expendi'!AC298, ",", "")))
A299: Aurangabad | B299: =IF('Jilla Parishad Income & Expendi'!B299="", "", VALUE(SUBSTITUTE('Jilla Parishad Income & Expendi'!B299, ",", ""))) -> 2013 | C299: =IF('Jilla Parishad Income & Expendi'!C299="", "", VALUE(SUBSTITUTE('Jilla Parishad Income & Expendi'!C299, ",", ""))) -> 25867.56 | D299: =IF('Jilla Parishad Income & Expendi'!D299="", "", VALUE(SUBSTITUTE('Jilla Parishad Income & Expendi'!D299, ",", ""))) -> 2216.43 | E299: =IF('Jilla Parishad Income & Expendi'!E299="", "", VALUE(SUBSTITUTE('Jilla Parishad Income & Expendi'!E299, ",", ""))) | F299: =IF('Jilla Parishad Income & Expendi'!F299="", "", VALUE(SUBSTITUTE('Jilla Parishad Income & Expendi'!F299, ",", ""))) -> 55962.87 | G299: =IF('Jilla Parishad Income & Expendi'!G299="", "", VALUE(SUBSTITUTE('Jilla Parishad Income & Expendi'!G299, ",", ""))) -> 8977.81 | H299: =IF('Jilla Parishad Income & Expendi'!H299="", "", VALUE(SUBSTITUTE('Jilla Parishad Income & Expendi'!H299, ",", ""))) -> 18696.78 | I299: =IF('Jilla Parishad Income & Expendi'!I299="", "", VALUE(SUBSTITUTE('Jilla Parishad Income & Expendi'!I299, ",", ""))) -> 0 | J299: -2424.27 | K299: =SUM(F299:J299) -> 81213.19 | L299: =IF('Jilla Parishad Income & Expendi'!K299="", "", VALUE(SUBSTITUTE('Jilla Parishad Income & Expendi'!K299, ",", ""))) -> 0 | M299: =IF('Jilla Parishad Income & Expendi'!L299="", "", VALUE(SUBSTITUTE('Jilla Parishad Income & Expendi'!L299, ",", ""))) -> 88 | N299: =IF('Jilla Parishad Income & Expendi'!M299="", "", VALUE(SUBSTITUTE('Jilla Parishad Income & Expendi'!M299, ",", ""))) -> 113599 | O299: =IF('Jilla Parishad Income & Expendi'!N299="", "", VALUE(SUBSTITUTE('Jilla Parishad Income & Expendi'!N299, ",", ""))) -> 113599 | P299: =IF('Jilla Parishad Income & Expendi'!O299="", "", VALUE(SUBSTITUTE('Jilla Parishad Income & Expendi'!O299, ",", ""))) -> 6517.27 | Q299: =IF('Jilla Parishad Income & Expendi'!P299="", "", VALUE(SUBSTITUTE('Jilla Parishad Income & Expendi'!P299, ",", ""))) -> 45886.25 | R299: =IF('Jilla Parishad Income & Expendi'!Q299="", "", VALUE(SUBSTITUTE('Jilla Parishad Income & Expendi'!Q299, ",", ""))) -> 913.86 | S299: =IF('Jilla Parishad Income & Expendi'!R299="", "", VALUE(SUBSTITUTE('Jilla Parishad Income & Expendi'!R299, ",", ""))) -> 949.31 | ... AD299: =IF('Jilla Parishad Income & Expendi'!AC299="", "", VALUE(SUBSTITUTE('Jilla Parishad Income & Expendi'!AC299, ",", "")))
A300: Aurangabad | B300: =IF('Jilla Parishad Income & Expendi'!B300="", "", VALUE(SUBSTITUTE('Jilla Parishad Income & Expendi'!B300, ",", ""))) -> 2014 | C300: =IF('Jilla Parishad Income & Expendi'!C300="", "", VALUE(SUBSTITUTE('Jilla Parishad Income & Expendi'!C300, ",", ""))) -> 28909.84 | D300: =IF('Jilla Parishad Income & Expendi'!D300="", "", VALUE(SUBSTITUTE('Jilla Parishad Income & Expendi'!D300, ",", ""))) -> 2079.87 | E300: =IF('Jilla Parishad Income & Expendi'!E300="", "", VALUE(SUBSTITUTE('Jilla Parishad Income & Expendi'!E300, ",", ""))) | F300: =IF('Jilla Parishad Income & Expendi'!F300="", "", VALUE(SUBSTITUTE('Jilla Parishad Income & Expendi'!F300, ",", ""))) -> 58992.29 | G300: =IF('Jilla Parishad Income & Expendi'!G300="", "", VALUE(SUBSTITUTE('Jilla Parishad Income & Expendi'!G300, ",", ""))) -> 12397.76 | H300: =IF('Jilla Parishad Income & Expendi'!H300="", "", VALUE(SUBSTITUTE('Jilla Parishad Income & Expendi'!H300, ",", ""))) -> 14406.19 | I300: =IF('Jilla Parishad Income & Expendi'!I300="", "", VALUE(SUBSTITUTE('Jilla Parishad Income & Expendi'!I300, ",", ""))) -> 0 | J300: =IF('Jilla Parishad Income & Expendi'!J300="", "", VALUE(SUBSTITUTE('Jilla Parishad Income & Expendi'!J300, ",", ""))) -> -671.23 | K300: =SUM(F300:J300) -> 85125.01 | L300: =IF('Jilla Parishad Income & Expendi'!K300="", "", VALUE(SUBSTITUTE('Jilla Parishad Income & Expendi'!K300, ",", ""))) -> 7758.54 | M300: =IF('Jilla Parishad Income & Expendi'!L300="", "", VALUE(SUBSTITUTE('Jilla Parishad Income & Expendi'!L300, ",", ""))) -> 94 | N300: =IF('Jilla Parishad Income & Expendi'!M300="", "", VALUE(SUBSTITUTE('Jilla Parishad Income & Expendi'!M300, ",", ""))) -> 127926 | O300: =IF('Jilla Parishad Income & Expendi'!N300="", "", VALUE(SUBSTITUTE('Jilla Parishad Income & Expendi'!N300, ",", ""))) -> 127926 | P300: =IF('Jilla Parishad Income & Expendi'!O300="", "", VALUE(SUBSTITUTE('Jilla Parishad Income & Expendi'!O300, ",", ""))) -> 7410.68 | Q300: =IF('Jilla Parishad Income & Expendi'!P300="", "", VALUE(SUBSTITUTE('Jilla Parishad Income & Expendi'!P300, ",", ""))) -> 51635.54 | R300: =IF('Jilla Parishad Income & Expendi'!Q300="", "", VALUE(SUBSTITUTE('Jilla Parishad Income & Expendi'!Q300, ",", ""))) -> 4243.63 | S300: =IF('Jilla Parishad Income & Expendi'!R300="", "", VALUE(SUBSTITUTE('Jilla Parishad Income & Expendi'!R300, ",", ""))) -> 874.78 | ... AD300: =IF('Jilla Parishad Income & Expendi'!AC300="", "", VALUE(SUBSTITUTE('Jilla Parishad Income & Expendi'!AC300, ",", "")))
A301: Aurangabad | B301: =IF('Jilla Parishad Income & Expendi'!B301="", "", VALUE(SUBSTITUTE('Jilla Parishad Income & Expendi'!B301, ",", ""))) -> 2015 | C301: =IF('Jilla Parishad Income & Expendi'!C301="", "", VALUE(SUBSTITUTE('Jilla Parishad Income & Expendi'!C301, ",", ""))) -> 35824.28 | D301: =IF('Jilla Parishad Income & Expendi'!D301="", "", VALUE(SUBSTITUTE('Jilla Parishad Income & Expendi'!D301, ",", ""))) -> 3196.05 | E301: =IF('Jilla Parishad Income & Expendi'!E301="", "", VALUE(SUBSTITUTE('Jilla Parishad Income & Expendi'!E301, ",", ""))) | F301: =IF('Jilla Parishad Income & Expendi'!F301="", "", VALUE(SUBSTITUTE('Jilla Parishad Income & Expendi'!F301, ",", ""))) -> 7119.6 | G301: =IF('Jilla Parishad Income & Expendi'!G301="", "", VALUE(SUBSTITUTE('Jilla Parishad Income & Expendi'!G301, ",", ""))) -> 13975.76 | H301: =IF('Jilla Parishad Income & Expendi'!H301="", "", VALUE(SUBSTITUTE('Jilla Parishad Income & Expendi'!H301, ",", ""))) -> 64581.27 | I301: =IF('Jilla Parishad Income & Expendi'!I301="", "", VALUE(SUBSTITUTE('Jilla Parishad Income & Expendi'!I301, ",", ""))) -> 0 | J301: =IF('Jilla Parishad Income & Expendi'!J301="", "", VALUE(SUBSTITUTE('Jilla Parishad Income & Expendi'!J301, ",", ""))) -> -5034.47 | K301: =SUM(F301:J301) -> 80642.16 | L301: =IF('Jilla Parishad Income & Expendi'!K301="", "", VALUE(SUBSTITUTE('Jilla Parishad Income & Expendi'!K301, ",", ""))) -> 9497.29 | M301: =IF('Jilla Parishad Income & Expendi'!L301="", "", VALUE(SUBSTITUTE('Jilla Parishad Income & Expendi'!L301, ",", ""))) -> 185 | N301: =IF('Jilla Parishad Income & Expendi'!M301="", "", VALUE(SUBSTITUTE('Jilla Parishad Income & Expendi'!M301, ",", ""))) -> 134207 | O301: =IF('Jilla Parishad Income & Expendi'!N301="", "", VALUE(SUBSTITUTE('Jilla Parishad Income & Expendi'!N301, ",", ""))) -> 134207 | P301: =IF('Jilla Parishad Income & Expendi'!O301="", "", VALUE(SUBSTITUTE('Jilla Parishad Income & Expendi'!O301, ",", ""))) -> 10928.24 | Q301: =IF('Jilla Parishad Income & Expendi'!P301="", "", VALUE(SUBSTITUTE('Jilla Parishad Income & Expendi'!P301, ",", ""))) -> 56526.35 | R301: =IF('Jilla Parishad Income & Expendi'!Q301="", "", VALUE(SUBSTITUTE('Jilla Parishad Income & Expendi'!Q301, ",", ""))) -> 1102.89 | S301: =IF('Jilla Parishad Income & Expendi'!R301="", "", VALUE(SUBSTITUTE('Jilla Parishad Income & Expendi'!R301, ",", ""))) -> 627.46 | ... AD301: =IF('Jilla Parishad Income & Expendi'!AC301="", "", VALUE(SUBSTITUTE('Jilla Parishad Income & Expendi'!AC301, ",", "")))
A302: Aurangabad | B302: =IF('Jilla Parishad Income & Expendi'!B302="", "", VALUE(SUBSTITUTE('Jilla Parishad Income & Expendi'!B302, ",", ""))) -> 2016 | C302: =IF('Jilla Parishad Income & Expendi'!C302="", "", VALUE(SUBSTITUTE('Jilla Parishad Income & Expendi'!C302, ",", ""))) -> 33244 | D302: =IF('Jilla Parishad Income & Expendi'!D302="", "", VALUE(SUBSTITUTE('Jilla Parishad Income & Expendi'!D302, ",", ""))) -> 2811.76 | E302: =IF('Jilla Parishad Income & Expendi'!E302="", "", VALUE(SUBSTITUTE('Jilla Parishad Income & Expendi'!E302, ",", ""))) | F302: =IF('Jilla Parishad Income & Expendi'!F302="", "", VALUE(SUBSTITUTE('Jilla Parishad Income & Expendi'!F302, ",", ""))) -> 1993.86 | G302: =IF('Jilla Parishad Income & Expendi'!G302="", "", VALUE(SUBSTITUTE('Jilla Parishad Income & Expendi'!G302, ",", ""))) -> 14191.27 | H302: =IF('Jilla Parishad Income & Expendi'!H302="", "", VALUE(SUBSTITUTE('Jilla Parishad Income & Expendi'!H302, ",", ""))) -> 76344.58 | I302: =IF('Jilla Parishad Income & Expendi'!I302="", "", VALUE(SUBSTITUTE('Jilla Parishad Income & Expendi'!I302, ",", ""))) -> -1854.81 | J302: =IF('Jilla Parishad Income & Expendi'!J302="", "", VALUE(SUBSTITUTE('Jilla Parishad Income & Expendi'!J302, ",", ""))) -> 12485.61 | K302: =SUM(F302:J302) -> 103160.51 | L302: =IF('Jilla Parishad Income & Expendi'!K302="", "", VALUE(SUBSTITUTE('Jilla Parishad Income & Expendi'!K302, ",", ""))) -> 156.97 | M302: =IF('Jilla Parishad Income & Expendi'!L302="", "", VALUE(SUBSTITUTE('Jilla Parishad Income & Expendi'!L302, ",", ""))) -> 3230.01 | N302: =IF('Jilla Parishad Income & Expendi'!M302="", "", VALUE(SUBSTITUTE('Jilla Parishad Income & Expendi'!M302, ",", ""))) -> 109359 | O302: =IF('Jilla Parishad Income & Expendi'!N302="", "", VALUE(SUBSTITUTE('Jilla Parishad Income & Expendi'!N302, ",", ""))) -> 142603 | P302: =IF('Jilla Parishad Income & Expendi'!O302="", "", VALUE(SUBSTITUTE('Jilla Parishad Income & Expendi'!O302, ",", ""))) -> 8537.17 | Q302: =IF('Jilla Parishad Income & Expendi'!P302="", "", VALUE(SUBSTITUTE('Jilla Parishad Income & Expendi'!P302, ",", ""))) -> 58395.92 | R302: =IF('Jilla Parishad Income & Expendi'!Q302="", "", VALUE(SUBSTITUTE('Jilla Parishad Income & Expendi'!Q302, ",", ""))) -> 2832.63 | S302: =IF('Jilla Parishad Income & Expendi'!R302="", "", VALUE(SUBSTITUTE('Jilla Parishad Income & Expendi'!R302, ",", ""))) -> 650.51 | ... AD302: =IF('Jilla Parishad Income & Expendi'!AC302="", "", VALUE(SUBSTITUTE('Jilla Parishad Income & Expendi'!AC302, ",", "")))
A303: Aurangabad | B303: =IF('Jilla Parishad Income & Expendi'!B303="", "", VALUE(SUBSTITUTE('Jilla Parishad Income & Expendi'!B303, ",", ""))) -> 2017 | C303: =IF('Jilla Parishad Income & Expendi'!C303="", "", VALUE(SUBSTITUTE('Jilla Parishad Income & Expendi'!C303, ",", ""))) -> 38187.89 | D303: =IF('Jilla Parishad Income & Expendi'!D303="", "", VALUE(SUBSTITUTE('Jilla Parishad Income & Expendi'!D303, ",", ""))) -> 3032.02 | E303: =IF('Jilla Parishad Income & Expendi'!E303="", "", VALUE(SUBSTITUTE('Jilla Parishad Income & Expendi'!E303, ",", ""))) | F303: =IF('Jilla Parishad Income & Expendi'!F303="", "", VALUE(SUBSTITUTE('Jilla Parishad Income & Expendi'!F303, ",", ""))) -> 10282.43 | G303: =IF('Jilla Parishad Income & Expendi'!G303="", "", VALUE(SUBSTITUTE('Jilla Parishad Income & Expendi'!G303, ",", ""))) -> 14742.03 | H303: =IF('Jilla Parishad Income & Expendi'!H303="", "", VALUE(SUBSTITUTE('Jilla Parishad Income & Expendi'!H303, ",", ""))) -> 64727.62 | I303: =IF('Jilla Parishad Income & Expendi'!I303="", "", VALUE(SUBSTITUTE('Jilla Parishad Income & Expendi'!I303, ",", ""))) -> 0 | J303: =IF('Jilla Parishad Income & Expendi'!J303="", "", VALUE(SUBSTITUTE('Jilla Parishad Income & Expendi'!J303, ",", ""))) -> 7517.09 | K303: =SUM(F303:J303) -> 97269.17 | L303: =IF('Jilla Parishad Income & Expendi'!K303="", "", VALUE(SUBSTITUTE('Jilla Parishad Income & Expendi'!K303, ",", ""))) -> 135.42 | M303: =IF('Jilla Parishad Income & Expendi'!L303="", "", VALUE(SUBSTITUTE('Jilla Parishad Income & Expendi'!L303, ",", ""))) -> 3542.68 | N303: =IF('Jilla Parishad Income & Expendi'!M303="", "", VALUE(SUBSTITUTE('Jilla Parishad Income & Expendi'!M303, ",", ""))) -> 103979 | O303: =IF('Jilla Parishad Income & Expendi'!N303="", "", VALUE(SUBSTITUTE('Jilla Parishad Income & Expendi'!N303, ",", ""))) -> 142167 | P303: =IF('Jilla Parishad Income & Expendi'!O303="", "", VALUE(SUBSTITUTE('Jilla Parishad Income & Expendi'!O303, ",", ""))) -> 9086.73 | Q303: =IF('Jilla Parishad Income & Expendi'!P303="", "", VALUE(SUBSTITUTE('Jilla Parishad Income & Expendi'!P303, ",", ""))) -> 60871.19 | R303: =IF('Jilla Parishad Income & Expendi'!Q303="", "", VALUE(SUBSTITUTE('Jilla Parishad Income & Expendi'!Q303, ",", ""))) -> 2656.8 | S303: =IF('Jilla Parishad Income & Expendi'!R303="", "", VALUE(SUBSTITUTE('Jilla Parishad Income & Expendi'!R303, ",", ""))) -> 882.16 | ... AD303: =IF('Jilla Parishad Income & Expendi'!AC303="", "", VALUE(SUBSTITUTE('Jilla Parishad Income & Expendi'!AC303, ",", "")))
A304: Aurangabad | B304: =IF('Jilla Parishad Income & Expendi'!B304="", "", VALUE(SUBSTITUTE('Jilla Parishad Income & Expendi'!B304, ",", ""))) -> 2018 | C304: =IF('Jilla Parishad Income & Expendi'!C304="", "", VALUE(SUBSTITUTE('Jilla Parishad Income & Expendi'!C304, ",", ""))) -> 398102.35 | D304: =IF('Jilla Parishad Income & Expendi'!D304="", "", VALUE(SUBSTITUTE('Jilla Parishad Income & Expendi'!D304, ",", ""))) -> 4240.34 | E304: =IF('Jilla Parishad Income & Expendi'!E304="", "", VALUE(SUBSTITUTE('Jilla Parishad Income & Expendi'!E304, ",", ""))) | F304: =IF('Jilla Parishad Income & Expendi'!F304="", "", VALUE(SUBSTITUTE('Jilla Parishad Income & Expendi'!F304, ",", ""))) -> 28948.21 | G304: =IF('Jilla Parishad Income & Expendi'!G304="", "", VALUE(SUBSTITUTE('Jilla Parishad Income & Expendi'!G304, ",", ""))) -> 15529.86 | H304: =IF('Jilla Parishad Income & Expendi'!H304="", "", VALUE(SUBSTITUTE('Jilla Parishad Income & Expendi'!H304, ",", ""))) -> 70403.79 | I304: =IF('Jilla Parishad Income & Expendi'!I304="", "", VALUE(SUBSTITUTE('Jilla Parishad Income & Expendi'!I304, ",", ""))) -> 0 | J304: =IF('Jilla Parishad Income & Expendi'!J304="", "", VALUE(SUBSTITUTE('Jilla Parishad Income & Expendi'!J304, ",", ""))) -> 19686.38 | K304: =SUM(F304:J304) -> 134568.24 | L304: =IF('Jilla Parishad Income & Expendi'!K304="", "", VALUE(SUBSTITUTE('Jilla Parishad Income & Expendi'!K304, ",", ""))) -> 114.42 | M304: =IF('Jilla Parishad Income & Expendi'!L304="", "", VALUE(SUBSTITUTE('Jilla Parishad Income & Expendi'!L304, ",", ""))) -> 3700.72 | N304: =IF('Jilla Parishad Income & Expendi'!M304="", "", VALUE(SUBSTITUTE('Jilla Parishad Income & Expendi'!M304, ",", ""))) -> 142624 | O304: =IF('Jilla Parishad Income & Expendi'!N304="", "", VALUE(SUBSTITUTE('Jilla Parishad Income & Expendi'!N304, ",", ""))) -> 540726 | P304: =IF('Jilla Parishad Income & Expendi'!O304="", "", VALUE(SUBSTITUTE('Jilla Parishad Income & Expendi'!O304, ",", ""))) -> 9771.74 | Q304: =IF('Jilla Parishad Income & Expendi'!P304="", "", VALUE(SUBSTITUTE('Jilla Parishad Income & Expendi'!P304, ",", ""))) -> 62838.27 | R304: =IF('Jilla Parishad Income & Expendi'!Q304="", "", VALUE(SUBSTITUTE('Jilla Parishad Income & Expendi'!Q304, ",", ""))) -> 1027.04 | S304: =IF('Jilla Parishad Income & Expendi'!R304="", "", VALUE(SUBSTITUTE('Jilla Parishad Income & Expendi'!R304, ",", ""))) -> 481.78 | ... AD304: =IF('Jilla Parishad Income & Expendi'!AC304="", "", VALUE(SUBSTITUTE('Jilla Parishad Income & Expendi'!AC304, ",", "")))
A305: Aurangabad | B305: =IF('Jilla Parishad Income & Expendi'!B305="", "", VALUE(SUBSTITUTE('Jilla Parishad Income & Expendi'!B305, ",", ""))) -> 2019 | C305: =IF('Jilla Parishad Income & Expendi'!C305="", "", VALUE(SUBSTITUTE('Jilla Parishad Income & Expendi'!C305, ",", ""))) -> 434146.65 | D305: =IF('Jilla Parishad Income & Expendi'!D305="", "", VALUE(SUBSTITUTE('Jilla Parishad Income & Expendi'!D305, ",", ""))) -> 5313.25 | E305: =IF('Jilla Parishad Income & Expendi'!E305="", "", VALUE(SUBSTITUTE('Jilla Parishad Income & Expendi'!E305, ",", ""))) | F305: =IF('Jilla Parishad Income & Expendi'!F305="", "", VALUE(SUBSTITUTE('Jilla Parishad Income & Expendi'!F305, ",", ""))) -> 18213.26 | G305: =IF('Jilla Parishad Income & Expendi'!G305="", "", VALUE(SUBSTITUTE('Jilla Parishad Income & Expendi'!G305, ",", ""))) | H305: =IF('Jilla Parishad Income & Expendi'!H305="", "", VALUE(SUBSTITUTE('Jilla Parishad Income & Expendi'!H305, ",", ""))) | I305: =IF('Jilla Parishad Income & Expendi'!I305="", "", VALUE(SUBSTITUTE('Jilla Parishad Income & Expendi'!I305, ",", ""))) -> 0 | J305: =IF('Jilla Parishad Income & Expendi'!J305="", "", VALUE(SUBSTITUTE('Jilla Parishad Income & Expendi'!J305, ",", ""))) -> 5313.25 | K305: =SUM(F305:J305) -> 23526.51 | L305: =IF('Jilla Parishad Income & Expendi'!K305="", "", VALUE(SUBSTITUTE('Jilla Parishad Income & Expendi'!K305, ",", ""))) | M305: =IF('Jilla Parishad Income & Expendi'!L305="", "", VALUE(SUBSTITUTE('Jilla Parishad Income & Expendi'!L305, ",", ""))) | N305: =IF('Jilla Parishad Income & Expendi'!M305="", "", VALUE(SUBSTITUTE('Jilla Parishad Income & Expendi'!M305, ",", ""))) -> 28840 | O305: =IF('Jilla Parishad Income & Expendi'!N305="", "", VALUE(SUBSTITUTE('Jilla Parishad Income & Expendi'!N305, ",", ""))) -> 462986 | P305: =IF('Jilla Parishad Income & Expendi'!O305="", "", VALUE(SUBSTITUTE('Jilla Parishad Income & Expendi'!O305, ",", ""))) -> 23690.13 | Q305: =IF('Jilla Parishad Income & Expendi'!P305="", "", VALUE(SUBSTITUTE('Jilla Parishad Income & Expendi'!P305, ",", ""))) -> 86538.48 | R305: =IF('Jilla Parishad Income & Expendi'!Q305="", "", VALUE(SUBSTITUTE('Jilla Parishad Income & Expendi'!Q305, ",", ""))) -> 1778.45 | S305: =IF('Jilla Parishad Income & Expendi'!R305="", "", VALUE(SUBSTITUTE('Jilla Parishad Income & Expendi'!R305, ",", ""))) -> 3452.17 | ... AD305: =IF('Jilla Parishad Income & Expendi'!AC305="", "", VALUE(SUBSTITUTE('Jilla Parishad Income & Expendi'!AC305, ",", "")))
A306: Aurangabad | B306: =IF('Jilla Parishad Income & Expendi'!B306="", "", VALUE(SUBSTITUTE('Jilla Parishad Income & Expendi'!B306, ",", ""))) -> 2020 | C306: =IF('Jilla Parishad Income & Expendi'!C306="", "", VALUE(SUBSTITUTE('Jilla Parishad Income & Expendi'!C306, ",", ""))) -> 325500.28 | D306: =IF('Jilla Parishad Income & Expendi'!D306="", "", VALUE(SUBSTITUTE('Jilla Parishad Income & Expendi'!D306, ",", ""))) -> 1077.12 | E306: =IF('Jilla Parishad Income & Expendi'!E306="", "", VALUE(SUBSTITUTE('Jilla Parishad Income & Expendi'!E306, ",", ""))) -> 74278 | F306: =IF('Jilla Parishad Income & Expendi'!F306="", "", VALUE(SUBSTITUTE('Jilla Parishad Income & Expendi'!F306, ",", ""))) -> 0 | G306: =IF('Jilla Parishad Income & Expendi'!G306="", "", VALUE(SUBSTITUTE('Jilla Parishad Income & Expendi'!G306, ",", ""))) -> 0 | H306: =IF('Jilla Parishad Income & Expendi'!H306="", "", VALUE(SUBSTITUTE('Jilla Parishad Income & Expendi'!H306, ",", ""))) -> 0 | I306: =IF('Jilla Parishad Income & Expendi'!I306="", "", VALUE(SUBSTITUTE('Jilla Parishad Income & Expendi'!I306, ",", ""))) -> 0 | J306: =IF('Jilla Parishad Income & Expendi'!J306="", "", VALUE(SUBSTITUTE('Jilla Parishad Income & Expendi'!J306, ",", ""))) -> 7076.17 | K306: =SUM(F306:J306) -> 7076.17 | L306: =IF('Jilla Parishad Income & Expendi'!K306="", "", VALUE(SUBSTITUTE('Jilla Parishad Income & Expendi'!K306, ",", ""))) -> 2882.84 | M306: =IF('Jilla Parishad Income & Expendi'!L306="", "", VALUE(SUBSTITUTE('Jilla Parishad Income & Expendi'!L306, ",", ""))) -> 133171 | N306: =IF('Jilla Parishad Income & Expendi'!M306="", "", VALUE(SUBSTITUTE('Jilla Parishad Income & Expendi'!M306, ",", ""))) -> 218485 | O306: =IF('Jilla Parishad Income & Expendi'!N306="", "", VALUE(SUBSTITUTE('Jilla Parishad Income & Expendi'!N306, ",", ""))) -> 543985 | P306: =IF('Jilla Parishad Income & Expendi'!O306="", "", VALUE(SUBSTITUTE('Jilla Parishad Income & Expendi'!O306, ",", ""))) -> 6456.97 | Q306: =IF('Jilla Parishad Income & Expendi'!P306="", "", VALUE(SUBSTITUTE('Jilla Parishad Income & Expendi'!P306, ",", ""))) -> 57627.74 | R306: =IF('Jilla Parishad Income & Expendi'!Q306="", "", VALUE(SUBSTITUTE('Jilla Parishad Income & Expendi'!Q306, ",", ""))) -> 794.15 | S306: =IF('Jilla Parishad Income & Expendi'!R306="", "", VALUE(SUBSTITUTE('Jilla Parishad Income & Expendi'!R306, ",", ""))) -> 834.63 | ... AD306: =IF('Jilla Parishad Income & Expendi'!AC306="", "", VALUE(SUBSTITUTE('Jilla Parishad Income & Expendi'!AC306, ",", "")))
A307: Aurangabad | B307: =IF('Jilla Parishad Income & Expendi'!B307="", "", VALUE(SUBSTITUTE('Jilla Parishad Income & Expendi'!B307, ",", ""))) -> 2021 | C307: =IF('Jilla Parishad Income & Expendi'!C307="", "", VALUE(SUBSTITUTE('Jilla Parishad Income & Expendi'!C307, ",", ""))) -> 473822.41 | D307: =IF('Jilla Parishad Income & Expendi'!D307="", "", VALUE(SUBSTITUTE('Jilla Parishad Income & Expendi'!D307, ",", ""))) -> 1532.1 | E307: =IF('Jilla Parishad Income & Expendi'!E307="", "", VALUE(SUBSTITUTE('Jilla Parishad Income & Expendi'!E307, ",", ""))) | F307: =IF('Jilla Parishad Income & Expendi'!F307="", "", VALUE(SUBSTITUTE('Jilla Parishad Income & Expendi'!F307, ",", ""))) -> 96789.8 | G307: =IF('Jilla Parishad Income & Expendi'!G307="", "", VALUE(SUBSTITUTE('Jilla Parishad Income & Expendi'!G307, ",", ""))) -> 20981.16 | H307: =IF('Jilla Parishad Income & Expendi'!H307="", "", VALUE(SUBSTITUTE('Jilla Parishad Income & Expendi'!H307, ",", ""))) -> 7143.17 | I307: =IF('Jilla Parishad Income & Expendi'!I307="", "", VALUE(SUBSTITUTE('Jilla Parishad Income & Expendi'!I307, ",", ""))) -> 0 | J307: =IF('Jilla Parishad Income & Expendi'!J307="", "", VALUE(SUBSTITUTE('Jilla Parishad Income & Expendi'!J307, ",", ""))) -> 8692.45 | K307: =SUM(F307:J307) -> 133606.58 | L307: =IF('Jilla Parishad Income & Expendi'!K307="", "", VALUE(SUBSTITUTE('Jilla Parishad Income & Expendi'!K307, ",", ""))) -> 0 | M307: =IF('Jilla Parishad Income & Expendi'!L307="", "", VALUE(SUBSTITUTE('Jilla Parishad Income & Expendi'!L307, ",", ""))) -> 23211.06 | N307: =IF('Jilla Parishad Income & Expendi'!M307="", "", VALUE(SUBSTITUTE('Jilla Parishad Income & Expendi'!M307, ",", ""))) -> 158350 | O307: =IF('Jilla Parishad Income & Expendi'!N307="", "", VALUE(SUBSTITUTE('Jilla Parishad Income & Expendi'!N307, ",", ""))) -> 632172 | P307: =IF('Jilla Parishad Income & Expendi'!O307="", "", VALUE(SUBSTITUTE('Jilla Parishad Income & Expendi'!O307, ",", ""))) -> 16089.24 | Q307: =IF('Jilla Parishad Income & Expendi'!P307="", "", VALUE(SUBSTITUTE('Jilla Parishad Income & Expendi'!P307, ",", ""))) -> 59965.19 | R307: =IF('Jilla Parishad Income & Expendi'!Q307="", "", VALUE(SUBSTITUTE('Jilla Parishad Income & Expendi'!Q307, ",", ""))) -> 2822.1 | S307: =IF('Jilla Parishad Income & Expendi'!R307="", "", VALUE(SUBSTITUTE('Jilla Parishad Income & Expendi'!R307, ",", ""))) -> 550.29 | ... AD307: =IF('Jilla Parishad Income & Expendi'!AC307="", "", VALUE(SUBSTITUTE('Jilla Parishad Income & Expendi'!AC307, ",", "")))
A308: Beed | B308: =IF('Jilla Parishad Income & Expendi'!B308="", "", VALUE(SUBSTITUTE('Jilla Parishad Income & Expendi'!B308, ",", ""))) -> 2013 | C308: =IF('Jilla Parishad Income & Expendi'!C308="", "", VALUE(SUBSTITUTE('Jilla Parishad Income & Expendi'!C308, ",", ""))) -> 22.64 | D308: =IF('Jilla Parishad Income & Expendi'!D308="", "", VALUE(SUBSTITUTE('Jilla Parishad Income & Expendi'!D308, ",", ""))) -> 2234.14 | E308: =IF('Jilla Parishad Income & Expendi'!E308="", "", VALUE(SUBSTITUTE('Jilla Parishad Income & Expendi'!E308, ",", ""))) | F308: =IF('Jilla Parishad Income & Expendi'!F308="", "", VALUE(SUBSTITUTE('Jilla Parishad Income & Expendi'!F308, ",", ""))) | G308: =IF('Jilla Parishad Income & Expendi'!G308="", "", VALUE(SUBSTITUTE('Jilla Parishad Income & Expendi'!G308, ",", ""))) -> 0 | H308: =IF('Jilla Parishad Income & Expendi'!H308="", "", VALUE(SUBSTITUTE('Jilla Parishad Income & Expendi'!H308, ",", ""))) -> 0 | I308: =IF('Jilla Parishad Income & Expendi'!I308="", "", VALUE(SUBSTITUTE('Jilla Parishad Income & Expendi'!I308, ",", ""))) -> 169.97 | J308: =IF('Jilla Parishad Income & Expendi'!J308="", "", VALUE(SUBSTITUTE('Jilla Parishad Income & Expendi'!J308, ",", ""))) -> 0 | K308: =SUM(F308:J308) -> 169.97 | L308: =IF('Jilla Parishad Income & Expendi'!K308="", "", VALUE(SUBSTITUTE('Jilla Parishad Income & Expendi'!K308, ",", ""))) -> 181.72 | M308: =IF('Jilla Parishad Income & Expendi'!L308="", "", VALUE(SUBSTITUTE('Jilla Parishad Income & Expendi'!L308, ",", ""))) -> 680.72 | N308: =IF('Jilla Parishad Income & Expendi'!M308="", "", VALUE(SUBSTITUTE('Jilla Parishad Income & Expendi'!M308, ",", ""))) -> 3267 | O308: =IF('Jilla Parishad Income & Expendi'!N308="", "", VALUE(SUBSTITUTE('Jilla Parishad Income & Expendi'!N308, ",", ""))) -> 3289 | P308: =IF('Jilla Parishad Income & Expendi'!O308="", "", VALUE(SUBSTITUTE('Jilla Parishad Income & Expendi'!O308, ",", ""))) -> 321.33 | Q308: =IF('Jilla Parishad Income & Expendi'!P308="", "", VALUE(SUBSTITUTE('Jilla Parishad Income & Expendi'!P308, ",", ""))) -> 216.79 | R308: =IF('Jilla Parishad Income & Expendi'!Q308="", "", VALUE(SUBSTITUTE('Jilla Parishad Income & Expendi'!Q308, ",", ""))) -> 923.37 | S308: =IF('Jilla Parishad Income & Expendi'!R308="", "", VALUE(SUBSTITUTE('Jilla Parishad Income & Expendi'!R308, ",", ""))) -> 55 | ... AD308: =IF('Jilla Parishad Income & Expendi'!AC308="", "", VALUE(SUBSTITUTE('Jilla Parishad Income & Expendi'!AC308, ",", "")))
A309: Beed | B309: =IF('Jilla Parishad Income & Expendi'!B309="", "", VALUE(SUBSTITUTE('Jilla Parishad Income & Expendi'!B309, ",", ""))) -> 2014 | C309: =IF('Jilla Parishad Income & Expendi'!C309="", "", VALUE(SUBSTITUTE('Jilla Parishad Income & Expendi'!C309, ",", ""))) -> 47031.56 | D309: =IF('Jilla Parishad Income & Expendi'!D309="", "", VALUE(SUBSTITUTE('Jilla Parishad Income & Expendi'!D309, ",", ""))) -> 0 | E309: =IF('Jilla Parishad Income & Expendi'!E309="", "", VALUE(SUBSTITUTE('Jilla Parishad Income & Expendi'!E309, ",", ""))) | F309: =IF('Jilla Parishad Income & Expendi'!F309="", "", VALUE(SUBSTITUTE('Jilla Parishad Income & Expendi'!F309, ",", ""))) -> 0 | G309: =IF('Jilla Parishad Income & Expendi'!G309="", "", VALUE(SUBSTITUTE('Jilla Parishad Income & Expendi'!G309, ",", ""))) -> 38925.22 | H309: =IF('Jilla Parishad Income & Expendi'!H309="", "", VALUE(SUBSTITUTE('Jilla Parishad Income & Expendi'!H309, ",", ""))) -> 43734.32 | I309: =IF('Jilla Parishad Income & Expendi'!I309="", "", VALUE(SUBSTITUTE('Jilla Parishad Income & Expendi'!I309, ",", ""))) -> 2124.9 | J309: =IF('Jilla Parishad Income & Expendi'!J309="", "", VALUE(SUBSTITUTE('Jilla Parishad Income & Expendi'!J309, ",", ""))) -> 7206.58 | K309: =SUM(F309:J309) -> 91991.02 | L309: =IF('Jilla Parishad Income & Expendi'!K309="", "", VALUE(SUBSTITUTE('Jilla Parishad Income & Expendi'!K309, ",", ""))) -> 69896.49 | M309: =IF('Jilla Parishad Income & Expendi'!L309="", "", VALUE(SUBSTITUTE('Jilla Parishad Income & Expendi'!L309, ",", ""))) -> 2046.92 | N309: =IF('Jilla Parishad Income & Expendi'!M309="", "", VALUE(SUBSTITUTE('Jilla Parishad Income & Expendi'!M309, ",", ""))) -> 163934 | O309: =IF('Jilla Parishad Income & Expendi'!N309="", "", VALUE(SUBSTITUTE('Jilla Parishad Income & Expendi'!N309, ",", ""))) -> 210966 | P309: =IF('Jilla Parishad Income & Expendi'!O309="", "", VALUE(SUBSTITUTE('Jilla Parishad Income & Expendi'!O309, ",", ""))) -> 8526.27 | Q309: =IF('Jilla Parishad Income & Expendi'!P309="", "", VALUE(SUBSTITUTE('Jilla Parishad Income & Expendi'!P309, ",", ""))) -> 48716.63 | R309: =IF('Jilla Parishad Income & Expendi'!Q309="", "", VALUE(SUBSTITUTE('Jilla Parishad Income & Expendi'!Q309, ",", ""))) -> 7382.33 | S309: =IF('Jilla Parishad Income & Expendi'!R309="", "", VALUE(SUBSTITUTE('Jilla Parishad Income & Expendi'!R309, ",", ""))) -> 2299.13 | ... AD309: =IF('Jilla Parishad Income & Expendi'!AC309="", "", VALUE(SUBSTITUTE('Jilla Parishad Income & Expendi'!AC309, ",", "")))
A310: Beed | B310: =IF('Jilla Parishad Income & Expendi'!B310="", "", VALUE(SUBSTITUTE('Jilla Parishad Income & Expendi'!B310, ",", ""))) -> 2015 | C310: =IF('Jilla Parishad Income & Expendi'!C310="", "", VALUE(SUBSTITUTE('Jilla Parishad Income & Expendi'!C310, ",", ""))) -> 45824 | D310: =IF('Jilla Parishad Income & Expendi'!D310="", "", VALUE(SUBSTITUTE('Jilla Parishad Income & Expendi'!D310, ",", ""))) -> 925 | E310: =IF('Jilla Parishad Income & Expendi'!E310="", "", VALUE(SUBSTITUTE('Jilla Parishad Income & Expendi'!E310, ",", ""))) | F310: =IF('Jilla Parishad Income & Expendi'!F310="", "", VALUE(SUBSTITUTE('Jilla Parishad Income & Expendi'!F310, ",", ""))) -> 0 | G310: =IF('Jilla Parishad Income & Expendi'!G310="", "", VALUE(SUBSTITUTE('Jilla Parishad Income & Expendi'!G310, ",", ""))) -> 57060 | H310: =IF('Jilla Parishad Income & Expendi'!H310="", "", VALUE(SUBSTITUTE('Jilla Parishad Income & Expendi'!H310, ",", ""))) -> 14265 | I310: =IF('Jilla Parishad Income & Expendi'!I310="", "", VALUE(SUBSTITUTE('Jilla Parishad Income & Expendi'!I310, ",", ""))) -> 39302 | J310: =IF('Jilla Parishad Income & Expendi'!J310="", "", VALUE(SUBSTITUTE('Jilla Parishad Income & Expendi'!J310, ",", ""))) -> 20727 | K310: =SUM(F310:J310) -> 131354 | L310: =IF('Jilla Parishad Income & Expendi'!K310="", "", VALUE(SUBSTITUTE('Jilla Parishad Income & Expendi'!K310, ",", ""))) -> 1075 | M310: =IF('Jilla Parishad Income & Expendi'!L310="", "", VALUE(SUBSTITUTE('Jilla Parishad Income & Expendi'!L310, ",", ""))) -> 1923 | N310: =IF('Jilla Parishad Income & Expendi'!M310="", "", VALUE(SUBSTITUTE('Jilla Parishad Income & Expendi'!M310, ",", ""))) -> 146689 | O310: =IF('Jilla Parishad Income & Expendi'!N310="", "", VALUE(SUBSTITUTE('Jilla Parishad Income & Expendi'!N310, ",", ""))) -> 192513 | P310: =IF('Jilla Parishad Income & Expendi'!O310="", "", VALUE(SUBSTITUTE('Jilla Parishad Income & Expendi'!O310, ",", ""))) -> 8761 | Q310: =IF('Jilla Parishad Income & Expendi'!P310="", "", VALUE(SUBSTITUTE('Jilla Parishad Income & Expendi'!P310, ",", ""))) -> 54361 | R310: =IF('Jilla Parishad Income & Expendi'!Q310="", "", VALUE(SUBSTITUTE('Jilla Parishad Income & Expendi'!Q310, ",", ""))) -> 2664 | S310: =IF('Jilla Parishad Income & Expendi'!R310="", "", VALUE(SUBSTITUTE('Jilla Parishad Income & Expendi'!R310, ",", ""))) -> 1814 | ... AD310: =IF('Jilla Parishad Income & Expendi'!AC310="", "", VALUE(SUBSTITUTE('Jilla Parishad Income & Expendi'!AC310, ",", "")))
A311: Beed | B311: =IF('Jilla Parishad Income & Expendi'!B311="", "", VALUE(SUBSTITUTE('Jilla Parishad Income & Expendi'!B311, ",", ""))) -> 2016 | C311: =IF('Jilla Parishad Income & Expendi'!C311="", "", VALUE(SUBSTITUTE('Jilla Parishad Income & Expendi'!C311, ",", ""))) -> 55286 | D311: =IF('Jilla Parishad Income & Expendi'!D311="", "", VALUE(SUBSTITUTE('Jilla Parishad Income & Expendi'!D311, ",", ""))) -> 83 | E311: =IF('Jilla Parishad Income & Expendi'!E311="", "", VALUE(SUBSTITUTE('Jilla Parishad Income & Expendi'!E311, ",", ""))) | F311: =IF('Jilla Parishad Income & Expendi'!F311="", "", VALUE(SUBSTITUTE('Jilla Parishad Income & Expendi'!F311, ",", ""))) -> 0 | G311: =IF('Jilla Parishad Income & Expendi'!G311="", "", VALUE(SUBSTITUTE('Jilla Parishad Income & Expendi'!G311, ",", ""))) -> 60006 | H311: =IF('Jilla Parishad Income & Expendi'!H311="", "", VALUE(SUBSTITUTE('Jilla Parishad Income & Expendi'!H311, ",", ""))) -> 13200 | I311: =IF('Jilla Parishad Income & Expendi'!I311="", "", VALUE(SUBSTITUTE('Jilla Parishad Income & Expendi'!I311, ",", ""))) -> 2273 | J311: =IF('Jilla Parishad Income & Expendi'!J311="", "", VALUE(SUBSTITUTE('Jilla Parishad Income & Expendi'!J311, ",", ""))) -> 21763 | K311: =SUM(F311:J311) -> 97242 | L311: =IF('Jilla Parishad Income & Expendi'!K311="", "", VALUE(SUBSTITUTE('Jilla Parishad Income & Expendi'!K311, ",", ""))) -> 1090 | M311: =IF('Jilla Parishad Income & Expendi'!L311="", "", VALUE(SUBSTITUTE('Jilla Parishad Income & Expendi'!L311, ",", ""))) -> 84104 | N311: =IF('Jilla Parishad Income & Expendi'!M311="", "", VALUE(SUBSTITUTE('Jilla Parishad Income & Expendi'!M311, ",", ""))) -> 187088 | O311: =IF('Jilla Parishad Income & Expendi'!N311="", "", VALUE(SUBSTITUTE('Jilla Parishad Income & Expendi'!N311, ",", ""))) -> 242374 | P311: =IF('Jilla Parishad Income & Expendi'!O311="", "", VALUE(SUBSTITUTE('Jilla Parishad Income & Expendi'!O311, ",", ""))) -> 8090 | Q311: =IF('Jilla Parishad Income & Expendi'!P311="", "", VALUE(SUBSTITUTE('Jilla Parishad Income & Expendi'!P311, ",", ""))) -> 55672 | R311: =IF('Jilla Parishad Income & Expendi'!Q311="", "", VALUE(SUBSTITUTE('Jilla Parishad Income & Expendi'!Q311, ",", ""))) -> 2081 | S311: =IF('Jilla Parishad Income & Expendi'!R311="", "", VALUE(SUBSTITUTE('Jilla Parishad Income & Expendi'!R311, ",", ""))) -> 4053 | ... AD311: =IF('Jilla Parishad Income & Expendi'!AC311="", "", VALUE(SUBSTITUTE('Jilla Parishad Income & Expendi'!AC311, ",", "")))
... A339: Kolhapur | B339: =IF('Jilla Parishad Income & Expendi'!B339="", "", VALUE(SUBSTITUTE('Jilla Parishad Income & Expendi'!B339, ",", ""))) -> 2020 | C339: =IF('Jilla Parishad Income & Expendi'!C339="", "", VALUE(SUBSTITUTE('Jilla Parishad Income & Expendi'!C339, ",", ""))) -> 32906 | D339: =IF('Jilla Parishad Income & Expendi'!D339="", "", VALUE(SUBSTITUTE('Jilla Parishad Income & Expendi'!D339, ",", ""))) -> 2673 | E339: =IF('Jilla Parishad Income & Expendi'!E339="", "", VALUE(SUBSTITUTE('Jilla Parishad Income & Expendi'!E339, ",", ""))) | F339: =IF('Jilla Parishad Income & Expendi'!F339="", "", VALUE(SUBSTITUTE('Jilla Parishad Income & Expendi'!F339, ",", ""))) -> 223481 | G339: =IF('Jilla Parishad Income & Expendi'!G339="", "", VALUE(SUBSTITUTE('Jilla Parishad Income & Expendi'!G339, ",", ""))) -> 20579 | H339: =IF('Jilla Parishad Income & Expendi'!H339="", "", VALUE(SUBSTITUTE('Jilla Parishad Income & Expendi'!H339, ",", ""))) -> 8700 | I339: =IF('Jilla Parishad Income & Expendi'!I339="", "", VALUE(SUBSTITUTE('Jilla Parishad Income & Expendi'!I339, ",", ""))) -> 868 | J339: =IF('Jilla Parishad Income & Expendi'!J339="", "", VALUE(SUBSTITUTE('Jilla Parishad Income & Expendi'!J339, ",", ""))) -> 3315 | K339: =SUM(F339:J339) -> 256943 | L339: =IF('Jilla Parishad Income & Expendi'!K339="", "", VALUE(SUBSTITUTE('Jilla Parishad Income & Expendi'!K339, ",", ""))) -> 0 | M339: =IF('Jilla Parishad Income & Expendi'!L339="", "", VALUE(SUBSTITUTE('Jilla Parishad Income & Expendi'!L339, ",", ""))) -> 29777 | N339: =IF('Jilla Parishad Income & Expendi'!M339="", "", VALUE(SUBSTITUTE('Jilla Parishad Income & Expendi'!M339, ",", ""))) -> 289393 | O339: =IF('Jilla Parishad Income & Expendi'!N339="", "", VALUE(SUBSTITUTE('Jilla Parishad Income & Expendi'!N339, ",", ""))) -> 322299 | P339: =IF('Jilla Parishad Income & Expendi'!O339="", "", VALUE(SUBSTITUTE('Jilla Parishad Income & Expendi'!O339, ",", ""))) -> 93616 | Q339: =IF('Jilla Parishad Income & Expendi'!P339="", "", VALUE(SUBSTITUTE('Jilla Parishad Income & Expendi'!P339, ",", ""))) -> 3387 | R339: =IF('Jilla Parishad Income & Expendi'!Q339="", "", VALUE(SUBSTITUTE('Jilla Parishad Income & Expendi'!Q339, ",", ""))) -> 1486 | S339: =IF('Jilla Parishad Income & Expendi'!R339="", "", VALUE(SUBSTITUTE('Jilla Parishad Income & Expendi'!R339, ",", ""))) -> 900 | ... AD339: =IF('Jilla Parishad Income & Expendi'!AC339="", "", VALUE(SUBSTITUTE('Jilla Parishad Income & Expendi'!AC339, ",", "")))
B340: =IF('Jilla Parishad Income & Expendi'!B340="", "", VALUE(SUBSTITUTE('Jilla Parishad Income & Expendi'!B340, ",", ""))) | C340: =IF('Jilla Parishad Income & Expendi'!C340="", "", VALUE(SUBSTITUTE('Jilla Parishad Income & Expendi'!C340, ",", ""))) | D340: =IF('Jilla Parishad Income & Expendi'!D340="", "", VALUE(SUBSTITUTE('Jilla Parishad Income & Expendi'!D340, ",", ""))) | E340: =IF('Jilla Parishad Income & Expendi'!E340="", "", VALUE(SUBSTITUTE('Jilla Parishad Income & Expendi'!E340, ",", ""))) | F340: =IF('Jilla Parishad Income & Expendi'!F340="", "", VALUE(SUBSTITUTE('Jilla Parishad Income & Expendi'!F340, ",", ""))) | G340: =IF('Jilla Parishad Income & Expendi'!G340="", "", VALUE(SUBSTITUTE('Jilla Parishad Income & Expendi'!G340, ",", ""))) | H340: =IF('Jilla Parishad Income & Expendi'!H340="", "", VALUE(SUBSTITUTE('Jilla Parishad Income & Expendi'!H340, ",", ""))) | I340: =IF('Jilla Parishad Income & Expendi'!I340="", "", VALUE(SUBSTITUTE('Jilla Parishad Income & Expendi'!I340, ",", ""))) | J340: =IF('Jilla Parishad Income & Expendi'!J340="", "", VALUE(SUBSTITUTE('Jilla Parishad Income & Expendi'!J340, ",", ""))) | L340: =IF('Jilla Parishad Income & Expendi'!K340="", "", VALUE(SUBSTITUTE('Jilla Parishad Income & Expendi'!K340, ",", ""))) | M340: =IF('Jilla Parishad Income & Expendi'!L340="", "", VALUE(SUBSTITUTE('Jilla Parishad Income & Expendi'!L340, ",", ""))) | N340: =IF('Jilla Parishad Income & Expendi'!M340="", "", VALUE(SUBSTITUTE('Jilla Parishad Income & Expendi'!M340, ",", ""))) | O340: =IF('Jilla Parishad Income & Expendi'!N340="", "", VALUE(SUBSTITUTE('Jilla Parishad Income & Expendi'!N340, ",", ""))) | P340: =IF('Jilla Parishad Income & Expendi'!O340="", "", VALUE(SUBSTITUTE('Jilla Parishad Income & Expendi'!O340, ",", ""))) | Q340: =IF('Jilla Parishad Income & Expendi'!P340="", "", VALUE(SUBSTITUTE('Jilla Parishad Income & Expendi'!P340, ",", ""))) | R340: =IF('Jilla Parishad Income & Expendi'!Q340="", "", VALUE(SUBSTITUTE('Jilla Parishad Income & Expendi'!Q340, ",", ""))) | S340: =IF('Jilla Parishad Income & Expendi'!R340="", "", VALUE(SUBSTITUTE('Jilla Parishad Income & Expendi'!R340, ",", ""))) | ... AD340: =IF('Jilla Parishad Income & Expendi'!AC340="", "", VALUE(SUBSTITUTE('Jilla Parishad Income & Expendi'!AC340, ",", "")))
B341: =IF('Jilla Parishad Income & Expendi'!B341="", "", VALUE(SUBSTITUTE('Jilla Parishad Income & Expendi'!B341, ",", ""))) | C341: =IF('Jilla Parishad Income & Expendi'!C341="", "", VALUE(SUBSTITUTE('Jilla Parishad Income & Expendi'!C341, ",", ""))) | D341: =IF('Jilla Parishad Income & Expendi'!D341="", "", VALUE(SUBSTITUTE('Jilla Parishad Income & Expendi'!D341, ",", ""))) | E341: =IF('Jilla Parishad Income & Expendi'!E341="", "", VALUE(SUBSTITUTE('Jilla Parishad Income & Expendi'!E341, ",", ""))) | F341: =IF('Jilla Parishad Income & Expendi'!F341="", "", VALUE(SUBSTITUTE('Jilla Parishad Income & Expendi'!F341, ",", ""))) | G341: =IF('Jilla Parishad Income & Expendi'!G341="", "", VALUE(SUBSTITUTE('Jilla Parishad Income & Expendi'!G341, ",", ""))) | H341: =IF('Jilla Parishad Income & Expendi'!H341="", "", VALUE(SUBSTITUTE('Jilla Parishad Income & Expendi'!H341, ",", ""))) | I341: =IF('Jilla Parishad Income & Expendi'!I341="", "", VALUE(SUBSTITUTE('Jilla Parishad Income & Expendi'!I341, ",", ""))) | J341: =IF('Jilla Parishad Income & Expendi'!J341="", "", VALUE(SUBSTITUTE('Jilla Parishad Income & Expendi'!J341, ",", ""))) | L341: =IF('Jilla Parishad Income & Expendi'!K341="", "", VALUE(SUBSTITUTE('Jilla Parishad Income & Expendi'!K341, ",", ""))) | M341: =IF('Jilla Parishad Income & Expendi'!L341="", "", VALUE(SUBSTITUTE('Jilla Parishad Income & Expendi'!L341, ",", ""))) | N341: =IF('Jilla Parishad Income & Expendi'!M341="", "", VALUE(SUBSTITUTE('Jilla Parishad Income & Expendi'!M341, ",", ""))) | O341: =IF('Jilla Parishad Income & Expendi'!N341="", "", VALUE(SUBSTITUTE('Jilla Parishad Income & Expendi'!N341, ",", ""))) | P341: =IF('Jilla Parishad Income & Expendi'!O341="", "", VALUE(SUBSTITUTE('Jilla Parishad Income & Expendi'!O341, ",", ""))) | Q341: =IF('Jilla Parishad Income & Expendi'!P341="", "", VALUE(SUBSTITUTE('Jilla Parishad Income & Expendi'!P341, ",", ""))) | R341: =IF('Jilla Parishad Income & Expendi'!Q341="", "", VALUE(SUBSTITUTE('Jilla Parishad Income & Expendi'!Q341, ",", ""))) | S341: =IF('Jilla Parishad Income & Expendi'!R341="", "", VALUE(SUBSTITUTE('Jilla Parishad Income & Expendi'!R341, ",", ""))) | ... AD341: =IF('Jilla Parishad Income & Expendi'!AC341="", "", VALUE(SUBSTITUTE('Jilla Parishad Income & Expendi'!AC341, ",", "")))
B342: =IF('Jilla Parishad Income & Expendi'!B342="", "", VALUE(SUBSTITUTE('Jilla Parishad Income & Expendi'!B342, ",", ""))) | C342: =IF('Jilla Parishad Income & Expendi'!C342="", "", VALUE(SUBSTITUTE('Jilla Parishad Income & Expendi'!C342, ",", ""))) | D342: =IF('Jilla Parishad Income & Expendi'!D342="", "", VALUE(SUBSTITUTE('Jilla Parishad Income & Expendi'!D342, ",", ""))) | E342: =IF('Jilla Parishad Income & Expendi'!E342="", "", VALUE(SUBSTITUTE('Jilla Parishad Income & Expendi'!E342, ",", ""))) | F342: =IF('Jilla Parishad Income & Expendi'!F342="", "", VALUE(SUBSTITUTE('Jilla Parishad Income & Expendi'!F342, ",", ""))) | G342: =IF('Jilla Parishad Income & Expendi'!G342="", "", VALUE(SUBSTITUTE('Jilla Parishad Income & Expendi'!G342, ",", ""))) | H342: =IF('Jilla Parishad Income & Expendi'!H342="", "", VALUE(SUBSTITUTE('Jilla Parishad Income & Expendi'!H342, ",", ""))) | I342: =IF('Jilla Parishad Income & Expendi'!I342="", "", VALUE(SUBSTITUTE('Jilla Parishad Income & Expendi'!I342, ",", ""))) | J342: =IF('Jilla Parishad Income & Expendi'!J342="", "", VALUE(SUBSTITUTE('Jilla Parishad Income & Expendi'!J342, ",", ""))) | L342: =IF('Jilla Parishad Income & Expendi'!K342="", "", VALUE(SUBSTITUTE('Jilla Parishad Income & Expendi'!K342, ",", ""))) | M342: =IF('Jilla Parishad Income & Expendi'!L342="", "", VALUE(SUBSTITUTE('Jilla Parishad Income & Expendi'!L342, ",", ""))) | N342: =IF('Jilla Parishad Income & Expendi'!M342="", "", VALUE(SUBSTITUTE('Jilla Parishad Income & Expendi'!M342, ",", ""))) | O342: =IF('Jilla Parishad Income & Expendi'!N342="", "", VALUE(SUBSTITUTE('Jilla Parishad Income & Expendi'!N342, ",", ""))) | P342: =IF('Jilla Parishad Income & Expendi'!O342="", "", VALUE(SUBSTITUTE('Jilla Parishad Income & Expendi'!O342, ",", ""))) | Q342: =IF('Jilla Parishad Income & Expendi'!P342="", "", VALUE(SUBSTITUTE('Jilla Parishad Income & Expendi'!P342, ",", ""))) | R342: =IF('Jilla Parishad Income & Expendi'!Q342="", "", VALUE(SUBSTITUTE('Jilla Parishad Income & Expendi'!Q342, ",", ""))) | S342: =IF('Jilla Parishad Income & Expendi'!R342="", "", VALUE(SUBSTITUTE('Jilla Parishad Income & Expendi'!R342, ",", ""))) | ... AD342: =IF('Jilla Parishad Income & Expendi'!AC342="", "", VALUE(SUBSTITUTE('Jilla Parishad Income & Expendi'!AC342, ",", "")))
B343: =IF('Jilla Parishad Income & Expendi'!B343="", "", VALUE(SUBSTITUTE('Jilla Parishad Income & Expendi'!B343, ",", ""))) | C343: =IF('Jilla Parishad Income & Expendi'!C343="", "", VALUE(SUBSTITUTE('Jilla Parishad Income & Expendi'!C343, ",", ""))) | D343: =IF('Jilla Parishad Income & Expendi'!D343="", "", VALUE(SUBSTITUTE('Jilla Parishad Income & Expendi'!D343, ",", ""))) | E343: =IF('Jilla Parishad Income & Expendi'!E343="", "", VALUE(SUBSTITUTE('Jilla Parishad Income & Expendi'!E343, ",", ""))) | F343: =IF('Jilla Parishad Income & Expendi'!F343="", "", VALUE(SUBSTITUTE('Jilla Parishad Income & Expendi'!F343, ",", ""))) | G343: =IF('Jilla Parishad Income & Expendi'!G343="", "", VALUE(SUBSTITUTE('Jilla Parishad Income & Expendi'!G343, ",", ""))) | H343: =IF('Jilla Parishad Income & Expendi'!H343="", "", VALUE(SUBSTITUTE('Jilla Parishad Income & Expendi'!H343, ",", ""))) | I343: =IF('Jilla Parishad Income & Expendi'!I343="", "", VALUE(SUBSTITUTE('Jilla Parishad Income & Expendi'!I343, ",", ""))) | J343: =IF('Jilla Parishad Income & Expendi'!J343="", "", VALUE(SUBSTITUTE('Jilla Parishad Income & Expendi'!J343, ",", ""))) | L343: =IF('Jilla Parishad Income & Expendi'!K343="", "", VALUE(SUBSTITUTE('Jilla Parishad Income & Expendi'!K343, ",", ""))) | M343: =IF('Jilla Parishad Income & Expendi'!L343="", "", VALUE(SUBSTITUTE('Jilla Parishad Income & Expendi'!L343, ",", ""))) | N343: =IF('Jilla Parishad Income & Expendi'!M343="", "", VALUE(SUBSTITUTE('Jilla Parishad Income & Expendi'!M343, ",", ""))) | O343: =IF('Jilla Parishad Income & Expendi'!N343="", "", VALUE(SUBSTITUTE('Jilla Parishad Income & Expendi'!N343, ",", ""))) | P343: =IF('Jilla Parishad Income & Expendi'!O343="", "", VALUE(SUBSTITUTE('Jilla Parishad Income & Expendi'!O343, ",", ""))) | Q343: =IF('Jilla Parishad Income & Expendi'!P343="", "", VALUE(SUBSTITUTE('Jilla Parishad Income & Expendi'!P343, ",", ""))) | R343: =IF('Jilla Parishad Income & Expendi'!Q343="", "", VALUE(SUBSTITUTE('Jilla Parishad Income & Expendi'!Q343, ",", ""))) | S343: =IF('Jilla Parishad Income & Expendi'!R343="", "", VALUE(SUBSTITUTE('Jilla Parishad Income & Expendi'!R343, ",", ""))) | ... AD343: =IF('Jilla Parishad Income & Expendi'!AC343="", "", VALUE(SUBSTITUTE('Jilla Parishad Income & Expendi'!AC343, ",", "")))
B344: =IF('Jilla Parishad Income & Expendi'!B344="", "", VALUE(SUBSTITUTE('Jilla Parishad Income & Expendi'!B344, ",", ""))) | C344: =IF('Jilla Parishad Income & Expendi'!C344="", "", VALUE(SUBSTITUTE('Jilla Parishad Income & Expendi'!C344, ",", ""))) | D344: =IF('Jilla Parishad Income & Expendi'!D344="", "", VALUE(SUBSTITUTE('Jilla Parishad Income & Expendi'!D344, ",", ""))) | E344: =IF('Jilla Parishad Income & Expendi'!E344="", "", VALUE(SUBSTITUTE('Jilla Parishad Income & Expendi'!E344, ",", ""))) | F344: =IF('Jilla Parishad Income & Expendi'!F344="", "", VALUE(SUBSTITUTE('Jilla Parishad Income & Expendi'!F344, ",", ""))) | G344: =IF('Jilla Parishad Income & Expendi'!G344="", "", VALUE(SUBSTITUTE('Jilla Parishad Income & Expendi'!G344, ",", ""))) | H344: =IF('Jilla Parishad Income & Expendi'!H344="", "", VALUE(SUBSTITUTE('Jilla Parishad Income & Expendi'!H344, ",", ""))) | I344: =IF('Jilla Parishad Income & Expendi'!I344="", "", VALUE(SUBSTITUTE('Jilla Parishad Income & Expendi'!I344, ",", ""))) | J344: =IF('Jilla Parishad Income & Expendi'!J344="", "", VALUE(SUBSTITUTE('Jilla Parishad Income & Expendi'!J344, ",", ""))) | L344: =IF('Jilla Parishad Income & Expendi'!K344="", "", VALUE(SUBSTITUTE('Jilla Parishad Income & Expendi'!K344, ",", ""))) | M344: =IF('Jilla Parishad Income & Expendi'!L344="", "", VALUE(SUBSTITUTE('Jilla Parishad Income & Expendi'!L344, ",", ""))) | N344: =IF('Jilla Parishad Income & Expendi'!M344="", "", VALUE(SUBSTITUTE('Jilla Parishad Income & Expendi'!M344, ",", ""))) | O344: =IF('Jilla Parishad Income & Expendi'!N344="", "", VALUE(SUBSTITUTE('Jilla Parishad Income & Expendi'!N344, ",", ""))) | P344: =IF('Jilla Parishad Income & Expendi'!O344="", "", VALUE(SUBSTITUTE('Jilla Parishad Income & Expendi'!O344, ",", ""))) | Q344: =IF('Jilla Parishad Income & Expendi'!P344="", "", VALUE(SUBSTITUTE('Jilla Parishad Income & Expendi'!P344, ",", ""))) | R344: =IF('Jilla Parishad Income & Expendi'!Q344="", "", VALUE(SUBSTITUTE('Jilla Parishad Income & Expendi'!Q344, ",", ""))) | S344: =IF('Jilla Parishad Income & Expendi'!R344="", "", VALUE(SUBSTITUTE('Jilla Parishad Income & Expendi'!R344, ",", ""))) | ... AD344: =IF('Jilla Parishad Income & Expendi'!AC344="", "", VALUE(SUBSTITUTE('Jilla Parishad Income & Expendi'!AC344, ",", "")))
B345: =IF('Jilla Parishad Income & Expendi'!B345="", "", VALUE(SUBSTITUTE('Jilla Parishad Income & Expendi'!B345, ",", ""))) | C345: =IF('Jilla Parishad Income & Expendi'!C345="", "", VALUE(SUBSTITUTE('Jilla Parishad Income & Expendi'!C345, ",", ""))) | D345: =IF('Jilla Parishad Income & Expendi'!D345="", "", VALUE(SUBSTITUTE('Jilla Parishad Income & Expendi'!D345, ",", ""))) | E345: =IF('Jilla Parishad Income & Expendi'!E345="", "", VALUE(SUBSTITUTE('Jilla Parishad Income & Expendi'!E345, ",", ""))) | F345: =IF('Jilla Parishad Income & Expendi'!F345="", "", VALUE(SUBSTITUTE('Jilla Parishad Income & Expendi'!F345, ",", ""))) | G345: =IF('Jilla Parishad Income & Expendi'!G345="", "", VALUE(SUBSTITUTE('Jilla Parishad Income & Expendi'!G345, ",", ""))) | H345: =IF('Jilla Parishad Income & Expendi'!H345="", "", VALUE(SUBSTITUTE('Jilla Parishad Income & Expendi'!H345, ",", ""))) | I345: =IF('Jilla Parishad Income & Expendi'!I345="", "", VALUE(SUBSTITUTE('Jilla Parishad Income & Expendi'!I345, ",", ""))) | J345: =IF('Jilla Parishad Income & Expendi'!J345="", "", VALUE(SUBSTITUTE('Jilla Parishad Income & Expendi'!J345, ",", ""))) | L345: =IF('Jilla Parishad Income & Expendi'!K345="", "", VALUE(SUBSTITUTE('Jilla Parishad Income & Expendi'!K345, ",", ""))) | M345: =IF('Jilla Parishad Income & Expendi'!L345="", "", VALUE(SUBSTITUTE('Jilla Parishad Income & Expendi'!L345, ",", ""))) | N345: =IF('Jilla Parishad Income & Expendi'!M345="", "", VALUE(SUBSTITUTE('Jilla Parishad Income & Expendi'!M345, ",", ""))) | O345: =IF('Jilla Parishad Income & Expendi'!N345="", "", VALUE(SUBSTITUTE('Jilla Parishad Income & Expendi'!N345, ",", ""))) | P345: =IF('Jilla Parishad Income & Expendi'!O345="", "", VALUE(SUBSTITUTE('Jilla Parishad Income & Expendi'!O345, ",", ""))) | Q345: =IF('Jilla Parishad Income & Expendi'!P345="", "", VALUE(SUBSTITUTE('Jilla Parishad Income & Expendi'!P345, ",", ""))) | R345: =IF('Jilla Parishad Income & Expendi'!Q345="", "", VALUE(SUBSTITUTE('Jilla Parishad Income & Expendi'!Q345, ",", ""))) | S345: =IF('Jilla Parishad Income & Expendi'!R345="", "", VALUE(SUBSTITUTE('Jilla Parishad Income & Expendi'!R345, ",", ""))) | ... AD345: =IF('Jilla Parishad Income & Expendi'!AC345="", "", VALUE(SUBSTITUTE('Jilla Parishad Income & Expendi'!AC345, ",", "")))
B346: =IF('Jilla Parishad Income & Expendi'!B346="", "", VALUE(SUBSTITUTE('Jilla Parishad Income & Expendi'!B346, ",", ""))) | C346: =IF('Jilla Parishad Income & Expendi'!C346="", "", VALUE(SUBSTITUTE('Jilla Parishad Income & Expendi'!C346, ",", ""))) | D346: =IF('Jilla Parishad Income & Expendi'!D346="", "", VALUE(SUBSTITUTE('Jilla Parishad Income & Expendi'!D346, ",", ""))) | E346: =IF('Jilla Parishad Income & Expendi'!E346="", "", VALUE(SUBSTITUTE('Jilla Parishad Income & Expendi'!E346, ",", ""))) | F346: =IF('Jilla Parishad Income & Expendi'!F346="", "", VALUE(SUBSTITUTE('Jilla Parishad Income & Expendi'!F346, ",", ""))) | G346: =IF('Jilla Parishad Income & Expendi'!G346="", "", VALUE(SUBSTITUTE('Jilla Parishad Income & Expendi'!G346, ",", ""))) | H346: =IF('Jilla Parishad Income & Expendi'!H346="", "", VALUE(SUBSTITUTE('Jilla Parishad Income & Expendi'!H346, ",", ""))) | I346: =IF('Jilla Parishad Income & Expendi'!I346="", "", VALUE(SUBSTITUTE('Jilla Parishad Income & Expendi'!I346, ",", ""))) | J346: =IF('Jilla Parishad Income & Expendi'!J346="", "", VALUE(SUBSTITUTE('Jilla Parishad Income & Expendi'!J346, ",", ""))) | L346: =IF('Jilla Parishad Income & Expendi'!K346="", "", VALUE(SUBSTITUTE('Jilla Parishad Income & Expendi'!K346, ",", ""))) | M346: =IF('Jilla Parishad Income & Expendi'!L346="", "", VALUE(SUBSTITUTE('Jilla Parishad Income & Expendi'!L346, ",", ""))) | N346: =IF('Jilla Parishad Income & Expendi'!M346="", "", VALUE(SUBSTITUTE('Jilla Parishad Income & Expendi'!M346, ",", ""))) | O346: =IF('Jilla Parishad Income & Expendi'!N346="", "", VALUE(SUBSTITUTE('Jilla Parishad Income & Expendi'!N346, ",", ""))) | P346: =IF('Jilla Parishad Income & Expendi'!O346="", "", VALUE(SUBSTITUTE('Jilla Parishad Income & Expendi'!O346, ",", ""))) | Q346: =IF('Jilla Parishad Income & Expendi'!P346="", "", VALUE(SUBSTITUTE('Jilla Parishad Income & Expendi'!P346, ",", ""))) | R346: =IF('Jilla Parishad Income & Expendi'!Q346="", "", VALUE(SUBSTITUTE('Jilla Parishad Income & Expendi'!Q346, ",", ""))) | S346: =IF('Jilla Parishad Income & Expendi'!R346="", "", VALUE(SUBSTITUTE('Jilla Parishad Income & Expendi'!R346, ",", ""))) | ... AD346: =IF('Jilla Parishad Income & Expendi'!AC346="", "", VALUE(SUBSTITUTE('Jilla Parishad Income & Expendi'!AC346, ",", "")))
B347: =IF('Jilla Parishad Income & Expendi'!B347="", "", VALUE(SUBSTITUTE('Jilla Parishad Income & Expendi'!B347, ",", ""))) | C347: =IF('Jilla Parishad Income & Expendi'!C347="", "", VALUE(SUBSTITUTE('Jilla Parishad Income & Expendi'!C347, ",", ""))) | D347: =IF('Jilla Parishad Income & Expendi'!D347="", "", VALUE(SUBSTITUTE('Jilla Parishad Income & Expendi'!D347, ",", ""))) | E347: =IF('Jilla Parishad Income & Expendi'!E347="", "", VALUE(SUBSTITUTE('Jilla Parishad Income & Expendi'!E347, ",", ""))) | F347: =IF('Jilla Parishad Income & Expendi'!F347="", "", VALUE(SUBSTITUTE('Jilla Parishad Income & Expendi'!F347, ",", ""))) | G347: =IF('Jilla Parishad Income & Expendi'!G347="", "", VALUE(SUBSTITUTE('Jilla Parishad Income & Expendi'!G347, ",", ""))) | H347: =IF('Jilla Parishad Income & Expendi'!H347="", "", VALUE(SUBSTITUTE('Jilla Parishad Income & Expendi'!H347, ",", ""))) | I347: =IF('Jilla Parishad Income & Expendi'!I347="", "", VALUE(SUBSTITUTE('Jilla Parishad Income & Expendi'!I347, ",", ""))) | J347: =IF('Jilla Parishad Income & Expendi'!J347="", "", VALUE(SUBSTITUTE('Jilla Parishad Income & Expendi'!J347, ",", ""))) | L347: =IF('Jilla Parishad Income & Expendi'!K347="", "", VALUE(SUBSTITUTE('Jilla Parishad Income & Expendi'!K347, ",", ""))) | M347: =IF('Jilla Parishad Income & Expendi'!L347="", "", VALUE(SUBSTITUTE('Jilla Parishad Income & Expendi'!L347, ",", ""))) | N347: =IF('Jilla Parishad Income & Expendi'!M347="", "", VALUE(SUBSTITUTE('Jilla Parishad Income & Expendi'!M347, ",", ""))) | O347: =IF('Jilla Parishad Income & Expendi'!N347="", "", VALUE(SUBSTITUTE('Jilla Parishad Income & Expendi'!N347, ",", ""))) | P347: =IF('Jilla Parishad Income & Expendi'!O347="", "", VALUE(SUBSTITUTE('Jilla Parishad Income & Expendi'!O347, ",", ""))) | Q347: =IF('Jilla Parishad Income & Expendi'!P347="", "", VALUE(SUBSTITUTE('Jilla Parishad Income & Expendi'!P347, ",", ""))) | R347: =IF('Jilla Parishad Income & Expendi'!Q347="", "", VALUE(SUBSTITUTE('Jilla Parishad Income & Expendi'!Q347, ",", ""))) | S347: =IF('Jilla Parishad Income & Expendi'!R347="", "", VALUE(SUBSTITUTE('Jilla Parishad Income & Expendi'!R347, ",", ""))) | ... AD347: =IF('Jilla Parishad Income & Expendi'!AC347="", "", VALUE(SUBSTITUTE('Jilla Parishad Income & Expendi'!AC347, ",", "")))
B348: =IF('Jilla Parishad Income & Expendi'!B348="", "", VALUE(SUBSTITUTE('Jilla Parishad Income & Expendi'!B348, ",", ""))) | C348: =IF('Jilla Parishad Income & Expendi'!C348="", "", VALUE(SUBSTITUTE('Jilla Parishad Income & Expendi'!C348, ",", ""))) | D348: =IF('Jilla Parishad Income & Expendi'!D348="", "", VALUE(SUBSTITUTE('Jilla Parishad Income & Expendi'!D348, ",", ""))) | E348: =IF('Jilla Parishad Income & Expendi'!E348="", "", VALUE(SUBSTITUTE('Jilla Parishad Income & Expendi'!E348, ",", ""))) | F348: =IF('Jilla Parishad Income & Expendi'!F348="", "", VALUE(SUBSTITUTE('Jilla Parishad Income & Expendi'!F348, ",", ""))) | G348: =IF('Jilla Parishad Income & Expendi'!G348="", "", VALUE(SUBSTITUTE('Jilla Parishad Income & Expendi'!G348, ",", ""))) | H348: =IF('Jilla Parishad Income & Expendi'!H348="", "", VALUE(SUBSTITUTE('Jilla Parishad Income & Expendi'!H348, ",", ""))) | I348: =IF('Jilla Parishad Income & Expendi'!I348="", "", VALUE(SUBSTITUTE('Jilla Parishad Income & Expendi'!I348, ",", ""))) | J348: =IF('Jilla Parishad Income & Expendi'!J348="", "", VALUE(SUBSTITUTE('Jilla Parishad Income & Expendi'!J348, ",", ""))) | L348: =IF('Jilla Parishad Income & Expendi'!K348="", "", VALUE(SUBSTITUTE('Jilla Parishad Income & Expendi'!K348, ",", ""))) | M348: =IF('Jilla Parishad Income & Expendi'!L348="", "", VALUE(SUBSTITUTE('Jilla Parishad Income & Expendi'!L348, ",", ""))) | N348: =IF('Jilla Parishad Income & Expendi'!M348="", "", VALUE(SUBSTITUTE('Jilla Parishad Income & Expendi'!M348, ",", ""))) | O348: =IF('Jilla Parishad Income & Expendi'!N348="", "", VALUE(SUBSTITUTE('Jilla Parishad Income & Expendi'!N348, ",", ""))) | P348: =IF('Jilla Parishad Income & Expendi'!O348="", "", VALUE(SUBSTITUTE('Jilla Parishad Income & Expendi'!O348, ",", ""))) | Q348: =IF('Jilla Parishad Income & Expendi'!P348="", "", VALUE(SUBSTITUTE('Jilla Parishad Income & Expendi'!P348, ",", ""))) | R348: =IF('Jilla Parishad Income & Expendi'!Q348="", "", VALUE(SUBSTITUTE('Jilla Parishad Income & Expendi'!Q348, ",", ""))) | S348: =IF('Jilla Parishad Income & Expendi'!R348="", "", VALUE(SUBSTITUTE('Jilla Parishad Income & Expendi'!R348, ",", ""))) | ... AD348: =IF('Jilla Parishad Income & Expendi'!AC348="", "", VALUE(SUBSTITUTE('Jilla Parishad Income & Expendi'!AC348, ",", "")))
B349: =IF('Jilla Parishad Income & Expendi'!B349="", "", VALUE(SUBSTITUTE('Jilla Parishad Income & Expendi'!B349, ",", ""))) | C349: =IF('Jilla Parishad Income & Expendi'!C349="", "", VALUE(SUBSTITUTE('Jilla Parishad Income & Expendi'!C349, ",", ""))) | D349: =IF('Jilla Parishad Income & Expendi'!D349="", "", VALUE(SUBSTITUTE('Jilla Parishad Income & Expendi'!D349, ",", ""))) | E349: =IF('Jilla Parishad Income & Expendi'!E349="", "", VALUE(SUBSTITUTE('Jilla Parishad Income & Expendi'!E349, ",", ""))) | F349: =IF('Jilla Parishad Income & Expendi'!F349="", "", VALUE(SUBSTITUTE('Jilla Parishad Income & Expendi'!F349, ",", ""))) | G349: =IF('Jilla Parishad Income & Expendi'!G349="", "", VALUE(SUBSTITUTE('Jilla Parishad Income & Expendi'!G349, ",", ""))) | H349: =IF('Jilla Parishad Income & Expendi'!H349="", "", VALUE(SUBSTITUTE('Jilla Parishad Income & Expendi'!H349, ",", ""))) | I349: =IF('Jilla Parishad Income & Expendi'!I349="", "", VALUE(SUBSTITUTE('Jilla Parishad Income & Expendi'!I349, ",", ""))) | J349: =IF('Jilla Parishad Income & Expendi'!J349="", "", VALUE(SUBSTITUTE('Jilla Parishad Income & Expendi'!J349, ",", ""))) | L349: =IF('Jilla Parishad Income & Expendi'!K349="", "", VALUE(SUBSTITUTE('Jilla Parishad Income & Expendi'!K349, ",", ""))) | M349: =IF('Jilla Parishad Income & Expendi'!L349="", "", VALUE(SUBSTITUTE('Jilla Parishad Income & Expendi'!L349, ",", ""))) | N349: =IF('Jilla Parishad Income & Expendi'!M349="", "", VALUE(SUBSTITUTE('Jilla Parishad Income & Expendi'!M349, ",", ""))) | O349: =IF('Jilla Parishad Income & Expendi'!N349="", "", VALUE(SUBSTITUTE('Jilla Parishad Income & Expendi'!N349, ",", ""))) | P349: =IF('Jilla Parishad Income & Expendi'!O349="", "", VALUE(SUBSTITUTE('Jilla Parishad Income & Expendi'!O349, ",", ""))) | Q349: =IF('Jilla Parishad Income & Expendi'!P349="", "", VALUE(SUBSTITUTE('Jilla Parishad Income & Expendi'!P349, ",", ""))) | R349: =IF('Jilla Parishad Income & Expendi'!Q349="", "", VALUE(SUBSTITUTE('Jilla Parishad Income & Expendi'!Q349, ",", ""))) | S349: =IF('Jilla Parishad Income & Expendi'!R349="", "", VALUE(SUBSTITUTE('Jilla Parishad Income & Expendi'!R349, ",", ""))) | ... AD349: =IF('Jilla Parishad Income & Expendi'!AC349="", "", VALUE(SUBSTITUTE('Jilla Parishad Income & Expendi'!AC349, ",", "")))
B350: =IF('Jilla Parishad Income & Expendi'!B350="", "", VALUE(SUBSTITUTE('Jilla Parishad Income & Expendi'!B350, ",", ""))) | C350: =IF('Jilla Parishad Income & Expendi'!C350="", "", VALUE(SUBSTITUTE('Jilla Parishad Income & Expendi'!C350, ",", ""))) | D350: =IF('Jilla Parishad Income & Expendi'!D350="", "", VALUE(SUBSTITUTE('Jilla Parishad Income & Expendi'!D350, ",", ""))) | E350: =IF('Jilla Parishad Income & Expendi'!E350="", "", VALUE(SUBSTITUTE('Jilla Parishad Income & Expendi'!E350, ",", ""))) | F350: =IF('Jilla Parishad Income & Expendi'!F350="", "", VALUE(SUBSTITUTE('Jilla Parishad Income & Expendi'!F350, ",", ""))) | G350: =IF('Jilla Parishad Income & Expendi'!G350="", "", VALUE(SUBSTITUTE('Jilla Parishad Income & Expendi'!G350, ",", ""))) | H350: =IF('Jilla Parishad Income & Expendi'!H350="", "", VALUE(SUBSTITUTE('Jilla Parishad Income & Expendi'!H350, ",", ""))) | I350: =IF('Jilla Parishad Income & Expendi'!I350="", "", VALUE(SUBSTITUTE('Jilla Parishad Income & Expendi'!I350, ",", ""))) | J350: =IF('Jilla Parishad Income & Expendi'!J350="", "", VALUE(SUBSTITUTE('Jilla Parishad Income & Expendi'!J350, ",", ""))) | L350: =IF('Jilla Parishad Income & Expendi'!K350="", "", VALUE(SUBSTITUTE('Jilla Parishad Income & Expendi'!K350, ",", ""))) | M350: =IF('Jilla Parishad Income & Expendi'!L350="", "", VALUE(SUBSTITUTE('Jilla Parishad Income & Expendi'!L350, ",", ""))) | N350: =IF('Jilla Parishad Income & Expendi'!M350="", "", VALUE(SUBSTITUTE('Jilla Parishad Income & Expendi'!M350, ",", ""))) | O350: =IF('Jilla Parishad Income & Expendi'!N350="", "", VALUE(SUBSTITUTE('Jilla Parishad Income & Expendi'!N350, ",", ""))) | P350: =IF('Jilla Parishad Income & Expendi'!O350="", "", VALUE(SUBSTITUTE('Jilla Parishad Income & Expendi'!O350, ",", ""))) | Q350: =IF('Jilla Parishad Income & Expendi'!P350="", "", VALUE(SUBSTITUTE('Jilla Parishad Income & Expendi'!P350, ",", ""))) | R350: =IF('Jilla Parishad Income & Expendi'!Q350="", "", VALUE(SUBSTITUTE('Jilla Parishad Income & Expendi'!Q350, ",", ""))) | S350: =IF('Jilla Parishad Income & Expendi'!R350="", "", VALUE(SUBSTITUTE('Jilla Parishad Income & Expendi'!R350, ",", ""))) | ... AD350: =IF('Jilla Parishad Income & Expendi'!AC350="", "", VALUE(SUBSTITUTE('Jilla Parishad Income & Expendi'!AC350, ",", "")))
B351: =IF('Jilla Parishad Income & Expendi'!B351="", "", VALUE(SUBSTITUTE('Jilla Parishad Income & Expendi'!B351, ",", ""))) | C351: =IF('Jilla Parishad Income & Expendi'!C351="", "", VALUE(SUBSTITUTE('Jilla Parishad Income & Expendi'!C351, ",", ""))) | D351: =IF('Jilla Parishad Income & Expendi'!D351="", "", VALUE(SUBSTITUTE('Jilla Parishad Income & Expendi'!D351, ",", ""))) | E351: =IF('Jilla Parishad Income & Expendi'!E351="", "", VALUE(SUBSTITUTE('Jilla Parishad Income & Expendi'!E351, ",", ""))) | F351: =IF('Jilla Parishad Income & Expendi'!F351="", "", VALUE(SUBSTITUTE('Jilla Parishad Income & Expendi'!F351, ",", ""))) | G351: =IF('Jilla Parishad Income & Expendi'!G351="", "", VALUE(SUBSTITUTE('Jilla Parishad Income & Expendi'!G351, ",", ""))) | H351: =IF('Jilla Parishad Income & Expendi'!H351="", "", VALUE(SUBSTITUTE('Jilla Parishad Income & Expendi'!H351, ",", ""))) | I351: =IF('Jilla Parishad Income & Expendi'!I351="", "", VALUE(SUBSTITUTE('Jilla Parishad Income & Expendi'!I351, ",", ""))) | J351: =IF('Jilla Parishad Income & Expendi'!J351="", "", VALUE(SUBSTITUTE('Jilla Parishad Income & Expendi'!J351, ",", ""))) | L351: =IF('Jilla Parishad Income & Expendi'!K351="", "", VALUE(SUBSTITUTE('Jilla Parishad Income & Expendi'!K351, ",", ""))) | M351: =IF('Jilla Parishad Income & Expendi'!L351="", "", VALUE(SUBSTITUTE('Jilla Parishad Income & Expendi'!L351, ",", ""))) | N351: =IF('Jilla Parishad Income & Expendi'!M351="", "", VALUE(SUBSTITUTE('Jilla Parishad Income & Expendi'!M351, ",", ""))) | O351: =IF('Jilla Parishad Income & Expendi'!N351="", "", VALUE(SUBSTITUTE('Jilla Parishad Income & Expendi'!N351, ",", ""))) | P351: =IF('Jilla Parishad Income & Expendi'!O351="", "", VALUE(SUBSTITUTE('Jilla Parishad Income & Expendi'!O351, ",", ""))) | Q351: =IF('Jilla Parishad Income & Expendi'!P351="", "", VALUE(SUBSTITUTE('Jilla Parishad Income & Expendi'!P351, ",", ""))) | R351: =IF('Jilla Parishad Income & Expendi'!Q351="", "", VALUE(SUBSTITUTE('Jilla Parishad Income & Expendi'!Q351, ",", ""))) | S351: =IF('Jilla Parishad Income & Expendi'!R351="", "", VALUE(SUBSTITUTE('Jilla Parishad Income & Expendi'!R351, ",", ""))) | ... AD351: =IF('Jilla Parishad Income & Expendi'!AC351="", "", VALUE(SUBSTITUTE('Jilla Parishad Income & Expendi'!AC351, ",", "")))
... B364: =IF('Jilla Parishad Income & Expendi'!B364="", "", VALUE(SUBSTITUTE('Jilla Parishad Income & Expendi'!B364, ",", ""))) | C364: =IF('Jilla Parishad Income & Expendi'!C364="", "", VALUE(SUBSTITUTE('Jilla Parishad Income & Expendi'!C364, ",", ""))) | D364: =IF('Jilla Parishad Income & Expendi'!D364="", "", VALUE(SUBSTITUTE('Jilla Parishad Income & Expendi'!D364, ",", ""))) | E364: =IF('Jilla Parishad Income & Expendi'!E364="", "", VALUE(SUBSTITUTE('Jilla Parishad Income & Expendi'!E364, ",", ""))) | F364: =IF('Jilla Parishad Income & Expendi'!F364="", "", VALUE(SUBSTITUTE('Jilla Parishad Income & Expendi'!F364, ",", ""))) | G364: =IF('Jilla Parishad Income & Expendi'!G364="", "", VALUE(SUBSTITUTE('Jilla Parishad Income & Expendi'!G364, ",", ""))) | H364: =IF('Jilla Parishad Income & Expendi'!H364="", "", VALUE(SUBSTITUTE('Jilla Parishad Income & Expendi'!H364, ",", ""))) | I364: =IF('Jilla Parishad Income & Expendi'!I364="", "", VALUE(SUBSTITUTE('Jilla Parishad Income & Expendi'!I364, ",", ""))) | J364: =IF('Jilla Parishad Income & Expendi'!J364="", "", VALUE(SUBSTITUTE('Jilla Parishad Income & Expendi'!J364, ",", ""))) | L364: =IF('Jilla Parishad Income & Expendi'!K364="", "", VALUE(SUBSTITUTE('Jilla Parishad Income & Expendi'!K364, ",", ""))) | M364: =IF('Jilla Parishad Income & Expendi'!L364="", "", VALUE(SUBSTITUTE('Jilla Parishad Income & Expendi'!L364, ",", ""))) | N364: =IF('Jilla Parishad Income & Expendi'!M364="", "", VALUE(SUBSTITUTE('Jilla Parishad Income & Expendi'!M364, ",", ""))) | O364: =IF('Jilla Parishad Income & Expendi'!N364="", "", VALUE(SUBSTITUTE('Jilla Parishad Income & Expendi'!N364, ",", ""))) | P364: =IF('Jilla Parishad Income & Expendi'!O364="", "", VALUE(SUBSTITUTE('Jilla Parishad Income & Expendi'!O364, ",", ""))) | Q364: =IF('Jilla Parishad Income & Expendi'!P364="", "", VALUE(SUBSTITUTE('Jilla Parishad Income & Expendi'!P364, ",", ""))) | R364: =IF('Jilla Parishad Income & Expendi'!Q364="", "", VALUE(SUBSTITUTE('Jilla Parishad Income & Expendi'!Q364, ",", ""))) | S364: =IF('Jilla Parishad Income & Expendi'!R364="", "", VALUE(SUBSTITUTE('Jilla Parishad Income & Expendi'!R364, ",", ""))) | ... AD364: =IF('Jilla Parishad Income & Expendi'!AC364="", "", VALUE(SUBSTITUTE('Jilla Parishad Income & Expendi'!AC364, ",", "")))

Sheet Jilla Parishad Income & Expendi
A1: District | B1: Year | C1: Opening Balance | D1: Revenue from self-made tools | E1: Government subsidies | F1: Purposive grants | G1: Establishment grants | H1: Grants for Plan Scheme | I1: Other Statutory grants | J1: For Agency Schemes | K1: Other sources of income | L1: Capital receipts | M1: Total receipts (D+E+F+G+H+I+J) | N1: Total Income (C+M) | O1: General Administration | P1: Education | Q1: Public Works | R1: Irrigation | S1: Agriculture | T1: Animal Husbandary | U1: Forests | V1: Public Health | W1: Social Welfare | X1: Other Expenses | Y1: Total Revenue Expenditure | Z1: Capital Expenditure | AA1: Total Expenses
A2: Ahmadnagar | B2: 2012 | C2: 22558 | D2: 215 | F2: 79949 | G2: 11644 | H2: 25133 | I2: 0 | J2: 82 | K2: 1045 | L2: 3221 | M2: 121289 | N2: 143847 | O2: 6686 | P2: 49386 | Q2: 6692 | R2: 1945 | S2: 775 | T2: 1635 | U2: 0 | V2: 7011 | W2: 3854 | X2: 36485 | Y2: 114469 | Z2: 3416 | AA2: 117885
A3: Ahmadnagar | B3: 2013 | C3: 27560 | D3: 5069 | F3: 75857 | G3: 13757 | H3: 22792 | I3: 104672 | J3: 8225 | K3: 0 | L3: 12217 | M3: 242589 | N3: 270149 | O3: 755.02 | P3: 54878.85 | Q3: 6710.03 | R3: 2131.6 | S3: 745.4 | T3: 2684.63 | U3: 0 | V3: 7223.8 | W3: 2942.4 | X3: 144355.48 | Y3: 222427.21 | Z3: 17440.06 | AA3: 239867.27
A4: Ahmadnagar | B4: 2014 | C4: 30282 | D4: 12775 | F4: 88311 | G4: 13970 | H4: 27567 | I4: 98665 | J4: 8806 | K4: 0 | L4: 59226 | M4: 309320 | N4: 339602 | O4: 7915.09 | P4: 60334.78 | Q4: 6860.52 | R4: 1798.22 | S4: 1268.34 | T4: 2995.49 | U4: 0 | V4: 7254.61 | W4: 5901.17 | X4: 52403.48 | Y4: 146731.7 | Z4: 159409.34 | AA4: 306141.04
A5: Ahmadnagar | B5: 2015 | C5: 32661 | D5: 6378 | F5: 97717 | G5: 21646 | H5: 30176 | I5: 30625 | J5: 13357 | K5: 0 | L5: 52095 | M5: 251995 | N5: 284655 | O5: 13803.81 | P5: 81040.09 | Q5: 6213.06 | R5: 602.65 | S5: 1508.93 | T5: 2972.09 | U5: 4984.66 | V5: 7354.95 | W5: 5187.17 | X5: 11927.05 | Y5: 135594.46 | Z5: 110316.28 | AA5: 245910.74
A6: Ahmadnagar | B6: 2016 | C6: 38745 | D6: 5419 | F6: 107363 | G6: 17545 | H6: 29623 | I6: 0 | J6: 10069 | K6: 92201 | L6: 11512 | M6: 273730 | N6: 312474 | O6: 15516.1 | P6: 85281.57 | Q6: 5531.07 | R6: 812.41 | S6: 1440.4 | T6: 3447.23 | U6: 1017.16 | V6: 7334.21 | W6: 11588.44 | X6: 128071.65 | Y6: 260040.24 | Z6: 11727.42 | AA6: 271767.66
A7: Ahmadnagar | B7: 2017 | C7: 40707 | D7: 2767 | F7: 39733 | G7: 17347 | H7: 110296 | I7: 0 | J7: 5567 | K7: 70330 | L7: 16051 | M7: 262090 | N7: 302797 | O7: 15278.95 | P7: 89993.68 | Q7: 1908.22 | R7: 911.33 | S7: 1634.16 | T7: 2615.57 | U7: 1680.12 | V7: 7819.92 | W7: 9110.1 | X7: 115891.9 | Y7: 246843.95 | Z7: 9092.03 | AA7: 255935.98
A8: Ahmadnagar | B8: 2018 | C8: 46861 | D8: 2994 | F8: 30528 | G8: 18328 | H8: 120617 | I8: 0 | J8: 7570 | K8: 53018 | L8: 71772 | M8: 304826 | N8: 351687 | O8: 18498.86 | P8: 95606.74 | Q8: 6472.43 | R8: 3670.21 | S8: 897.41 | T8: 3227.86 | U8: 5493.03 | V8: 8867.42 | W8: 9993.06 | X8: 65900.81 | Y8: 218627.83 | Z8: 66868.86 | AA8: 285496.69
A9: Ahmadnagar | B9: 2019 | C9: 46861 | D9: 2165 | F9: 28757 | G9: 24892 | H9: 166370 | I9: 0 | J9: 8956 | K9: 58248 | L9: 50566 | M9: 339954 | N9: 386815 | O9: 24180.49 | P9: 122784.95 | Q9: 9489.65 | R9: 4062.07 | S9: 994.71 | T9: 4230.04 | U9: 13447.73 | V9: 11446.33 | W9: 18399.81 | X9: 55249.53 | Y9: 264285.31 | Z9: 96148 | AA9: 360433.31
A10: Ahmadnagar | B10: 2020 | C10: 45711 | D10: 3247 | F10: 34450 | G10: 122385 | H10: 57698 | I10: 0 | J10: 9071 | K10: 49700 | L10: 49881 | M10: 326433 | N10: 372144 | O10: 20813.44 | P10: 117956.45 | Q10: 5810.9 | R10: 1908.84 | S10: 779.88 | T10: 3002.7 | U10: 4009.24 | V10: 10252.64 | W10: 18149.42 | X10: 27710.25 | Y10: 210393.76 | Z10: 104507.92 | AA10: 314901.68
A11: Akola | B11: 2012 | C11: 10988.41 | D11: 0 | F11: 27017.6 | G11: 4726.93 | H11: 12999.99 | I11: 179.36 | J11: 2613.12 | K11: 0 | L11: 50063.4 | M11: 97600 | N11: 108589 | O11: 1976.1 | P11: 24250.41 | Q11: 2540.9 | R11: 601.23 | S11: 850.8 | T11: 650 | U11: 3 | V11: 2850 | W11: 1917.95 | X11: 10788.97 | Y11: 46429.36 | Z11: 51852.16 | AA11: 98281.52
A12: Akola | B12: 2013 | C12: 13073.92 | D12: 3920.53 | F12: 28212.05 | G12: 5062.06 | H12: 11451.46 | I12: 11.36 | J12: 2680.86 | K12: 131.13 | L12: 49579.17 | M12: 101049 | N12: 114123 | O12: 2230.21 | P12: 25881.29 | Q12: 2155.08 | R12: 416 | S12: 659.81 | T12: 751.25 | U12: 0 | V12: 2616.49 | W12: 1964.01 | X12: 8915.24 | Y12: 45589.38 | Z12: 49493.2 | AA12: 95082.58
A13: Akola | B13: 2014 | C13: 19039.92 | D13: 3948.69 | F13: 27867.28 | G13: 9175.73 | H13: 13058.25 | I13: 45.5 | J13: 3738.17 | K13: 0 | L13: 51549.49 | M13: 109383 | N13: 128423 | O13: 5564.49 | P13: 26948.05 | Q13: 3428.23 | R13: 935.49 | S13: 818.69 | T13: 788.33 | U13: 0 | V13: 3157.12 | W13: 2332.2 | X13: 7980.52 | Y13: 51953.12 | Z13: 52309.55 | AA13: 104262.67
... A30: Amravati | B30: 2021 | C30: 48658.07 | D30: 1843.65 | F30: 0 | G30: 111488.48 | H30: 29389.98 | I30: 0 | J30: 7981.36 | K30: 0 | L30: 1862.14 | M30: 152566 | N30: 201224 | O30: 309.1 | P30: 75026.73 | Q30: 13355.06 | R30: 1250.16 | S30: 654.68 | T30: 1642.36 | U30: 150.83 | V30: 11259.49 | W30: 1969.14 | X30: 36867.53 | Y30: 142485.08 | Z30: 9780.53 | AA30: 152265.61
A31: Bhandara | B31: 2012 | C31: 13642 | D31: 0 | F31: 41775 | K31: 587 | L31: 2620 | M31: #REF! | N31: #REF! | O31: 1805 | P31: 19482 | Q31: 1954 | R31: 1377 | S31: 431 | T31: 343 | U31: 22 | V31: 2437 | W31: 1454 | X31: 6064 | Y31: 35369 | Z31: 1977 | AA31: 37346
A32: Bhandara | B32: 2013 | C32: 17434 | D32: 0 | F32: 44957 | K32: 495 | L32: 1908 | M32: #REF! | N32: #REF! | O32: 4873 | P32: 23505 | Q32: 3023 | R32: 1140 | S32: 554 | T32: 583 | U32: 13 | V32: 3373 | W32: 2587 | X32: 8629 | Y32: 48280 | Z32: 1809 | AA32: 50089
A33: Bhandara | B33: 2014 | C33: 14812 | D33: 0 | F33: 49800 | K33: 799 | L33: 2420 | M33: #REF! | N33: #REF! | O33: 5467 | P33: 24748 | Q33: 5038 | R33: 814 | S33: 612 | T33: 579 | U33: 5 | V33: 4499 | W33: 2386 | X33: 6051 | Y33: 50199 | Z33: 2531 | AA33: 52730
A34: Bhandara | B34: 2015 | C34: 13177 | D34: 599 | F34: 51509 | J34: 2326 | K34: 374 | L34: 3750 | M34: #REF! | N34: #REF! | O34: 6264 | P34: 24995 | Q34: 3659 | R34: 1805 | S34: 601 | T34: 647 | U34: 8 | V34: 3339 | W34: 3049 | X34: 7012 | Y34: 51379 | Z34: 2174 | AA34: 53553
A35: Bhandara | B35: 2016 | C35: 13599 | D35: 697 | F35: 54333 | J35: 1642 | K35: 295 | L35: 3975 | M35: #REF! | N35: #REF! | O35: 6938 | P35: 27887 | Q35: 3192 | R35: 1249 | S35: 781 | T35: 647 | U35: 6 | V35: 3693 | W35: 3066 | X35: 9361 | Y35: 56820 | Z35: 4040 | AA35: 60860
A36: Bhandara | B36: 2017 | C36: 17513 | D36: 1061 | F36: 0 | G36: 37225 | H36: 17626 | I36: 53 | J36: 2434 | K36: 70 | L36: 2751 | M36: 61220 | N36: 78733 | O36: 6607 | P36: 29249 | Q36: 601 | R36: 725 | S36: 554 | T36: 606 | U36: 30 | V36: 4223 | W36: 2718 | X36: 16974 | Y36: 62287 | Z36: 4470 | AA36: 66757
A37: Bhandara | B37: 2018 | C37: 12641 | D37: 931 | F37: 0 | G37: 39239 | H37: 18507 | I37: 56 | J37: 3270 | K37: 73 | L37: 3984 | M37: 66060 | N37: 78701 | O37: 6911 | P37: 31283 | Q37: 662 | R37: 785 | S37: 543 | T37: 683 | U37: 6 | V37: 4767 | W37: 2907 | X37: 14390 | Y37: 62937 | Z37: 2817 | AA37: 65754
A38: Bhandara | B38: 2019 | C38: 12947 | D38: 1127 | F38: 0 | G38: 46637 | H38: 17983 | I38: 17 | J38: 3270 | K38: 0 | L38: 2733 | M38: 71767 | N38: 84714 | O38: 7322 | P38: 33061 | Q38: 785 | R38: 848 | S38: 754 | T38: 646 | U38: 6 | V38: 4798 | W38: 3002 | X38: 16884 | Y38: 68106 | Z38: 3193 | AA38: 71299
A39: Bhandara | B39: 2020 | C39: 13180 | D39: 878 | F39: 0 | G39: 56941 | H39: 17014 | I39: 122 | J39: 3714 | K39: 0 | L39: 2190 | M39: 80859 | N39: 94039 | O39: 11363 | P39: 41805 | Q39: 3384 | R39: 509 | S39: 342 | T39: 741 | U39: 6 | V39: 5092 | W39: 2340 | X39: 14570 | Y39: 80152 | Z39: 2194 | AA39: 82346
A40: Bhandara | B40: 2021 | C40: 13415 | D40: 1015 | F40: 0 | G40: 48969 | H40: 18702 | I40: 18 | J40: 3434 | K40: 0 | L40: 2815 | M40: 74953 | N40: 88368 | O40: 7688 | P40: 39439 | Q40: 1034 | R40: 890 | S40: 792 | T40: 678 | U40: 6 | V40: 5062 | W40: 3152 | X40: 13528 | Y40: 72269 | Z40: 2919 | AA40: 75188
A41: Buldhana | B41: 2013 | C41: 24456 | D41: 3497 | F41: 47467 | G41: 8670 | H41: 9248 | I41: 5771 | J41: 4298 | K41: 0 | L41: 2132 | M41: 81083 | N41: 105539 | O41: 7125 | P41: 44722 | Q41: 3174 | R41: 999 | S41: 1042 | T41: 1248 | U41: 0 | V41: 4490 | W41: 2092 | X41: 1002 | Y41: 65894 | Z41: 2640 | AA41: 68534
A42: Buldhana | B42: 2014 | C42: 25586 | D42: 2033 | F42: 49584 | G42: 13048 | H42: 12192 | I42: 4697 | J42: 5743 | K42: 0 | L42: 3233 | M42: 90530 | N42: 116116 | O42: 8629 | P42: 46053 | Q42: 4191 | R42: 1762 | S42: 1076 | T42: 1046 | U42: 0 | V42: 4464 | W42: 3334 | X42: 14234 | Y42: 84789 | Z42: 1104 | AA42: 85893
A43: Buldhana | B43: 2015 | C43: 29083 | D43: 1172 | G43: 60231 | H43: 30890 | J43: 3679 | K43: 0 | L43: 4618 | M43: 100590 | N43: 129673 | O43: 10395 | P43: 48082 | Q43: 2778 | R43: 1195 | S43: 1272 | T43: 1223 | V43: 4814 | W43: 2141 | X43: 17887 | Y43: 89787 | Z43: 2429 | AA43: 92216
A44: Buldhana | B44: 2016 | C44: 36121 | D44: 2494 | F44: 16145 | G44: 62062 | H44: 1614 | I44: 11172 | J44: 6054 | K44: 0 | L44: 6039 | M44: 105580 | N44: 141701 | O44: 10290 | P44: 53305 | Q44: 4292 | R44: 1662 | S44: 1437 | T44: 1538 | U44: 0 | V44: 5124 | W44: 4447 | X44: 16273 | Y44: 98368 | Z44: 6460 | AA44: 104828
A45: Buldhana | B45: 2017 | C45: 40129 | D45: 3640 | F45: 8181 | G45: 65553 | H45: 18609 | I45: 11332 | J45: 3452 | K45: 0 | L45: 2002 | M45: 112769 | N45: 152898 | O45: 20375 | P45: 55412 | Q45: 5035 | R45: 9979 | S45: 2228 | T45: 1342 | U45: 0 | V45: 3543 | W45: 3791 | X45: 1748 | Y45: 103453 | Z45: 1732 | AA45: 105185
A46: Buldhana | B46: 2018 | C46: 47711 | D46: 3074 | F46: 8478 | G46: 74015 | H46: 19505 | I46: 11596 | J46: 3225 | K46: 0 | L46: 2595 | M46: 122488 | N46: 170199 | O46: 16648 | P46: 57512 | Q46: 2130 | R46: 5960 | S46: 2804 | T46: 1059 | V46: 6753 | W46: 3612 | X46: 753 | Y46: 97231 | Z46: 4325 | AA46: 101556
A47: Buldhana | B47: 2019 | C47: 68643 | D47: 1223 | F47: 6638 | G47: 97093 | H47: 16643 | I47: 11875 | J47: 7179 | K47: 0 | L47: 2267 | M47: 142918 | N47: 211561 | O47: 12044 | P47: 66151 | Q47: 10035 | R47: 1576 | S47: 3227 | T47: 993 | U47: 0 | V47: 2983 | W47: 50096 | X47: 10602 | Y47: 157707 | Z47: 1926 | AA47: 159633
A48: Buldhana | B48: 2020 | C48: 51926 | D48: 351 | F48: 8367 | G48: 102918 | H48: 11270 | I48: 15063 | K48: 0 | L48: 6546 | M48: 144515 | N48: 196441 | O48: 16665 | P48: 74712 | Q48: 5582 | R48: 1506 | S48: 1074 | T48: 1080 | U48: 0 | V48: 7605 | W48: 202 | X48: 1434 | Y48: 109860 | Z48: 1034 | AA48: 110894
A49: Buldhana | B49: 2021 | C49: 85547 | D49: 18 | F49: 567 | G49: 112822 | H49: 12692 | I49: 5033 | J49: 3960 | K49: 0 | L49: 32746 | M49: 167838 | N49: 253385 | O49: 20278 | P49: 82458 | Q49: 5020 | R49: 1722 | S49: 786 | T49: 1140 | U49: 0 | V49: 8281 | W49: 4369 | X49: 4426 | Y49: 128480 | Z49: 1137 | AA49: 129617
A50: Chandrapur | B50: 2012 | C50: 22321.7 | D50: 269.2 | F50: 10343.1 | G50: 38055.8 | H50: 9534.4 | I50: 0 | J50: 4852.6 | K50: 5026.2 | L50: 80179.3 | M50: 148261 | N50: 170582 | O50: 2990.8 | P50: 28815.1 | Q50: 3037.9 | R50: 2049.8 | S50: 1556 | T50: 1531.5 | U50: 3.3 | V50: 4523.1 | W50: 1569.5 | X50: 16573.9 | Y50: 62650.9 | Z50: 80996.6 | AA50: 143647.5
A51: Chandrapur | B51: 2013 | C51: 26934.5 | D51: 443.1 | F51: 6238 | G51: 323433.1 | H51: 7825.4 | I51: 0 | J51: 2059.7 | K51: 2657.6 | L51: 23287.7 | M51: 365945 | N51: 392879 | O51: 3835.1 | P51: 33822.6 | Q51: 4027.8 | R51: 1801.3 | S51: 1294.7 | T51: 1359.7 | U51: 4.4 | V51: 4983.2 | W51: 1362.5 | X51: 2000.1 | Y51: 54491.4 | Z51: 74301.1 | AA51: 128792.5
A52: Chandrapur | B52: 2014 | C52: 264086.6 | D52: 410.5 | F52: 1690.9 | G52: 37382.7 | H52: 17000.8 | I52: 0 | J52: 2956.5 | K52: 0 | L52: 18616.6 | M52: 78058 | N52: 342145 | O52: 7905.8 | P52: 37288.1 | Q52: 5914.5 | R52: 1565.6 | S52: 1428 | T52: 1599 | U52: 48.4 | V52: 5600 | W52: 2334.3 | X52: 244126.4 | Y52: 307810.1 | Z52: 17189.5 | AA52: 324999.6
A53: Chandrapur | B53: 2015 | C53: 17144.88 | D53: 712.36 | F53: 1291.76 | G53: 62023.75 | H53: 22439 | I53: 0 | J53: 3101.26 | K53: 0 | L53: 6062.58 | M53: 95631 | N53: 112776 | O53: 9221.31 | P53: 44024.88 | Q53: 7577.03 | R53: 1461.01 | S53: 1279.73 | T53: 1600.76 | U53: 74.38 | V53: 5813.2 | W53: 2277.67 | X53: 9121.29 | Y53: 82451.26 | Z53: 6728.73 | AA53: 89179.99
A54: Chandrapur | B54: 2016 | C54: 23595.72 | D54: 2578.77 | F54: 59056 | G54: 13470.05 | H54: 18244.22 | I54: 1365.72 | J54: 3766.7 | K54: 0 | L54: 4467.99 | M54: 102949 | N54: 126545 | O54: 9643.42 | P54: 43975.85 | Q54: 6228.57 | R54: 1138.4 | S54: 979.52 | T54: 1441.74 | U54: 87 | V54: 6072.22 | W54: 3216.41 | X54: 15598.11 | Y54: 88381.24 | Z54: 6258.13 | AA54: 94639.37
A55: Chandrapur | B55: 2017 | C55: 39571.7 | D55: 4022.32 | F55: 0 | G55: 51021.57 | H55: 39873.59 | I55: 0 | J55: 4902.82 | K55: 0 | L55: 25308.3 | M55: 125129 | N55: 164700 | O55: 10624.48 | P55: 48062.92 | Q55: 2095.66 | R55: 1069.54 | S55: 1526.32 | T55: 1500.16 | U55: 39.54 | V55: 6666.93 | W55: 554.23 | X55: 26694.12 | Y55: 98833.9 | Z55: 25930.04 | AA55: 124763.94
A56: Chandrapur | B56: 2018 | C56: 39936.36 | D56: 4933.53 | F56: 0 | G56: 78296.79 | H56: 17459.81 | I56: 1543.13 | J56: 9017.01 | K56: 0 | L56: 32860.44 | M56: 144111 | N56: 184047 | O56: 14837.37 | P56: 51471.38 | Q56: 4774.77 | R56: 1043.81 | S56: 2065.48 | T56: 1796.99 | U56: 34.78 | V56: 8882.35 | W56: 966.51 | X56: 10864.19 | Y56: 96737.63 | Z56: 56023.44 | AA56: 152761.07
A57: Chandrapur | B57: 2019 | C57: 51312.08 | D57: 5369.09 | F57: 0 | G57: 101568.8 | H57: 15944 | I57: 11629.97 | J57: 0 | K57: 7630.48 | L57: 21043 | M57: 163185 | N57: 214497 | O57: 14513.72 | P57: 65347.57 | Q57: 17958.35 | R57: 1818.2 | S57: 863.65 | T57: 2079.03 | U57: 4.8 | V57: 8560.62 | W57: 8695.27 | X57: 13017.49 | Y57: 132858.71 | Z57: 27418.9 | AA57: 160277.61
A58: Chandrapur | B58: 2020 | C58: 54219.09 | D58: 3069.13 | F58: 0 | G58: 88454.76 | H58: 10251.43 | I58: 151.03 | J58: 0 | K58: 7851.17 | L58: 389217.85 | M58: 498995 | N58: 553214 | O58: 15626.58 | P58: 59566.97 | Q58: 4607.42 | R58: 1447.8 | S58: 4585.43 | T58: 1968.79 | U58: 20 | V58: 8071.06 | W58: 2871.4 | X58: 6395.47 | Y58: 105160.92 | Z58: 62390.35 | AA58: 167551.27
A59: Chandrapur | B59: 2021 | C59: 54219.09 | D59: 3069.13 | F59: 0 | H59: 10251.43 | I59: 151.03 | J59: 0 | K59: 7851.17 | L59: 389217.85 | M59: 498995 | N59: 501016 | O59: 15626.58 | P59: 59566.97 | Q59: 4607.42 | R59: 1447.8 | S59: 4585.43 | T59: 1968.79 | U59: 20 | V59: 8071.06 | W59: 2871.4 | X59: 6395.47 | Y59: 105160.92 | Z59: 62390.35 | AA59: 167551.27
A60: Dhule | B60: 2013 | C60: 821.6 | D60: 0 | E60: 1215.25 | F60: 0 | G60: 0 | H60: 0 | I60: 300.3 | J60: 23.34 | K60: 177.24 | L60: 2481 | M60: 4197 | N60: 5018 | O60: 34.67 | P60: 7.4 | Q60: 133.19 | R60: 14.31 | S60: 14.94 | T60: 11.79 | U60: 2.9 | V60: 6 | W60: 73.23 | X60: 888.27 | Y60: 1186.7 | Z60: 2323.27 | AA60: 3509.97
A61: Dhule | B61: 2014 | C61: 1508.36 | D61: 6.69 | E61: 441.33 | F61: 0 | G61: 0 | H61: 0 | I61: 246.28 | J61: 27.46 | L61: 2438.07 | M61: 3160 | N61: 4668 | O61: 131.97 | P61: 28.71 | Q61: 81.57 | R61: 21.91 | S61: 40.98 | T61: 33.79 | U61: 2.99 | V61: 37.59 | W61: 189.63 | X61: 776.85 | Y61: 1345.99 | Z61: 1916.77 | AA61: 3262.76
A62: Dhule | B62: 2015 | C62: 1290.9 | D62: 45.1 | E62: 590.45 | F62: 0 | G62: 100 | H62: 0 | I62: 42.63 | L62: 2082.82 | M62: 2861 | N62: 4152 | O62: 137.87 | P62: 21.13 | Q62: 115.24 | R62: 40.87 | S62: 14.93 | T62: 4.18 | U62: 0 | V62: 28.07 | W62: 59.95 | X62: 516.74 | Y62: 938.98 | Z62: 1754.5 | AA62: 2693.48
A63: Dhule | B63: 2016 | C63: 1458.42 | D63: 198.75 | F63: 0 | G63: 110 | H63: 0 | I63: 1080.79 | J63: 0 | K63: 3.84 | L63: 2884.66 | M63: 4278 | N63: 5736 | O63: 135.54 | P63: 10.2 | Q63: 98.4 | R63: 19.1 | S63: 11.05 | T63: 13.19 | U63: 0 | V63: 19.76 | W63: 68.52 | X63: 589.19 | Y63: 964.95 | Z63: 2873.22 | AA63: 3838.17
A64: Dhule | B64: 2017 | C64: 1920.45 | D64: 130.33 | F64: 0 | G64: 110 | H64: 0 | I64: 810.85 | J64: 0 | L64: 3846.71 | M64: 4898 | N64: 6818 | O64: 159.91 | P64: 28.73 | Q64: 0.05 | R64: 8.77 | S64: 0 | T64: 15.51 | U64: 99.26 | V64: 678.35 | W64: 151.99 | X64: 16.46 | Y64: 1159.03 | Z64: 3380.45 | AA64: 4539.48
A65: Dhule | B65: 2018 | C65: 1182.84 | D65: 128.36 | F65: 379.42 | G65: 110 | H65: 0 | I65: 0 | J65: 69.43 | K65: 102.28 | L65: 3251.87 | M65: 4041 | N65: 5224 | O65: 151.99 | P65: 16.4 | Q65: 159.91 | R65: 28.74 | S65: 0.05 | T65: 7.85 | U65: 0 | V65: 15.51 | W65: 99.26 | X65: 325.92 | Y65: 805.63 | Z65: 3071 | AA65: 3876.63
A66: Dhule | B66: 2019 | C66: 20765.59 | D66: 890.94 | F66: 50663.13 | G66: 13710.66 | H66: 14810.61 | I66: 6123.38 | J66: 4834.07 | K66: 662.86 | L66: 1113.57 | M66: 92809 | N66: 113575 | O66: 4415.97 | P66: 981.45 | Q66: 8075.05 | R66: 1916.05 | S66: 95.69 | T66: 982.96 | U66: 0 | V66: 6329.97 | W66: 1600.11 | X66: 71371 | Y66: 95768.25 | Z66: 494.15 | AA66: 96262.4
A67: Dhule | B67: 2020 | C67: 17312.32 | D67: 203.05 | F67: 48402.1 | G67: 12669.12 | H67: 21407.94 | I67: 5218.1 | J67: 4398.61 | K67: 735.45 | L67: 814.99 | M67: 93849 | N67: 111162 | O67: 4544.34 | P67: 964.37 | Q67: 7997.11 | R67: 1073.9 | S67: 87.61 | T67: 819.98 | U67: 0 | V67: 6517.84 | W67: 500.9 | X67: 61336.13 | Y67: 83842.18 | Z67: 516.07 | AA67: 84358.25
A68: Dhule | B68: 2021 | C68: 26803.43 | D68: 587.48 | F68: 49145.29 | G68: 15056.86 | H68: 21141.92 | I68: 10424.1 | J68: 6789.43 | K68: 714.21 | L68: 1147.39 | M68: 105007 | N68: 131810 | O68: 4733.62 | P68: 2319.43 | Q68: 15569.96 | R68: 1746.7 | S68: 1038.81 | T68: 1071.86 | U68: 0 | V68: 8557.84 | W68: 1146.02 | X68: 71526.28 | Y68: 107710.52 | Z68: 657.24 | AA68: 108367.76
A69: Gadchiroli | B69: 2012 | C69: 111553 | D69: 1957 | E69: 45499 | F69: 9904 | G69: 10609 | H69: 12781 | I69: 12205 | J69: 2969 | K69: 0 | L69: 38129 | M69: 134053 | N69: 245606 | O69: 5091 | P69: 19121 | Q69: 1039 | R69: 719 | S69: 456 | T69: 923 | U69: 995 | V69: 5727 | W69: 1832 | X69: 8231 | Y69: 44134 | Z69: 36703 | AA69: 80837
A70: Gadchiroli | B70: 2013 | C70: 164769 | D70: 2482 | E70: 52892 | F70: 10903 | G70: 12009 | H70: 19905 | I70: 10075 | J70: 3445 | K70: 0 | L70: 40603 | M70: 152314 | N70: 317083 | O70: 5548 | P70: 24350 | Q70: 1353 | R70: 1616 | S70: 335 | T70: 1269 | U70: 0 | V70: 5666 | W70: 1173 | X70: 6162 | Y70: 47472 | Z70: 45245 | AA70: 92717
A71: Gadchiroli | B71: 2014 | C71: 22235.02 | D71: 2765.97 | E71: 5654.03 | F71: 34985.17 | G71: 7063.26 | H71: 13212.18 | I71: 0 | J71: 3718.34 | K71: 0 | L71: 45158.48 | M71: 112557 | N71: 134792 | O71: 5616.06 | P71: 27108.69 | Q71: 3214.57 | R71: 1182.94 | S71: 1228.54 | T71: 1640.15 | U71: 624.34 | V71: 7280.19 | W71: 1338.73 | X71: 11498.06 | Y71: 60732.27 | Z71: 49703.71 | AA71: 110435.98
A72: Gadchiroli | B72: 2015 | C72: 24356.46 | D72: 1579.87 | E72: 0 | F72: 51435.42 | G72: 7179.08 | H72: 1691.58 | I72: 2137.98 | J72: 4372.85 | K72: 0 | L72: 51396.62 | M72: 119793 | N72: 144150 | O72: 4729.27 | P72: 30549.91 | Q72: 4470.78 | R72: 1163.38 | S72: 1337.3 | T72: 1635.1 | U72: 568.59 | V72: 6593.71 | W72: 558.17 | X72: 13100.97 | Y72: 64707.18 | Z72: 53216.64 | AA72: 117923.82
A73: Gadchiroli | B73: 2016 | C73: 23841.24 | D73: 1375.25 | F73: 67787.45 | G73: 0 | H73: 0 | I73: 0 | J73: 4556.63 | K73: 0 | L73: 47263.63 | M73: 120983 | N73: 144824 | O73: 4794.7 | P73: 28494.37 | Q73: 1816.44 | R73: 2398.48 | S73: 1619.24 | T73: 1175.1 | U73: 1040.69 | V73: 6579.87 | W73: 1743.25 | X73: 19152.81 | Y73: 68814.95 | Z73: 47776.56 | AA73: 116591.51
A74: Gadchiroli | B74: 2017 | C74: 28232.69 | D74: 1401.02 | F74: 68309.21 | G74: 0 | H74: 0 | I74: 0 | J74: 4607.2 | K74: 0 | L74: 48103.82 | M74: 122421 | N74: 150654 | O74: 4807 | P74: 30399.1 | Q74: 1906.02 | R74: 2399.58 | S74: 1671.23 | T74: 1204 | U74: 1021.44 | V74: 6683.22 | W74: 1788.02 | X74: 19161.93 | Y74: 71041.54 | Z74: 47981.23 | AA74: 119022.77
A75: Gadchiroli | B75: 2018 | C75: 25349.92 | D75: 1388.83 | F75: 32496.82 | G75: 34496.81 | H75: 0 | I75: 0 | J75: 4500.16 | K75: 0 | L75: 50518.04 | M75: 123401 | N75: 148751 | O75: 4544.1 | P75: 34436.16 | Q75: 4918.55 | R75: 1281.01 | S75: 1361.72 | T75: 1483.51 | U75: 0 | V75: 6587.39 | W75: 571.46 | X75: 10822.62 | Y75: 66006.52 | Z75: 52627.97 | AA75: 118634.49
A76: Gadchiroli | B76: 2019 | C76: 34931.45 | D76: 1507.04 | F76: 30044.6 | G76: 50789.69 | H76: 0 | I76: 0 | J76: 1457.3 | K76: 0 | L76: 49260.06 | M76: 133059 | N76: 167990 | O76: 8407.01 | P76: 33698.98 | Q76: 1425.6 | R76: 2201.99 | S76: 1912.84 | T76: 1405.61 | U76: 328.48 | V76: 6668.24 | W76: 802.07 | X76: 17174.99 | Y76: 74025.81 | Z76: 49090.72 | AA76: 123116.53
A77: Gadchiroli | B77: 2020 | C77: 44873.58 | D77: 301.37 | F77: 527.77 | G77: 40687.47 | H77: 0 | I77: 0 | J77: 723.87 | K77: 0 | L77: 55780.78 | M77: 98021 | N77: 142895 | O77: 6676.16 | P77: 35473.23 | Q77: 1213.65 | R77: 460.7 | S77: 1051.82 | T77: 213.81 | U77: 25.58 | V77: 1602.53 | W77: 374.68 | X77: 11157.67 | Y77: 58249.83 | Z77: 47348.55 | AA77: 105598.38
A78: Gadchiroli | B78: 2021 | C78: 37296.46 | D78: 1173.76 | F78: 22950.2 | G78: 69209.52 | H78: 0 | I78: 0 | J78: 3387.09 | K78: 0 | L78: 42118.57 | M78: 138839 | N78: 176136 | O78: 15025.78 | P78: 48417.22 | Q78: 2521.71 | R78: 1460.74 | S78: 1513.54 | T78: 1797.05 | U78: 96.61 | V78: 7097.96 | W78: 355.3 | X78: 11739.96 | Y78: 90025.87 | Z78: 53004.79 | AA78: 143030.66
A79: Gondia | B79: 2012 | C79: 14479.83 | D79: 703.87 | E79: 1312.21 | F79: 22436.13 | G79: 7220.47 | H79: 8455.8 | I79: 12.5 | J79: 8877.78 | K79: 28089.62 | L79: 2206.09 | M79: 79314 | N79: 93794 | O79: 3870.6 | P79: 26314.22 | Q79: 2716.66 | R79: 1817.62 | S79: 517.3 | T79: 842.99 | U79: 25.68 | V79: 3443.25 | W79: 1256.66 | X79: 40970.29 | Y79: 81775.27 | Z79: 3779.44 | AA79: 85554.71
A80: Gondia | B80: 2013 | C80: 8239.59 | D80: 833.39 | G80: 34960.32 | H80: 11137.3 | I80: 370.5 | J80: 4146.48 | L80: 4193.21 | M80: 55641 | N80: 63881 | O80: 6916.34 | P80: 25662.99 | Q80: 455.33 | R80: 827.64 | S80: 770.29 | T80: 1370.15 | U80: 31.25 | V80: 5678.57 | W80: 1642.98 | X80: 5319.39 | Y80: 48674.93 | Z80: 6423.97 | AA80: 55098.9
A81: Gondia | B81: 2014 | C81: 8781.89 | D81: 1187.27 | G81: 38456.35 | H81: 12251.03 | I81: 2413.1 | J81: 4183.04 | L81: 4740.08 | M81: 63231 | N81: 72013 | O81: 7542.42 | P81: 24671.29 | Q81: 3234.35 | R81: 621.7 | S81: 614.16 | T81: 974.28 | U81: 13.34 | V81: 3176.13 | W81: 1508.91 | X81: 12251.99 | Y81: 54608.57 | Z81: 6729.12 | AA81: 61337.69
A82: Gondia | B82: 2015 | C82: 10675.08 | D82: 1079.51 | F82: 0 | G82: 25452.47 | H82: 7624.25 | I82: 0 | J82: 3438.63 | K82: 0 | L82: 2513.81 | M82: 40109 | N82: 50784 | O82: 4500.49 | P82: 7567.39 | Q82: 1268.19 | R82: 220.56 | S82: 627.71 | T82: 953.29 | U82: 11.69 | V82: 811.18 | W82: 1236.63 | X82: 6745.37 | Y82: 23942.5 | Z82: 17848.89 | AA82: 41791.39
A83: Gondia | B83: 2016 | C83: 8992.36 | D83: 942.63 | F83: 0 | G83: 27435.73 | H83: 6705.41 | I83: 0 | J83: 2538.9 | K83: 0 | L83: 19146.15 | M83: 56769 | N83: 65761 | O83: 4132.06 | P83: 7571.83 | Q83: 2572.05 | R83: 82.68 | S83: 899.73 | T83: 751.1 | U83: 24.26 | V83: 705.48 | W83: 1462.59 | X83: 5352.36 | Y83: 23554.14 | Z83: 20128.82 | AA83: 43682.96
A84: Gondia | B84: 2017 | C84: 22078.22 | D84: 421.45 | F84: 0 | G84: 25662.44 | H84: 2441.1 | I84: 0 | J84: 2230.51 | K84: 0 | L84: 2615.32 | M84: 33371 | N84: 55449 | O84: 3545.15 | P84: 9310.32 | Q84: 5314.63 | R84: 3407.89 | S84: 627.37 | T84: 644.93 | U84: 30.01 | V84: 2327.23 | W84: 1390.47 | X84: 9645.81 | Y84: 36243.81 | Z84: 3426.87 | AA84: 39670.68
A85: Gondia | B85: 2018 | C85: 15778.36 | D85: 463.6 | F85: 0 | G85: 28228.68 | H85: 2685.21 | I85: 0 | J85: 2453.56 | K85: 0 | L85: 2876.85 | M85: 36708 | N85: 52486 | O85: 3899.66 | P85: 10241.35 | Q85: 5846.09 | R85: 3748.68 | S85: 690.11 | T85: 709.42 | U85: 33.01 | V85: 2559.95 | W85: 1529.52 | X85: 6902.72 | Y85: 36160.51 | Z85: 4729.32 | AA85: 40889.83
A86: Gondia | B86: 2019 | C86: 11596.43 | D86: 418.8 | F86: 0 | G86: 41205.62 | H86: 4572.65 | I86: 0 | J86: 3430.51 | K86: 0 | L86: 3815.34 | M86: 53443 | N86: 65039 | O86: 5219.99 | P86: 7524.81 | Q86: 5704.05 | R86: 4479.54 | S86: 553.42 | T86: 425.24 | U86: 29.45 | V86: 4711.35 | W86: 1335.7 | X86: 15523.88 | Y86: 45507.43 | Z86: 4586.51 | AA86: 50093.94
A87: Gondia | B87: 2020 | C87: 102198.03 | D87: 18048.97 | F87: 0 | G87: 513283.76 | H87: 62345.08 | I87: 0 | J87: 37610.07 | K87: 0 | L87: 98216.15 | M87: 729504 | N87: 831702 | O87: 15585.58 | P87: 14419.4 | Q87: 75129.21 | R87: 11697.49 | S87: 58259.7 | T87: 19958.7 | U87: 6230 | V87: 396692.4 | W87: 11557.74 | X87: 16009 | Y87: 625539.22 | Z87: 7337.09 | AA87: 632876.31
A88: Gondia | B88: 2021 | C88: 208010.29 | D88: 17980.3 | F88: 0 | G88: 538147.08 | H88: 65358.48 | I88: 0 | J88: 76486.3 | K88: 0 | L88: 88326.2 | M88: 786298 | N88: 994309 | O88: 23468.45 | P88: 56823.76 | Q88: 79186.28 | R88: 58609.63 | S88: 64569 | T88: 21234.34 | U88: 8120 | V88: 447351.59 | W88: 72214 | X88: 14751.49 | Y88: 846328.54 | Z88: 9834.75 | AA88: 856163.29
A89: Hingoli | B89: 2012 | C89: 9364.35 | D89: 844.05 | E89: 0 | F89: 17325.68 | G89: 3328.98 | H89: 5901.11 | I89: 73.89 | J89: 1111.71 | K89: 83.18 | L89: 27824.23 | M89: 56493 | N89: 65857 | O89: 2577.06 | P89: 19985.51 | Q89: 438.51 | R89: 557.63 | S89: 909.67 | T89: 170.58 | U89: 0 | V89: 1581.23 | W89: 1466.61 | X89: 28934.66 | Y89: 56621.46 | Z89: 1617.21 | AA89: 58238.67
A90: Hingoli | B90: 2013 | C90: 6948.3 | D90: 1115.34 | E90: 0 | F90: 19074.79 | G90: 4550.91 | H90: 9205.23 | I90: 2066.32 | J90: 1713.67 | K90: 152.72 | L90: 228.98 | M90: 38108 | N90: 45056 | O90: 3082.95 | P90: 21570.16 | Q90: 286.29 | R90: 570 | S90: 72.18 | T90: 541.03 | U90: 0 | V90: 1735.52 | W90: 1581.44 | X90: 4504.76 | Y90: 33944.33 | Z90: 1368.4 | AA90: 35312.73
A91: Hingoli | B91: 2014 | C91: 9743.53 | D91: 773.42 | E91: 0 | F91: 27528.58 | G91: 3682.97 | H91: 6902.3 | I91: 0 | J91: 1664.62 | K91: 0 | L91: 430.63 | M91: 40983 | N91: 50726 | O91: 3910.94 | P91: 22929.2 | Q91: 442.65 | R91: 514.33 | S91: 489.26 | T91: 457.75 | U91: 1.87 | V91: 2315.99 | W91: 2091 | X91: 7885.04 | Y91: 41038.03 | Z91: 705.08 | AA91: 41743.11
A92: Hingoli | B92: 2015 | C92: 8982.94 | D92: 665.55 | E92: 0 | F92: 23245.72 | G92: 6509.64 | H92: 9886.93 | I92: 0 | J92: 2666.13 | K92: 0 | L92: 693.47 | M92: 43667 | N92: 52650 | O92: 4266.22 | P92: 23469.99 | Q92: 526.86 | R92: 413.09 | S92: 831.08 | T92: 649.59 | U92: 1.91 | V92: 1567.19 | W92: 1662.89 | X92: 6010.96 | Y92: 39399.78 | Z92: 612.63 | AA92: 40012.41
A93: Hingoli | B93: 2016 | C93: 12637.98 | D93: 557.16 | E93: 0 | F93: 29798.94 | G93: 6231.88 | H93: 9136.46 | I93: 0 | J93: 2801.53 | K93: 0 | L93: 310.7 | M93: 48837 | N93: 61475 | O93: 4321.8 | P93: 28000.8 | Q93: 1917.82 | R93: 981.59 | S93: 612.54 | T93: 709.71 | U93: 1.91 | V93: 2026.6 | W93: 2929.61 | X93: 5412.09 | Y93: 46914.47 | Z93: 361.72 | AA93: 47276.19
A94: Hingoli | B94: 2017 | C94: 14198.47 | D94: 898.24 | E94: 0 | F94: 32493.14 | G94: 7106.3 | H94: 12343.15 | I94: 0 | J94: 2396.52 | K94: 0 | L94: 275.36 | M94: 55513 | N94: 69711 | O94: 4637.5 | P94: 27531.28 | Q94: 2482.61 | R94: 868.29 | S94: 830.77 | T94: 710.21 | U94: 0 | V94: 1562.9 | W94: 2281.99 | X94: 16826.99 | Y94: 57732.54 | Z94: 334.1 | AA94: 58066.64
A95: Hingoli | B95: 2018 | C95: 11644.81 | D95: 1306.5 | E95: 0 | F95: 29706.21 | G95: 9242.6 | H95: 18085.8 | I95: 0 | J95: 3423.88 | K95: 0 | L95: 691.06 | M95: 62456 | N95: 74101 | O95: 5202.78 | P95: 28570.59 | Q95: 2418.76 | R95: 610.99 | S95: 1161.76 | T95: 622.61 | U95: 0 | V95: 1655.65 | W95: 4068.75 | X95: 12668.8 | Y95: 56980.69 | Z95: 836.05 | AA95: 57816.74
A96: Hingoli | B96: 2019 | C96: 16284.14 | D96: 1464.26 | E96: 0 | F96: 37000.33 | G96: 11691.69 | H96: 15364.41 | I96: 0 | J96: 4305.24 | K96: 0 | L96: 846.61 | M96: 70673 | N96: 86957 | O96: 7322.07 | P96: 37401.14 | Q96: 4227.81 | R96: 484.36 | S96: 1299.41 | T96: 839.77 | U96: 0 | V96: 2595.05 | W96: 3179.23 | X96: 12497.67 | Y96: 69846.51 | Z96: 1106.66 | AA96: 70953.17
A97: Hingoli | B97: 2020 | C97: 16004.18 | D97: 1203.12 | E97: 0 | F97: 37571.44 | G97: 13040.43 | H97: 18696.18 | I97: 0 | J97: 4634.32 | K97: 0 | L97: 957.55 | M97: 76103 | N97: 92107 | O97: 6715.65 | P97: 38273.8 | Q97: 3400.69 | R97: 568.97 | S97: 2182.84 | T97: 1129.62 | U97: 0 | V97: 2934.84 | W97: 2556.95 | X97: 16116.2 | Y97: 73879.56 | Z97: 365.24 | AA97: 74244.8
A98: Hingoli | B98: 2021 | C98: 17862.41 | D98: 849.73 | E98: 0 | F98: 36769.44 | G98: 12238.43 | H98: 22718.12 | I98: 0 | J98: 4480.2 | K98: 0 | L98: 940.34 | M98: 77996 | N98: 95859 | O98: 7959.3 | P98: 39829.07 | Q98: 3810.89 | R98: 656.69 | S98: 1897.1 | T98: 870.66 | U98: 0 | V98: 4185.99 | W98: 2960.7 | X98: 11719.28 | Y98: 73889.68 | Z98: 405.19 | AA98: 74294.87
A99: Jalna | B99: 2013 | C99: 20126.39 | D99: 4874.69 | F99: 0 | G99: 7536.59 | H99: 11018.63 | I99: 35612.22 | J99: 9649.4 | K99: 660.62 | L99: 314.72 | M99: 69667 | N99: 89793 | O99: 5803.69 | P99: 28103.34 | Q99: 10986.12 | R99: 620.94 | S99: 826.2 | T99: 664.18 | U99: 0 | V99: 3279.51 | W99: 1838.89 | X99: 5971.68 | Y99: 58094.55 | Z99: 3824.49 | AA99: 61919.04
A100: Jalna | B100: 2014 | C100: 27874.22 | D100: 2475.38 | F100: 0 | G100: 8636.15 | H100: 20713.21 | I100: 34808.08 | J100: 3475.72 | K100: 8551.11 | L100: 6385.56 | M100: 85045 | N100: 112919 | O100: 6238.55 | P100: 33523.26 | Q100: 11406.41 | R100: 33.48 | S100: 153 | T100: 36.51 | U100: 0 | V100: 4594.49 | W100: 810.6 | X100: 69465.17 | Y100: 126261.47 | Z100: 1390.13 | AA100: 127651.6
A101: Jalna | B101: 2015 | C101: 26922.48 | D101: 1127.68 | F101: 0 | G101: 9070.03 | H101: 21197.59 | I101: 38025.95 | J101: 577.64 | K101: 6274.91 | L101: 1596.03 | M101: 77870 | N101: 104792 | O101: 6562.52 | P101: 33776.95 | Q101: 3263.94 | R101: 0 | S101: 2116.63 | T101: 0 | U101: 0 | V101: 13436.47 | W101: 3270.01 | X101: 5853.71 | Y101: 68280.23 | Z101: 7703.23 | AA101: 75983.46
A102: Jalna | B102: 2016 | C102: 30221.64 | D102: 591.61 | F102: 0 | G102: 3396.36 | H102: 16408.83 | I102: 57881.44 | J102: 0 | K102: 2276.51 | L102: 1200.09 | M102: 81755 | N102: 111976 | O102: 7635.82 | P102: 38955.78 | Q102: 6118.78 | R102: 1548.52 | S102: 1395.34 | T102: 994.85 | U102: 0 | V102: 15283.89 | W102: 3229.37 | X102: 2705.6 | Y102: 77867.95 | Z102: 6791.99 | AA102: 84659.94
A103: Jalna | B103: 2017 | C103: 27319.54 | D103: 959.33 | F103: 0 | G103: 54732.72 | H103: 7258.48 | I103: 15375.25 | J103: 0 | K103: 1009.42 | L103: 3867.87 | M103: 83203 | N103: 110523 | O103: 7962.28 | P103: 39887.74 | Q103: 2506.56 | R103: 917.09 | S103: 597.11 | T103: 991.75 | U103: 0 | V103: 4539.36 | W103: 2642.34 | X103: 11404.37 | Y103: 71448.6 | Z103: 2569.44 | AA103: 74018.04
A104: Jalna | B104: 2018 | C104: 36504.56 | D104: 1958.12 | F104: 0 | G104: 68684.8 | H104: 3942.8 | I104: 5845.68 | J104: 0 | K104: 775.7 | L104: 4181.87 | M104: 85389 | N104: 121894 | O104: 8538.13 | P104: 40493.03 | Q104: 5222.01 | R104: 1079.89 | S104: 2070.21 | T104: 903.28 | U104: 0 | V104: 4718.1 | W104: 2917.5 | X104: 9285.79 | Y104: 75227.94 | Z104: 3915.75 | AA104: 79143.69
A105: Jalna | B105: 2019 | C105: 42749.84 | D105: 361.46 | F105: 0 | G105: 79899.26 | H105: 3992.22 | I105: 3502.31 | J105: 4974.92 | K105: 428.29 | L105: 6247.17 | M105: 99406 | N105: 142155 | O105: 11525.97 | P105: 54115.65 | Q105: 5638.33 | R105: 7132.41 | S105: 2298.02 | T105: 1151.76 | U105: 0 | V105: 5478.89 | W105: 4388.35 | X105: 7537.09 | Y105: 99266.47 | Z105: 5837.12 | AA105: 105103.59
A106: Jalna | B106: 2020 | C106: 37051.89 | D106: 1393.86 | F106: 0 | G106: 79202.6 | H106: 4659.25 | I106: 8289.7 | J106: 4929.23 | K106: 686.04 | L106: 3668.58 | M106: 102829 | N106: 139881 | O106: 12079.26 | P106: 52655.65 | Q106: 11907.61 | R106: 8175.59 | S106: 1434.83 | T106: 1157.3 | U106: 0 | V106: 6036.89 | W106: 2458.82 | X106: 1117.15 | Y106: 97023.1 | Z106: 3903.13 | AA106: 100926.23
A107: Latur | B107: 2007 | C107: 5693 | F107: 17837.93 | G107: 1553.93 | H107: 2198.12 | I107: 118.91 | J107: 3609 | K107: 1181.31 | L107: 4497.87 | M107: 30997 | N107: 36690 | O107: 1881.18 | P107: 14367.89 | Q107: 2700.09 | R107: 601.77 | S107: 704.89 | T107: 462.6 | U107: - | V107: 3042.15 | W107: 1748.02 | X107: 5461.14 | Y107: 30969.73 | Z107: 249.46 | AA107: 31219.19
A108: Latur | B108: 2008 | C108: 5470.86 | F108: 24149.45 | H108: 8968.63 | I108: 214.97 | J108: 4140.23 | K108: 4520.84 | L108: 1587.36 | M108: 43581 | N108: 49052 | O108: 2415.7 | P108: 17157.44 | Q108: 2904.5 | R108: 1833.34 | S108: 594.16 | T108: 477.44 | U108: - | V108: 5735.31 | W108: 5014.77 | X108: 5234.67 | Y108: 41367.33 | Z108: 353.7 | AA108: 41721.03
A109: Latur | B109: 2009 | C109: 7331.31 | E109: 217.88 | F109: 32530.1 | H109: 542.1 | I109: 5174.14 | J109: 2993.27 | K109: 3980.07 | L109: 352.7 | M109: 45790 | N109: 53122 | O109: 3494.32 | P109: 23998.52 | Q109: 2968.99 | R109: 1436.91 | S109: 517.29 | T109: 601.12 | U109: 0.49 | V109: 6353.19 | W109: 3702.29 | X109: 4256.14 | Y109: 47329.26 | Z109: 373.18 | AA109: 47702.44
A110: Latur | B110: 2010 | C110: 5219.13 | D110: 571.22 | F110: 38538.43 | H110: 6141.78 | I110: 1248.53 | J110: 3058.43 | K110: 2431.18 | L110: 300.48 | M110: 52290 | N110: 57509 | O110: 4110.4 | P110: 28530.59 | Q110: 3154.71 | R110: 689.11 | S110: 536.21 | T110: 754.16 | V110: 6034.38 | W110: 3551.85 | X110: 2584.36 | Y110: 49945.77 | Z110: 351.28 | AA110: 50297.05
A111: Latur | B111: 2011 | C111: 7212.13 | D111: 540.88 | F111: 43256.32 | H111: 6199.24 | I111: 743.19 | J111: 2415.89 | K111: 46308.99 | L111: 378.9 | M111: 99843 | N111: 107056 | O111: 4522.31 | P111: 32087.47 | Q111: 3606.15 | R111: 845.4 | S111: 616.2 | T111: 778.5 | V111: 3236.9 | W111: 3937.62 | X111: 49515.99 | Y111: 99146.54 | Z111: 321 | AA111: 99467.54
A112: Latur | B112: 2012 | C112: 7588 | D112: 1219.97 | F112: 48639.05 | H112: 9327.94 | I112: 590.71 | J112: 3249.2 | K112: 6241.59 | L112: 47654.59 | M112: 116923 | N112: 124511 | O112: 5169.33 | P112: 35484.44 | Q112: 4049.11 | R112: 722.93 | S112: 957.95 | T112: 1145.08 | U112: 0 | V112: 3413.3 | W112: 4921.53 | X112: 57789.81 | Y112: 113653.48 | Z112: 492.95 | AA112: 114146.43
A113: Latur | B113: 2013 | C113: 10365 | D113: 2177.58 | F113: 55247.47 | H113: 6713.99 | I113: 366.82 | J113: 3004.75 | K113: 60705.29 | L113: 682.98 | M113: 128899 | N113: 139264 | O113: 6109.15 | P113: 39993.9 | Q113: 4277.67 | R113: 637.05 | S113: 705.5 | T113: 1189.77 | U113: 0 | V113: 3633.9 | W113: 5272.57 | X113: 63471.32 | Y113: 125290.83 | Z113: 362.78 | AA113: 125653.61
A114: Latur | B114: 2014 | C114: 13609 | D114: 1288.13 | F114: 54356.98 | H114: 6035.77 | I114: 384.15 | J114: 2927.43 | K114: 65857 | L114: 580.46 | M114: 131430 | N114: 145039 | O114: 7140.16 | P114: 40939.88 | Q114: 5284.62 | R114: 367.76 | S114: 847.02 | T114: 1441.27 | V114: 4313.46 | W114: 5306.67 | X114: 65145.91 | Y114: 130786.75 | Z114: 358.05 | AA114: 131144.8
A115: Latur | B115: 2015 | C115: 13895.04 | D115: 964.98 | F115: 12732.94 | G115: 0 | H115: 61873.42 | I115: 354.02 | J115: 5056.97 | K115: 60966 | L115: 707.26 | M115: 1,42,655.59 | N115: 1,56,550.63 | O115: 7772.61 | P115: 45070.5 | Q115: 3661.21 | R115: 731.32 | S115: 944.87 | T115: 1220.67 | U115: 0 | V115: 6834.65 | W115: 5702.48 | X115: 66969.99 | Y115: 1,38,908.30 | Z115: 748.98 | AA115: 1,39,657.28
A116: Latur | B116: 2016 | C116: 16893.35 | D116: 717.93 | F116: 14268.51 | G116: 0 | H116: 55807.49 | I116: 400.33 | J116: 3915.73 | K116: 58064.01 | L116: 1030.7 | M116: 1,34,204.70 | N116: 1,51,098.05 | O116: 8145.03 | P116: 46451.18 | Q116: 3383.67 | R116: 864.67 | S116: 914.07 | T116: 1495.69 | U116: 0 | V116: 2721.7 | W116: 9159.55 | X116: 58636.26 | Y116: 1,31,771.82 | Z116: 405.79 | AA116: 1,32,177.61
...

Sheet Banking Sector (DSA)
A1: Year | B1: District | C1: Taluka | D1: Towns and cities where banks have offices | E1: Number of classified banks | F1: Number of branch offices of classified banks | G1: Deposits | H1: Agriculture Loans | I1: Non-Agriculture Loans | J1: Total Loan
A2: 2012 | B2: Ahmadnagar | C2: Akole | D2: 24 | E2: 5 | F2: 33 | G2: 58781 | H2: 33998 | I2: 38423 | J2: 72421
A3: 2012 | B3: Ahmadnagar | C3: Sangamner | D3: 37 | E3: 21 | F3: 72 | G3: 94076 | H3: 39976 | I3: 39263 | J3: 79239
A4: 2012 | B4: Ahmadnagar | C4: Kopargaon | D4: 24 | E4: 13 | F4: 40 | G4: 77544 | H4: 44032 | I4: 44304 | J4: 88336
A5: 2012 | B5: Ahmadnagar | C5: Rahata | D5: 28 | E5: 19 | F5: 47 | G5: 114413 | H5: 34491 | I5: 37470 | J5: 71961
A6: 2012 | B6: Ahmadnagar | C6: Srirampur | D6: 20 | E6: 14 | F6: 35 | G6: 64685 | H6: 40578 | I6: 39375 | J6: 79953
A7: 2012 | B7: Ahmadnagar | C7: Nevasa | D7: 28 | E7: 7 | F7: 43 | G7: 43823 | H7: 30104 | I7: 34222 | J7: 64326
A8: 2012 | B8: Ahmadnagar | C8: Shevgaon | D8: 19 | E8: 4 | F8: 29 | G8: 39231 | H8: 35754 | I8: 39207 | J8: 74961
A9: 2012 | B9: Ahmadnagar | C9: Pathardi | D9: 19 | E9: 9 | F9: 28 | G9: 59306 | H9: 35752 | I9: 37582 | J9: 73334
A10: 2012 | B10: Ahmadnagar | C10: Nagar | D10: 33 | E10: 28 | F10: 97 | G10: 525095 | H10: 59386 | I10: 56458 | J10: 115844
A11: 2012 | B11: Ahmadnagar | C11: Rahuri | D11: 31 | E11: 9 | F11: 41 | G11: 59306 | H11: 40577 | I11: 40047 | J11: 80624
A12: 2012 | B12: Ahmadnagar | C12: Parner | D12: 26 | E12: 4 | F12: 39 | G12: 41068 | H12: 35039 | I12: 37526 | J12: 72565
A13: 2012 | B13: Ahmadnagar | C13: Srigonda | D13: 30 | E13: 9 | F13: 37 | G13: 59175 | H13: 39700 | I13: 39319 | J13: 79019
... A141: 2021 | B141: Ahmadnagar | C141: Jamkhed | D141: 14 | E141: 7 | F141: 20 | G141: 143527 | H141: 107268 | I141: 105469 | J141: 212737
A143: 2012 | B143: Akola | C143: Telhara | D143: 20 | E143: 8 | F143: 20 | J143: 0
A144: 2012 | B144: Akola | C144: Akot | D144: 24 | E144: 11 | F144: 24 | J144: 0
A145: 2012 | B145: Akola | C145: Balapur | D145: 19 | E145: 6 | F145: 19 | J145: 0
A146: 2012 | B146: Akola | C146: Akola | D146: 84 | E146: 20 | F146: 84 | J146: 0
A147: 2012 | B147: Akola | C147: Murtijapur | D147: 16 | E147: 9 | F147: 16 | J147: 0
A148: 2012 | B148: Akola | C148: Patur | D148: 11 | E148: 2 | F148: 11 | J148: 0
A149: 2012 | B149: Akola | C149: Barshitakali | D149: 12 | E149: 4 | F149: 12 | J149: 0
A150: 2013 | B150: Akola | C150: Telhara | D150: 20 | E150: 8 | F150: 13 | J150: 0
A151: 2013 | B151: Akola | C151: Akot | D151: 24 | E151: 9 | F151: 20 | J151: 0
A152: 2013 | B152: Akola | C152: Balapur | D152: 19 | E152: 7 | F152: 12 | J152: 0
A153: 2013 | B153: Akola | C153: Akola | D153: 84 | E153: 26 | F153: 65 | J153: 0
A154: 2013 | B154: Akola | C154: Murtijapur | D154: 16 | E154: 5 | F154: 15 | J154: 0
... A163: 2014 | B163: Akola | C163: Barshitakali | D163: 12 | E163: 5 | F163: 12 | J163: 0
A164: 2015
A165: 2016 | B165: Akola | C165: Telhara | D165: 20 | E165: 12 | F165: 20 | J165: 0
A166: 2016 | B166: Akola | C166: Akot | D166: 33 | E166: 19 | F166: 33 | J166: 0
A167: 2016 | B167: Akola | C167: Balapur | D167: 21 | E167: 14 | F167: 21 | J167: 0
A168: 2016 | B168: Akola | C168: Akola | D168: 99 | E168: 65 | F168: 99 | J168: 0
A169: 2016 | B169: Akola | C169: Murtijapur | D169: 21 | E169: 15 | F169: 21 | J169: 0
A170: 2016 | B170: Akola | C170: Patur | D170: 12 | E170: 7 | F170: 12 | J170: 0
